Workbook

Sheet Cómo usar
B1: Qi Snacks · Calculadora de costos y precios
B2: Compras → Recetas → Producto terminado → Precio de venta
B4: Paso a paso
B5: 1. Insumos | C5: Lista de todo lo que comprás: ingredientes, bolsas, etiquetas y productos de reventa. Ya están cargados los ingredientes de la web. Para cada uno indicá la unidad base: g (sólidos), ml (líquidos) o unidad.
B6: 2. Compras | C6: Cada vez que comprás algo, agregá una fila: fecha, insumo, cantidad, unidad (kg, g, l, ml, unidad…) y precio total pagado. La planilla convierte todo y calcula el costo por gramo / ml / unidad.
B7: 3. Recetas | C7: Para cada receta, una fila por ingrediente con la cantidad que usás en UNA tanda. Ya están cargados los ingredientes de cada producto: solo falta completar las cantidades (columna amarilla).
B8: 4. Costo por Receta | C8: Pesá el producto terminado que sale de cada tanda (después del horno) y cargalo como rendimiento. Así se obtiene el costo real por gramo.
B9: 5. Precios | C9: Cada producto y presentación (individual / familiar). Elegís receta, gramos por paquete, envase y etiqueta. Te muestra el COSTO TOTAL, el PRECIO SUGERIDO y el margen real con el precio que cobrás hoy.
B10: 6. Combos | C10: Combo Degustación y Promo del Recreo: suma los costos de los productos que llevan, más extras (juguete, caja), y muestra el margen y el descuento frente a comprarlos sueltos.
B11: Configuración | C11: Margen deseado, % de gastos indirectos (gas, luz, tu tiempo), método de precio (último o promedio) y redondeo. Cambiar un valor actualiza todo.
B13: Colores
B14: Texto azul / fondo amarillo | C14: Celdas para completar o modificar.
B15: Texto negro / fondo gris | C15: Fórmulas: se calculan solas, no hace falta tocarlas.
B16: Texto verde | C16: Fórmula que trae un dato de otra hoja.
B17: Fondo naranja claro | C17: DATOS DE EJEMPLO (Galletas Marineras y sus compras). Reemplazalos por tus datos reales.
B19: Cómo se calcula
B20: Costo por gramo de insumo | C20: Precio total pagado ÷ cantidad comprada (pasada a g, ml o unidades).
B21: Costo de la receta | C21: Suma de (cantidad de cada ingrediente × su costo por gramo).
B22: Costo por gramo terminado | C22: Costo de la receta ÷ gramos de producto terminado que rinde la tanda.
B23: Costo del paquete | C23: Gramos del paquete × costo por gramo terminado + envase + etiqueta + % gastos indirectos.
B24: Precio sugerido | C24: Costo del paquete ÷ (1 − margen). Con 60% de margen, el precio es 2,5 veces el costo.
B26: Columnas Control / Estado | C26: Avisan qué falta ("Falta cantidad", "Insumo sin compras", "Falta rendimiento", "Unidad incompatible"…). Cuando todo dice OK, el costo de ese producto está completo.
B27: Agregar cosas nuevas | C27: Insumo nuevo → hoja Insumos. Receta nueva → nombre en Costo por Receta y sus ingredientes en Recetas. Producto o presentación nueva → hoja Precios. Escribilo en la primera fila vacía, sin dejar filas en blanco en el medio: así aparece solo en las listas desplegables.

Sheet Insumos
A1: Insumos: ingredientes, packaging y reventa
A2: Lista maestra. Cargá acá cada cosa que comprás (una sola vez). Los costos se calculan solos desde la hoja Compras.
A4: Insumo | B4: Tipo | C4: Unidad base | D4: Fecha última compra | E4: Costo último ($ por unidad base) | F4: Costo promedio ($ por unidad base) | G4: Costo que se usa ($ por unidad base) | H4: Costo por kg / litro / unidad | I4: Estado
A5: Aceite de oliva | B5: Ingrediente | C5: ml | D5: =IF(A5="","",IF(COUNTIFS(Compras!$B$5:$B$2000,A5,Compras!$H$5:$H$2000,">0")=0,"",_xlfn.MAXIFS(Compras!$A$5:$A$2000,Compras!$B$5:$B$2000,A5,Compras!$H$5:$H$2000,">0"))) -> 46280 | E5: =IF(D5="","",SUMIFS(Compras!$H$5:$H$2000,Compras!$B$5:$B$2000,A5,Compras!$A$5:$A$2000,D5,Compras!$H$5:$H$2000,">0")/COUNTIFS(Compras!$B$5:$B$2000,A5,Compras!$A$5:$A$2000,D5,Compras!$H$5:$H$2000,">0")) -> 18 | F5: =IF(D5="","",SUMIFS(Compras!$F$5:$F$2000,Compras!$B$5:$B$2000,A5,Compras!$H$5:$H$2000,">0")/SUMIFS(Compras!$G$5:$G$2000,Compras!$B$5:$B$2000,A5,Compras!$H$5:$H$2000,">0")) -> 17.25 | G5: =IF(D5="","",IF(CFG_Metodo="Promedio",F5,E5)) -> 18 | H5: =IF(G5="","",IF(C5="unidad",G5,G5*1000)) -> 18000 | I5: =IF(A5="","",IF(C5="","Falta unidad base",IF(D5="","Sin compras cargadas","OK"))) -> OK
A6: Ajo en polvo | B6: Ingrediente | C6: g | D6: =IF(A6="","",IF(COUNTIFS(Compras!$B$5:$B$2000,A6,Compras!$H$5:$H$2000,">0")=0,"",_xlfn.MAXIFS(Compras!$A$5:$A$2000,Compras!$B$5:$B$2000,A6,Compras!$H$5:$H$2000,">0"))) | E6: =IF(D6="","",SUMIFS(Compras!$H$5:$H$2000,Compras!$B$5:$B$2000,A6,Compras!$A$5:$A$2000,D6,Compras!$H$5:$H$2000,">0")/COUNTIFS(Compras!$B$5:$B$2000,A6,Compras!$A$5:$A$2000,D6,Compras!$H$5:$H$2000,">0")) | F6: =IF(D6="","",SUMIFS(Compras!$F$5:$F$2000,Compras!$B$5:$B$2000,A6,Compras!$H$5:$H$2000,">0")/SUMIFS(Compras!$G$5:$G$2000,Compras!$B$5:$B$2000,A6,Compras!$H$5:$H$2000,">0")) | G6: =IF(D6="","",IF(CFG_Metodo="Promedio",F6,E6)) | H6: =IF(G6="","",IF(C6="unidad",G6,G6*1000)) | I6: =IF(A6="","",IF(C6="","Falta unidad base",IF(D6="","Sin compras cargadas","OK"))) -> Sin compras cargadas
A7: Almidón de maíz | B7: Ingrediente | C7: g | D7: =IF(A7="","",IF(COUNTIFS(Compras!$B$5:$B$2000,A7,Compras!$H$5:$H$2000,">0")=0,"",_xlfn.MAXIFS(Compras!$A$5:$A$2000,Compras!$B$5:$B$2000,A7,Compras!$H$5:$H$2000,">0"))) -> 46267 | E7: =IF(D7="","",SUMIFS(Compras!$H$5:$H$2000,Compras!$B$5:$B$2000,A7,Compras!$A$5:$A$2000,D7,Compras!$H$5:$H$2000,">0")/COUNTIFS(Compras!$B$5:$B$2000,A7,Compras!$A$5:$A$2000,D7,Compras!$H$5:$H$2000,">0")) -> 3 | F7: =IF(D7="","",SUMIFS(Compras!$F$5:$F$2000,Compras!$B$5:$B$2000,A7,Compras!$H$5:$H$2000,">0")/SUMIFS(Compras!$G$5:$G$2000,Compras!$B$5:$B$2000,A7,Compras!$H$5:$H$2000,">0")) -> 3 | G7: =IF(D7="","",IF(CFG_Metodo="Promedio",F7,E7)) -> 3 | H7: =IF(G7="","",IF(C7="unidad",G7,G7*1000)) -> 3000 | I7: =IF(A7="","",IF(C7="","Falta unidad base",IF(D7="","Sin compras cargadas","OK"))) -> OK
A8: Almidón de mandioca | B8: Ingrediente | C8: g | D8: =IF(A8="","",IF(COUNTIFS(Compras!$B$5:$B$2000,A8,Compras!$H$5:$H$2000,">0")=0,"",_xlfn.MAXIFS(Compras!$A$5:$A$2000,Compras!$B$5:$B$2000,A8,Compras!$H$5:$H$2000,">0"))) -> 46267 | E8: =IF(D8="","",SUMIFS(Compras!$H$5:$H$2000,Compras!$B$5:$B$2000,A8,Compras!$A$5:$A$2000,D8,Compras!$H$5:$H$2000,">0")/COUNTIFS(Compras!$B$5:$B$2000,A8,Compras!$A$5:$A$2000,D8,Compras!$H$5:$H$2000,">0")) -> 3.5 | F8: =IF(D8="","",SUMIFS(Compras!$F$5:$F$2000,Compras!$B$5:$B$2000,A8,Compras!$H$5:$H$2000,">0")/SUMIFS(Compras!$G$5:$G$2000,Compras!$B$5:$B$2000,A8,Compras!$H$5:$H$2000,">0")) -> 3.5 | G8: =IF(D8="","",IF(CFG_Metodo="Promedio",F8,E8)) -> 3.5 | H8: =IF(G8="","",IF(C8="unidad",G8,G8*1000)) -> 3500 | I8: =IF(A8="","",IF(C8="","Falta unidad base",IF(D8="","Sin compras cargadas","OK"))) -> OK
A9: Azúcar de coco | B9: Ingrediente | C9: g | D9: =IF(A9="","",IF(COUNTIFS(Compras!$B$5:$B$2000,A9,Compras!$H$5:$H$2000,">0")=0,"",_xlfn.MAXIFS(Compras!$A$5:$A$2000,Compras!$B$5:$B$2000,A9,Compras!$H$5:$H$2000,">0"))) | E9: =IF(D9="","",SUMIFS(Compras!$H$5:$H$2000,Compras!$B$5:$B$2000,A9,Compras!$A$5:$A$2000,D9,Compras!$H$5:$H$2000,">0")/COUNTIFS(Compras!$B$5:$B$2000,A9,Compras!$A$5:$A$2000,D9,Compras!$H$5:$H$2000,">0")) | F9: =IF(D9="","",SUMIFS(Compras!$F$5:$F$2000,Compras!$B$5:$B$2000,A9,Compras!$H$5:$H$2000,">0")/SUMIFS(Compras!$G$5:$G$2000,Compras!$B$5:$B$2000,A9,Compras!$H$5:$H$2000,">0")) | G9: =IF(D9="","",IF(CFG_Metodo="Promedio",F9,E9)) | H9: =IF(G9="","",IF(C9="unidad",G9,G9*1000)) | I9: =IF(A9="","",IF(C9="","Falta unidad base",IF(D9="","Sin compras cargadas","OK"))) -> Sin compras cargadas
A10: Batata | B10: Ingrediente | C10: g | D10: =IF(A10="","",IF(COUNTIFS(Compras!$B$5:$B$2000,A10,Compras!$H$5:$H$2000,">0")=0,"",_xlfn.MAXIFS(Compras!$A$5:$A$2000,Compras!$B$5:$B$2000,A10,Compras!$H$5:$H$2000,">0"))) | E10: =IF(D10="","",SUMIFS(Compras!$H$5:$H$2000,Compras!$B$5:$B$2000,A10,Compras!$A$5:$A$2000,D10,Compras!$H$5:$H$2000,">0")/COUNTIFS(Compras!$B$5:$B$2000,A10,Compras!$A$5:$A$2000,D10,Compras!$H$5:$H$2000,">0")) | F10: =IF(D10="","",SUMIFS(Compras!$F$5:$F$2000,Compras!$B$5:$B$2000,A10,Compras!$H$5:$H$2000,">0")/SUMIFS(Compras!$G$5:$G$2000,Compras!$B$5:$B$2000,A10,Compras!$H$5:$H$2000,">0")) | G10: =IF(D10="","",IF(CFG_Metodo="Promedio",F10,E10)) | H10: =IF(G10="","",IF(C10="unidad",G10,G10*1000)) | I10: =IF(A10="","",IF(C10="","Falta unidad base",IF(D10="","Sin compras cargadas","OK"))) -> Sin compras cargadas
A11: Cebolla en polvo | B11: Ingrediente | C11: g | D11: =IF(A11="","",IF(COUNTIFS(Compras!$B$5:$B$2000,A11,Compras!$H$5:$H$2000,">0")=0,"",_xlfn.MAXIFS(Compras!$A$5:$A$2000,Compras!$B$5:$B$2000,A11,Compras!$H$5:$H$2000,">0"))) | E11: =IF(D11="","",SUMIFS(Compras!$H$5:$H$2000,Compras!$B$5:$B$2000,A11,Compras!$A$5:$A$2000,D11,Compras!$H$5:$H$2000,">0")/COUNTIFS(Compras!$B$5:$B$2000,A11,Compras!$A$5:$A$2000,D11,Compras!$H$5:$H$2000,">0")) | F11: =IF(D11="","",SUMIFS(Compras!$F$5:$F$2000,Compras!$B$5:$B$2000,A11,Compras!$H$5:$H$2000,">0")/SUMIFS(Compras!$G$5:$G$2000,Compras!$B$5:$B$2000,A11,Compras!$H$5:$H$2000,">0")) | G11: =IF(D11="","",IF(CFG_Metodo="Promedio",F11,E11)) | H11: =IF(G11="","",IF(C11="unidad",G11,G11*1000)) | I11: =IF(A11="","",IF(C11="","Falta unidad base",IF(D11="","Sin compras cargadas","OK"))) -> Sin compras cargadas
A12: Chocolate 70% sin azúcar | B12: Ingrediente | C12: g | D12: =IF(A12="","",IF(COUNTIFS(Compras!$B$5:$B$2000,A12,Compras!$H$5:$H$2000,">0")=0,"",_xlfn.MAXIFS(Compras!$A$5:$A$2000,Compras!$B$5:$B$2000,A12,Compras!$H$5:$H$2000,">0"))) | E12: =IF(D12="","",SUMIFS(Compras!$H$5:$H$2000,Compras!$B$5:$B$2000,A12,Compras!$A$5:$A$2000,D12,Compras!$H$5:$H$2000,">0")/COUNTIFS(Compras!$B$5:$B$2000,A12,Compras!$A$5:$A$2000,D12,Compras!$H$5:$H$2000,">0")) | F12: =IF(D12="","",SUMIFS(Compras!$F$5:$F$2000,Compras!$B$5:$B$2000,A12,Compras!$H$5:$H$2000,">0")/SUMIFS(Compras!$G$5:$G$2000,Compras!$B$5:$B$2000,A12,Compras!$H$5:$H$2000,">0")) | G12: =IF(D12="","",IF(CFG_Metodo="Promedio",F12,E12)) | H12: =IF(G12="","",IF(C12="unidad",G12,G12*1000)) | I12: =IF(A12="","",IF(C12="","Falta unidad base",IF(D12="","Sin compras cargadas","OK"))) -> Sin compras cargadas
A13: Cúrcuma | B13: Ingrediente | C13: g | D13: =IF(A13="","",IF(COUNTIFS(Compras!$B$5:$B$2000,A13,Compras!$H$5:$H$2000,">0")=0,"",_xlfn.MAXIFS(Compras!$A$5:$A$2000,Compras!$B$5:$B$2000,A13,Compras!$H$5:$H$2000,">0"))) | E13: =IF(D13="","",SUMIFS(Compras!$H$5:$H$2000,Compras!$B$5:$B$2000,A13,Compras!$A$5:$A$2000,D13,Compras!$H$5:$H$2000,">0")/COUNTIFS(Compras!$B$5:$B$2000,A13,Compras!$A$5:$A$2000,D13,Compras!$H$5:$H$2000,">0")) | F13: =IF(D13="","",SUMIFS(Compras!$F$5:$F$2000,Compras!$B$5:$B$2000,A13,Compras!$H$5:$H$2000,">0")/SUMIFS(Compras!$G$5:$G$2000,Compras!$B$5:$B$2000,A13,Compras!$H$5:$H$2000,">0")) | G13: =IF(D13="","",IF(CFG_Metodo="Promedio",F13,E13)) | H13: =IF(G13="","",IF(C13="unidad",G13,G13*1000)) | I13: =IF(A13="","",IF(C13="","Falta unidad base",IF(D13="","Sin compras cargadas","OK"))) -> Sin compras cargadas
A14: Extracto de vainilla | B14: Ingrediente | C14: ml | D14: =IF(A14="","",IF(COUNTIFS(Compras!$B$5:$B$2000,A14,Compras!$H$5:$H$2000,">0")=0,"",_xlfn.MAXIFS(Compras!$A$5:$A$2000,Compras!$B$5:$B$2000,A14,Compras!$H$5:$H$2000,">0"))) | E14: =IF(D14="","",SUMIFS(Compras!$H$5:$H$2000,Compras!$B$5:$B$2000,A14,Compras!$A$5:$A$2000,D14,Compras!$H$5:$H$2000,">0")/COUNTIFS(Compras!$B$5:$B$2000,A14,Compras!$A$5:$A$2000,D14,Compras!$H$5:$H$2000,">0")) | F14: =IF(D14="","",SUMIFS(Compras!$F$5:$F$2000,Compras!$B$5:$B$2000,A14,Compras!$H$5:$H$2000,">0")/SUMIFS(Compras!$G$5:$G$2000,Compras!$B$5:$B$2000,A14,Compras!$H$5:$H$2000,">0")) | G14: =IF(D14="","",IF(CFG_Metodo="Promedio",F14,E14)) | H14: =IF(G14="","",IF(C14="unidad",G14,G14*1000)) | I14: =IF(A14="","",IF(C14="","Falta unidad base",IF(D14="","Sin compras cargadas","OK"))) -> Sin compras cargadas
A15: Garbanzos | B15: Ingrediente | C15: g | D15: =IF(A15="","",IF(COUNTIFS(Compras!$B$5:$B$2000,A15,Compras!$H$5:$H$2000,">0")=0,"",_xlfn.MAXIFS(Compras!$A$5:$A$2000,Compras!$B$5:$B$2000,A15,Compras!$H$5:$H$2000,">0"))) | E15: =IF(D15="","",SUMIFS(Compras!$H$5:$H$2000,Compras!$B$5:$B$2000,A15,Compras!$A$5:$A$2000,D15,Compras!$H$5:$H$2000,">0")/COUNTIFS(Compras!$B$5:$B$2000,A15,Compras!$A$5:$A$2000,D15,Compras!$H$5:$H$2000,">0")) | F15: =IF(D15="","",SUMIFS(Compras!$F$5:$F$2000,Compras!$B$5:$B$2000,A15,Compras!$H$5:$H$2000,">0")/SUMIFS(Compras!$G$5:$G$2000,Compras!$B$5:$B$2000,A15,Compras!$H$5:$H$2000,">0")) | G15: =IF(D15="","",IF(CFG_Metodo="Promedio",F15,E15)) | H15: =IF(G15="","",IF(C15="unidad",G15,G15*1000)) | I15: =IF(A15="","",IF(C15="","Falta unidad base",IF(D15="","Sin compras cargadas","OK"))) -> Sin compras cargadas
A16: Goma xántica | B16: Ingrediente | C16: g | D16: =IF(A16="","",IF(COUNTIFS(Compras!$B$5:$B$2000,A16,Compras!$H$5:$H$2000,">0")=0,"",_xlfn.MAXIFS(Compras!$A$5:$A$2000,Compras!$B$5:$B$2000,A16,Compras!$H$5:$H$2000,">0"))) -> 46267 | E16: =IF(D16="","",SUMIFS(Compras!$H$5:$H$2000,Compras!$B$5:$B$2000,A16,Compras!$A$5:$A$2000,D16,Compras!$H$5:$H$2000,">0")/COUNTIFS(Compras!$B$5:$B$2000,A16,Compras!$A$5:$A$2000,D16,Compras!$H$5:$H$2000,">0")) -> 60 | F16: =IF(D16="","",SUMIFS(Compras!$F$5:$F$2000,Compras!$B$5:$B$2000,A16,Compras!$H$5:$H$2000,">0")/SUMIFS(Compras!$G$5:$G$2000,Compras!$B$5:$B$2000,A16,Compras!$H$5:$H$2000,">0")) -> 60 | G16: =IF(D16="","",IF(CFG_Metodo="Promedio",F16,E16)) -> 60 | H16: =IF(G16="","",IF(C16="unidad",G16,G16*1000)) -> 60000 | I16: =IF(A16="","",IF(C16="","Falta unidad base",IF(D16="","Sin compras cargadas","OK"))) -> OK
... A50: Berenjenas y Pera 200 g | B50: Reventa | C50: unidad | D50: =IF(A50="","",IF(COUNTIFS(Compras!$B$5:$B$2000,A50,Compras!$H$5:$H$2000,">0")=0,"",_xlfn.MAXIFS(Compras!$A$5:$A$2000,Compras!$B$5:$B$2000,A50,Compras!$H$5:$H$2000,">0"))) | E50: =IF(D50="","",SUMIFS(Compras!$H$5:$H$2000,Compras!$B$5:$B$2000,A50,Compras!$A$5:$A$2000,D50,Compras!$H$5:$H$2000,">0")/COUNTIFS(Compras!$B$5:$B$2000,A50,Compras!$A$5:$A$2000,D50,Compras!$H$5:$H$2000,">0")) | F50: =IF(D50="","",SUMIFS(Compras!$F$5:$F$2000,Compras!$B$5:$B$2000,A50,Compras!$H$5:$H$2000,">0")/SUMIFS(Compras!$G$5:$G$2000,Compras!$B$5:$B$2000,A50,Compras!$H$5:$H$2000,">0")) | G50: =IF(D50="","",IF(CFG_Metodo="Promedio",F50,E50)) | H50: =IF(G50="","",IF(C50="unidad",G50,G50*1000)) | I50: =IF(A50="","",IF(C50="","Falta unidad base",IF(D50="","Sin compras cargadas","OK"))) -> Sin compras cargadas
D51: =IF(A51="","",IF(COUNTIFS(Compras!$B$5:$B$2000,A51,Compras!$H$5:$H$2000,">0")=0,"",_xlfn.MAXIFS(Compras!$A$5:$A$2000,Compras!$B$5:$B$2000,A51,Compras!$H$5:$H$2000,">0"))) | E51: =IF(D51="","",SUMIFS(Compras!$H$5:$H$2000,Compras!$B$5:$B$2000,A51,Compras!$A$5:$A$2000,D51,Compras!$H$5:$H$2000,">0")/COUNTIFS(Compras!$B$5:$B$2000,A51,Compras!$A$5:$A$2000,D51,Compras!$H$5:$H$2000,">0")) | F51: =IF(D51="","",SUMIFS(Compras!$F$5:$F$2000,Compras!$B$5:$B$2000,A51,Compras!$H$5:$H$2000,">0")/SUMIFS(Compras!$G$5:$G$2000,Compras!$B$5:$B$2000,A51,Compras!$H$5:$H$2000,">0")) | G51: =IF(D51="","",IF(CFG_Metodo="Promedio",F51,E51)) | H51: =IF(G51="","",IF(C51="unidad",G51,G51*1000)) | I51: =IF(A51="","",IF(C51="","Falta unidad base",IF(D51="","Sin compras cargadas","OK")))
D52: =IF(A52="","",IF(COUNTIFS(Compras!$B$5:$B$2000,A52,Compras!$H$5:$H$2000,">0")=0,"",_xlfn.MAXIFS(Compras!$A$5:$A$2000,Compras!$B$5:$B$2000,A52,Compras!$H$5:$H$2000,">0"))) | E52: =IF(D52="","",SUMIFS(Compras!$H$5:$H$2000,Compras!$B$5:$B$2000,A52,Compras!$A$5:$A$2000,D52,Compras!$H$5:$H$2000,">0")/COUNTIFS(Compras!$B$5:$B$2000,A52,Compras!$A$5:$A$2000,D52,Compras!$H$5:$H$2000,">0")) | F52: =IF(D52="","",SUMIFS(Compras!$F$5:$F$2000,Compras!$B$5:$B$2000,A52,Compras!$H$5:$H$2000,">0")/SUMIFS(Compras!$G$5:$G$2000,Compras!$B$5:$B$2000,A52,Compras!$H$5:$H$2000,">0")) | G52: =IF(D52="","",IF(CFG_Metodo="Promedio",F52,E52)) | H52: =IF(G52="","",IF(C52="unidad",G52,G52*1000)) | I52: =IF(A52="","",IF(C52="","Falta unidad base",IF(D52="","Sin compras cargadas","OK")))
D53: =IF(A53="","",IF(COUNTIFS(Compras!$B$5:$B$2000,A53,Compras!$H$5:$H$2000,">0")=0,"",_xlfn.MAXIFS(Compras!$A$5:$A$2000,Compras!$B$5:$B$2000,A53,Compras!$H$5:$H$2000,">0"))) | E53: =IF(D53="","",SUMIFS(Compras!$H$5:$H$2000,Compras!$B$5:$B$2000,A53,Compras!$A$5:$A$2000,D53,Compras!$H$5:$H$2000,">0")/COUNTIFS(Compras!$B$5:$B$2000,A53,Compras!$A$5:$A$2000,D53,Compras!$H$5:$H$2000,">0")) | F53: =IF(D53="","",SUMIFS(Compras!$F$5:$F$2000,Compras!$B$5:$B$2000,A53,Compras!$H$5:$H$2000,">0")/SUMIFS(Compras!$G$5:$G$2000,Compras!$B$5:$B$2000,A53,Compras!$H$5:$H$2000,">0")) | G53: =IF(D53="","",IF(CFG_Metodo="Promedio",F53,E53)) | H53: =IF(G53="","",IF(C53="unidad",G53,G53*1000)) | I53: =IF(A53="","",IF(C53="","Falta unidad base",IF(D53="","Sin compras cargadas","OK")))
D54: =IF(A54="","",IF(COUNTIFS(Compras!$B$5:$B$2000,A54,Compras!$H$5:$H$2000,">0")=0,"",_xlfn.MAXIFS(Compras!$A$5:$A$2000,Compras!$B$5:$B$2000,A54,Compras!$H$5:$H$2000,">0"))) | E54: =IF(D54="","",SUMIFS(Compras!$H$5:$H$2000,Compras!$B$5:$B$2000,A54,Compras!$A$5:$A$2000,D54,Compras!$H$5:$H$2000,">0")/COUNTIFS(Compras!$B$5:$B$2000,A54,Compras!$A$5:$A$2000,D54,Compras!$H$5:$H$2000,">0")) | F54: =IF(D54="","",SUMIFS(Compras!$F$5:$F$2000,Compras!$B$5:$B$2000,A54,Compras!$H$5:$H$2000,">0")/SUMIFS(Compras!$G$5:$G$2000,Compras!$B$5:$B$2000,A54,Compras!$H$5:$H$2000,">0")) | G54: =IF(D54="","",IF(CFG_Metodo="Promedio",F54,E54)) | H54: =IF(G54="","",IF(C54="unidad",G54,G54*1000)) | I54: =IF(A54="","",IF(C54="","Falta unidad base",IF(D54="","Sin compras cargadas","OK")))
D55: =IF(A55="","",IF(COUNTIFS(Compras!$B$5:$B$2000,A55,Compras!$H$5:$H$2000,">0")=0,"",_xlfn.MAXIFS(Compras!$A$5:$A$2000,Compras!$B$5:$B$2000,A55,Compras!$H$5:$H$2000,">0"))) | E55: =IF(D55="","",SUMIFS(Compras!$H$5:$H$2000,Compras!$B$5:$B$2000,A55,Compras!$A$5:$A$2000,D55,Compras!$H$5:$H$2000,">0")/COUNTIFS(Compras!$B$5:$B$2000,A55,Compras!$A$5:$A$2000,D55,Compras!$H$5:$H$2000,">0")) | F55: =IF(D55="","",SUMIFS(Compras!$F$5:$F$2000,Compras!$B$5:$B$2000,A55,Compras!$H$5:$H$2000,">0")/SUMIFS(Compras!$G$5:$G$2000,Compras!$B$5:$B$2000,A55,Compras!$H$5:$H$2000,">0")) | G55: =IF(D55="","",IF(CFG_Metodo="Promedio",F55,E55)) | H55: =IF(G55="","",IF(C55="unidad",G55,G55*1000)) | I55: =IF(A55="","",IF(C55="","Falta unidad base",IF(D55="","Sin compras cargadas","OK")))
D56: =IF(A56="","",IF(COUNTIFS(Compras!$B$5:$B$2000,A56,Compras!$H$5:$H$2000,">0")=0,"",_xlfn.MAXIFS(Compras!$A$5:$A$2000,Compras!$B$5:$B$2000,A56,Compras!$H$5:$H$2000,">0"))) | E56: =IF(D56="","",SUMIFS(Compras!$H$5:$H$2000,Compras!$B$5:$B$2000,A56,Compras!$A$5:$A$2000,D56,Compras!$H$5:$H$2000,">0")/COUNTIFS(Compras!$B$5:$B$2000,A56,Compras!$A$5:$A$2000,D56,Compras!$H$5:$H$2000,">0")) | F56: =IF(D56="","",SUMIFS(Compras!$F$5:$F$2000,Compras!$B$5:$B$2000,A56,Compras!$H$5:$H$2000,">0")/SUMIFS(Compras!$G$5:$G$2000,Compras!$B$5:$B$2000,A56,Compras!$H$5:$H$2000,">0")) | G56: =IF(D56="","",IF(CFG_Metodo="Promedio",F56,E56)) | H56: =IF(G56="","",IF(C56="unidad",G56,G56*1000)) | I56: =IF(A56="","",IF(C56="","Falta unidad base",IF(D56="","Sin compras cargadas","OK")))
D57: =IF(A57="","",IF(COUNTIFS(Compras!$B$5:$B$2000,A57,Compras!$H$5:$H$2000,">0")=0,"",_xlfn.MAXIFS(Compras!$A$5:$A$2000,Compras!$B$5:$B$2000,A57,Compras!$H$5:$H$2000,">0"))) | E57: =IF(D57="","",SUMIFS(Compras!$H$5:$H$2000,Compras!$B$5:$B$2000,A57,Compras!$A$5:$A$2000,D57,Compras!$H$5:$H$2000,">0")/COUNTIFS(Compras!$B$5:$B$2000,A57,Compras!$A$5:$A$2000,D57,Compras!$H$5:$H$2000,">0")) | F57: =IF(D57="","",SUMIFS(Compras!$F$5:$F$2000,Compras!$B$5:$B$2000,A57,Compras!$H$5:$H$2000,">0")/SUMIFS(Compras!$G$5:$G$2000,Compras!$B$5:$B$2000,A57,Compras!$H$5:$H$2000,">0")) | G57: =IF(D57="","",IF(CFG_Metodo="Promedio",F57,E57)) | H57: =IF(G57="","",IF(C57="unidad",G57,G57*1000)) | I57: =IF(A57="","",IF(C57="","Falta unidad base",IF(D57="","Sin compras cargadas","OK")))
D58: =IF(A58="","",IF(COUNTIFS(Compras!$B$5:$B$2000,A58,Compras!$H$5:$H$2000,">0")=0,"",_xlfn.MAXIFS(Compras!$A$5:$A$2000,Compras!$B$5:$B$2000,A58,Compras!$H$5:$H$2000,">0"))) | E58: =IF(D58="","",SUMIFS(Compras!$H$5:$H$2000,Compras!$B$5:$B$2000,A58,Compras!$A$5:$A$2000,D58,Compras!$H$5:$H$2000,">0")/COUNTIFS(Compras!$B$5:$B$2000,A58,Compras!$A$5:$A$2000,D58,Compras!$H$5:$H$2000,">0")) | F58: =IF(D58="","",SUMIFS(Compras!$F$5:$F$2000,Compras!$B$5:$B$2000,A58,Compras!$H$5:$H$2000,">0")/SUMIFS(Compras!$G$5:$G$2000,Compras!$B$5:$B$2000,A58,Compras!$H$5:$H$2000,">0")) | G58: =IF(D58="","",IF(CFG_Metodo="Promedio",F58,E58)) | H58: =IF(G58="","",IF(C58="unidad",G58,G58*1000)) | I58: =IF(A58="","",IF(C58="","Falta unidad base",IF(D58="","Sin compras cargadas","OK")))
D59: =IF(A59="","",IF(COUNTIFS(Compras!$B$5:$B$2000,A59,Compras!$H$5:$H$2000,">0")=0,"",_xlfn.MAXIFS(Compras!$A$5:$A$2000,Compras!$B$5:$B$2000,A59,Compras!$H$5:$H$2000,">0"))) | E59: =IF(D59="","",SUMIFS(Compras!$H$5:$H$2000,Compras!$B$5:$B$2000,A59,Compras!$A$5:$A$2000,D59,Compras!$H$5:$H$2000,">0")/COUNTIFS(Compras!$B$5:$B$2000,A59,Compras!$A$5:$A$2000,D59,Compras!$H$5:$H$2000,">0")) | F59: =IF(D59="","",SUMIFS(Compras!$F$5:$F$2000,Compras!$B$5:$B$2000,A59,Compras!$H$5:$H$2000,">0")/SUMIFS(Compras!$G$5:$G$2000,Compras!$B$5:$B$2000,A59,Compras!$H$5:$H$2000,">0")) | G59: =IF(D59="","",IF(CFG_Metodo="Promedio",F59,E59)) | H59: =IF(G59="","",IF(C59="unidad",G59,G59*1000)) | I59: =IF(A59="","",IF(C59="","Falta unidad base",IF(D59="","Sin compras cargadas","OK")))
D60: =IF(A60="","",IF(COUNTIFS(Compras!$B$5:$B$2000,A60,Compras!$H$5:$H$2000,">0")=0,"",_xlfn.MAXIFS(Compras!$A$5:$A$2000,Compras!$B$5:$B$2000,A60,Compras!$H$5:$H$2000,">0"))) | E60: =IF(D60="","",SUMIFS(Compras!$H$5:$H$2000,Compras!$B$5:$B$2000,A60,Compras!$A$5:$A$2000,D60,Compras!$H$5:$H$2000,">0")/COUNTIFS(Compras!$B$5:$B$2000,A60,Compras!$A$5:$A$2000,D60,Compras!$H$5:$H$2000,">0")) | F60: =IF(D60="","",SUMIFS(Compras!$F$5:$F$2000,Compras!$B$5:$B$2000,A60,Compras!$H$5:$H$2000,">0")/SUMIFS(Compras!$G$5:$G$2000,Compras!$B$5:$B$2000,A60,Compras!$H$5:$H$2000,">0")) | G60: =IF(D60="","",IF(CFG_Metodo="Promedio",F60,E60)) | H60: =IF(G60="","",IF(C60="unidad",G60,G60*1000)) | I60: =IF(A60="","",IF(C60="","Falta unidad base",IF(D60="","Sin compras cargadas","OK")))
D61: =IF(A61="","",IF(COUNTIFS(Compras!$B$5:$B$2000,A61,Compras!$H$5:$H$2000,">0")=0,"",_xlfn.MAXIFS(Compras!$A$5:$A$2000,Compras!$B$5:$B$2000,A61,Compras!$H$5:$H$2000,">0"))) | E61: =IF(D61="","",SUMIFS(Compras!$H$5:$H$2000,Compras!$B$5:$B$2000,A61,Compras!$A$5:$A$2000,D61,Compras!$H$5:$H$2000,">0")/COUNTIFS(Compras!$B$5:$B$2000,A61,Compras!$A$5:$A$2000,D61,Compras!$H$5:$H$2000,">0")) | F61: =IF(D61="","",SUMIFS(Compras!$F$5:$F$2000,Compras!$B$5:$B$2000,A61,Compras!$H$5:$H$2000,">0")/SUMIFS(Compras!$G$5:$G$2000,Compras!$B$5:$B$2000,A61,Compras!$H$5:$H$2000,">0")) | G61: =IF(D61="","",IF(CFG_Metodo="Promedio",F61,E61)) | H61: =IF(G61="","",IF(C61="unidad",G61,G61*1000)) | I61: =IF(A61="","",IF(C61="","Falta unidad base",IF(D61="","Sin compras cargadas","OK")))
D62: =IF(A62="","",IF(COUNTIFS(Compras!$B$5:$B$2000,A62,Compras!$H$5:$H$2000,">0")=0,"",_xlfn.MAXIFS(Compras!$A$5:$A$2000,Compras!$B$5:$B$2000,A62,Compras!$H$5:$H$2000,">0"))) | E62: =IF(D62="","",SUMIFS(Compras!$H$5:$H$2000,Compras!$B$5:$B$2000,A62,Compras!$A$5:$A$2000,D62,Compras!$H$5:$H$2000,">0")/COUNTIFS(Compras!$B$5:$B$2000,A62,Compras!$A$5:$A$2000,D62,Compras!$H$5:$H$2000,">0")) | F62: =IF(D62="","",SUMIFS(Compras!$F$5:$F$2000,Compras!$B$5:$B$2000,A62,Compras!$H$5:$H$2000,">0")/SUMIFS(Compras!$G$5:$G$2000,Compras!$B$5:$B$2000,A62,Compras!$H$5:$H$2000,">0")) | G62: =IF(D62="","",IF(CFG_Metodo="Promedio",F62,E62)) | H62: =IF(G62="","",IF(C62="unidad",G62,G62*1000)) | I62: =IF(A62="","",IF(C62="","Falta unidad base",IF(D62="","Sin compras cargadas","OK")))
... D250: =IF(A250="","",IF(COUNTIFS(Compras!$B$5:$B$2000,A250,Compras!$H$5:$H$2000,">0")=0,"",_xlfn.MAXIFS(Compras!$A$5:$A$2000,Compras!$B$5:$B$2000,A250,Compras!$H$5:$H$2000,">0"))) | E250: =IF(D250="","",SUMIFS(Compras!$H$5:$H$2000,Compras!$B$5:$B$2000,A250,Compras!$A$5:$A$2000,D250,Compras!$H$5:$H$2000,">0")/COUNTIFS(Compras!$B$5:$B$2000,A250,Compras!$A$5:$A$2000,D250,Compras!$H$5:$H$2000,">0")) | F250: =IF(D250="","",SUMIFS(Compras!$F$5:$F$2000,Compras!$B$5:$B$2000,A250,Compras!$H$5:$H$2000,">0")/SUMIFS(Compras!$G$5:$G$2000,Compras!$B$5:$B$2000,A250,Compras!$H$5:$H$2000,">0")) | G250: =IF(D250="","",IF(CFG_Metodo="Promedio",F250,E250)) | H250: =IF(G250="","",IF(C250="unidad",G250,G250*1000)) | I250: =IF(A250="","",IF(C250="","Falta unidad base",IF(D250="","Sin compras cargadas","OK")))

Sheet Compras
A1: Compras de insumos
A2: Una fila por compra. Anotá la cantidad tal como la comprás (ej.: 1 kg, 500 g, 1 l, 100 unidades) y el precio total pagado.
A4: Fecha | B4: Insumo | C4: Proveedor | D4: Cantidad comprada | E4: Unidad | F4: Precio total pagado ($) | G4: Cantidad en unidad base | H4: Costo por unidad base ($) | I4: Control | J4: Notas
A5: 46267 | B5: Almidón de maíz | C5: Dietética (ejemplo) | D5: 1 | E5: kg | F5: 3000 | G5: =IF(OR(D5="",E5=""),"",IFERROR(D5*INDEX(UnidadesFactor,MATCH(E5,Unidades,0)),"")) -> 1000 | H5: =IF(I5<>"OK","",IF(G5=0,"",F5/G5)) -> 3 | I5: =IF(B5="","",IF(ISNA(MATCH(B5,ListaInsumos,0)),"Insumo no está en Insumos",IF(OR(D5="",E5="",F5=""),"Faltan datos",IF(INDEX(UnidadesBase,MATCH(E5,Unidades,0))<>INDEX(InsBase,MATCH(B5,ListaInsumos,0)),"Unidad incompatible",IF(A5="","Falta fecha","OK"))))) -> OK | J5: EJEMPLO: reemplazar por datos reales
A6: 46267 | B6: Harina de arroz | C6: Dietética (ejemplo) | D6: 1 | E6: kg | F6: 2800 | G6: =IF(OR(D6="",E6=""),"",IFERROR(D6*INDEX(UnidadesFactor,MATCH(E6,Unidades,0)),"")) -> 1000 | H6: =IF(I6<>"OK","",IF(G6=0,"",F6/G6)) -> 2.8 | I6: =IF(B6="","",IF(ISNA(MATCH(B6,ListaInsumos,0)),"Insumo no está en Insumos",IF(OR(D6="",E6="",F6=""),"Faltan datos",IF(INDEX(UnidadesBase,MATCH(E6,Unidades,0))<>INDEX(InsBase,MATCH(B6,ListaInsumos,0)),"Unidad incompatible",IF(A6="","Falta fecha","OK"))))) -> OK | J6: EJEMPLO: reemplazar por datos reales
A7: 46267 | B7: Almidón de mandioca | C7: Dietética (ejemplo) | D7: 1 | E7: kg | F7: 3500 | G7: =IF(OR(D7="",E7=""),"",IFERROR(D7*INDEX(UnidadesFactor,MATCH(E7,Unidades,0)),"")) -> 1000 | H7: =IF(I7<>"OK","",IF(G7=0,"",F7/G7)) -> 3.5 | I7: =IF(B7="","",IF(ISNA(MATCH(B7,ListaInsumos,0)),"Insumo no está en Insumos",IF(OR(D7="",E7="",F7=""),"Faltan datos",IF(INDEX(UnidadesBase,MATCH(E7,Unidades,0))<>INDEX(InsBase,MATCH(B7,ListaInsumos,0)),"Unidad incompatible",IF(A7="","Falta fecha","OK"))))) -> OK | J7: EJEMPLO: reemplazar por datos reales
A8: 46254 | B8: Aceite de oliva | C8: Mayorista (ejemplo) | D8: 1 | E8: l | F8: 16500 | G8: =IF(OR(D8="",E8=""),"",IFERROR(D8*INDEX(UnidadesFactor,MATCH(E8,Unidades,0)),"")) -> 1000 | H8: =IF(I8<>"OK","",IF(G8=0,"",F8/G8)) -> 16.5 | I8: =IF(B8="","",IF(ISNA(MATCH(B8,ListaInsumos,0)),"Insumo no está en Insumos",IF(OR(D8="",E8="",F8=""),"Faltan datos",IF(INDEX(UnidadesBase,MATCH(E8,Unidades,0))<>INDEX(InsBase,MATCH(B8,ListaInsumos,0)),"Unidad incompatible",IF(A8="","Falta fecha","OK"))))) -> OK | J8: EJEMPLO: reemplazar por datos reales
A9: 46280 | B9: Aceite de oliva | C9: Mayorista (ejemplo) | D9: 1 | E9: l | F9: 18000 | G9: =IF(OR(D9="",E9=""),"",IFERROR(D9*INDEX(UnidadesFactor,MATCH(E9,Unidades,0)),"")) -> 1000 | H9: =IF(I9<>"OK","",IF(G9=0,"",F9/G9)) -> 18 | I9: =IF(B9="","",IF(ISNA(MATCH(B9,ListaInsumos,0)),"Insumo no está en Insumos",IF(OR(D9="",E9="",F9=""),"Faltan datos",IF(INDEX(UnidadesBase,MATCH(E9,Unidades,0))<>INDEX(InsBase,MATCH(B9,ListaInsumos,0)),"Unidad incompatible",IF(A9="","Falta fecha","OK"))))) -> OK | J9: EJEMPLO: reemplazar por datos reales
A10: 46267 | B10: Sal marina | C10: Dietética (ejemplo) | D10: 500 | E10: g | F10: 2500 | G10: =IF(OR(D10="",E10=""),"",IFERROR(D10*INDEX(UnidadesFactor,MATCH(E10,Unidades,0)),"")) -> 500 | H10: =IF(I10<>"OK","",IF(G10=0,"",F10/G10)) -> 5 | I10: =IF(B10="","",IF(ISNA(MATCH(B10,ListaInsumos,0)),"Insumo no está en Insumos",IF(OR(D10="",E10="",F10=""),"Faltan datos",IF(INDEX(UnidadesBase,MATCH(E10,Unidades,0))<>INDEX(InsBase,MATCH(B10,ListaInsumos,0)),"Unidad incompatible",IF(A10="","Falta fecha","OK"))))) -> OK | J10: EJEMPLO: reemplazar por datos reales
A11: 46267 | B11: Goma xántica | C11: Dietética (ejemplo) | D11: 100 | E11: g | F11: 6000 | G11: =IF(OR(D11="",E11=""),"",IFERROR(D11*INDEX(UnidadesFactor,MATCH(E11,Unidades,0)),"")) -> 100 | H11: =IF(I11<>"OK","",IF(G11=0,"",F11/G11)) -> 60 | I11: =IF(B11="","",IF(ISNA(MATCH(B11,ListaInsumos,0)),"Insumo no está en Insumos",IF(OR(D11="",E11="",F11=""),"Faltan datos",IF(INDEX(UnidadesBase,MATCH(E11,Unidades,0))<>INDEX(InsBase,MATCH(B11,ListaInsumos,0)),"Unidad incompatible",IF(A11="","Falta fecha","OK"))))) -> OK | J11: EJEMPLO: reemplazar por datos reales
A12: 46267 | B12: Polvo leudante | C12: Dietética (ejemplo) | D12: 100 | E12: g | F12: 1500 | G12: =IF(OR(D12="",E12=""),"",IFERROR(D12*INDEX(UnidadesFactor,MATCH(E12,Unidades,0)),"")) -> 100 | H12: =IF(I12<>"OK","",IF(G12=0,"",F12/G12)) -> 15 | I12: =IF(B12="","",IF(ISNA(MATCH(B12,ListaInsumos,0)),"Insumo no está en Insumos",IF(OR(D12="",E12="",F12=""),"Faltan datos",IF(INDEX(UnidadesBase,MATCH(E12,Unidades,0))<>INDEX(InsBase,MATCH(B12,ListaInsumos,0)),"Unidad incompatible",IF(A12="","Falta fecha","OK"))))) -> OK | J12: EJEMPLO: reemplazar por datos reales
A13: 46270 | B13: Bolsa individual | C13: Packaging (ejemplo) | D13: 100 | E13: unidad | F13: 8000 | G13: =IF(OR(D13="",E13=""),"",IFERROR(D13*INDEX(UnidadesFactor,MATCH(E13,Unidades,0)),"")) -> 100 | H13: =IF(I13<>"OK","",IF(G13=0,"",F13/G13)) -> 80 | I13: =IF(B13="","",IF(ISNA(MATCH(B13,ListaInsumos,0)),"Insumo no está en Insumos",IF(OR(D13="",E13="",F13=""),"Faltan datos",IF(INDEX(UnidadesBase,MATCH(E13,Unidades,0))<>INDEX(InsBase,MATCH(B13,ListaInsumos,0)),"Unidad incompatible",IF(A13="","Falta fecha","OK"))))) -> OK | J13: EJEMPLO: reemplazar por datos reales
A14: 46270 | B14: Bolsa familiar | C14: Packaging (ejemplo) | D14: 100 | E14: unidad | F14: 12000 | G14: =IF(OR(D14="",E14=""),"",IFERROR(D14*INDEX(UnidadesFactor,MATCH(E14,Unidades,0)),"")) -> 100 | H14: =IF(I14<>"OK","",IF(G14=0,"",F14/G14)) -> 120 | I14: =IF(B14="","",IF(ISNA(MATCH(B14,ListaInsumos,0)),"Insumo no está en Insumos",IF(OR(D14="",E14="",F14=""),"Faltan datos",IF(INDEX(UnidadesBase,MATCH(E14,Unidades,0))<>INDEX(InsBase,MATCH(B14,ListaInsumos,0)),"Unidad incompatible",IF(A14="","Falta fecha","OK"))))) -> OK | J14: EJEMPLO: reemplazar por datos reales
A15: 46270 | B15: Etiqueta | C15: Imprenta (ejemplo) | D15: 100 | E15: unidad | F15: 5000 | G15: =IF(OR(D15="",E15=""),"",IFERROR(D15*INDEX(UnidadesFactor,MATCH(E15,Unidades,0)),"")) -> 100 | H15: =IF(I15<>"OK","",IF(G15=0,"",F15/G15)) -> 50 | I15: =IF(B15="","",IF(ISNA(MATCH(B15,ListaInsumos,0)),"Insumo no está en Insumos",IF(OR(D15="",E15="",F15=""),"Faltan datos",IF(INDEX(UnidadesBase,MATCH(E15,Unidades,0))<>INDEX(InsBase,MATCH(B15,ListaInsumos,0)),"Unidad incompatible",IF(A15="","Falta fecha","OK"))))) -> OK | J15: EJEMPLO: reemplazar por datos reales
G16: =IF(OR(D16="",E16=""),"",IFERROR(D16*INDEX(UnidadesFactor,MATCH(E16,Unidades,0)),"")) | H16: =IF(I16<>"OK","",IF(G16=0,"",F16/G16)) | I16: =IF(B16="","",IF(ISNA(MATCH(B16,ListaInsumos,0)),"Insumo no está en Insumos",IF(OR(D16="",E16="",F16=""),"Faltan datos",IF(INDEX(UnidadesBase,MATCH(E16,Unidades,0))<>INDEX(InsBase,MATCH(B16,ListaInsumos,0)),"Unidad incompatible",IF(A16="","Falta fecha","OK")))))
G17: =IF(OR(D17="",E17=""),"",IFERROR(D17*INDEX(UnidadesFactor,MATCH(E17,Unidades,0)),"")) | H17: =IF(I17<>"OK","",IF(G17=0,"",F17/G17)) | I17: =IF(B17="","",IF(ISNA(MATCH(B17,ListaInsumos,0)),"Insumo no está en Insumos",IF(OR(D17="",E17="",F17=""),"Faltan datos",IF(INDEX(UnidadesBase,MATCH(E17,Unidades,0))<>INDEX(InsBase,MATCH(B17,ListaInsumos,0)),"Unidad incompatible",IF(A17="","Falta fecha","OK")))))
G18: =IF(OR(D18="",E18=""),"",IFERROR(D18*INDEX(UnidadesFactor,MATCH(E18,Unidades,0)),"")) | H18: =IF(I18<>"OK","",IF(G18=0,"",F18/G18)) | I18: =IF(B18="","",IF(ISNA(MATCH(B18,ListaInsumos,0)),"Insumo no está en Insumos",IF(OR(D18="",E18="",F18=""),"Faltan datos",IF(INDEX(UnidadesBase,MATCH(E18,Unidades,0))<>INDEX(InsBase,MATCH(B18,ListaInsumos,0)),"Unidad incompatible",IF(A18="","Falta fecha","OK")))))
G19: =IF(OR(D19="",E19=""),"",IFERROR(D19*INDEX(UnidadesFactor,MATCH(E19,Unidades,0)),"")) | H19: =IF(I19<>"OK","",IF(G19=0,"",F19/G19)) | I19: =IF(B19="","",IF(ISNA(MATCH(B19,ListaInsumos,0)),"Insumo no está en Insumos",IF(OR(D19="",E19="",F19=""),"Faltan datos",IF(INDEX(UnidadesBase,MATCH(E19,Unidades,0))<>INDEX(InsBase,MATCH(B19,ListaInsumos,0)),"Unidad incompatible",IF(A19="","Falta fecha","OK")))))
G20: =IF(OR(D20="",E20=""),"",IFERROR(D20*INDEX(UnidadesFactor,MATCH(E20,Unidades,0)),"")) | H20: =IF(I20<>"OK","",IF(G20=0,"",F20/G20)) | I20: =IF(B20="","",IF(ISNA(MATCH(B20,ListaInsumos,0)),"Insumo no está en Insumos",IF(OR(D20="",E20="",F20=""),"Faltan datos",IF(INDEX(UnidadesBase,MATCH(E20,Unidades,0))<>INDEX(InsBase,MATCH(B20,ListaInsumos,0)),"Unidad incompatible",IF(A20="","Falta fecha","OK")))))
G21: =IF(OR(D21="",E21=""),"",IFERROR(D21*INDEX(UnidadesFactor,MATCH(E21,Unidades,0)),"")) | H21: =IF(I21<>"OK","",IF(G21=0,"",F21/G21)) | I21: =IF(B21="","",IF(ISNA(MATCH(B21,ListaInsumos,0)),"Insumo no está en Insumos",IF(OR(D21="",E21="",F21=""),"Faltan datos",IF(INDEX(UnidadesBase,MATCH(E21,Unidades,0))<>INDEX(InsBase,MATCH(B21,ListaInsumos,0)),"Unidad incompatible",IF(A21="","Falta fecha","OK")))))
G22: =IF(OR(D22="",E22=""),"",IFERROR(D22*INDEX(UnidadesFactor,MATCH(E22,Unidades,0)),"")) | H22: =IF(I22<>"OK","",IF(G22=0,"",F22/G22)) | I22: =IF(B22="","",IF(ISNA(MATCH(B22,ListaInsumos,0)),"Insumo no está en Insumos",IF(OR(D22="",E22="",F22=""),"Faltan datos",IF(INDEX(UnidadesBase,MATCH(E22,Unidades,0))<>INDEX(InsBase,MATCH(B22,ListaInsumos,0)),"Unidad incompatible",IF(A22="","Falta fecha","OK")))))
G23: =IF(OR(D23="",E23=""),"",IFERROR(D23*INDEX(UnidadesFactor,MATCH(E23,Unidades,0)),"")) | H23: =IF(I23<>"OK","",IF(G23=0,"",F23/G23)) | I23: =IF(B23="","",IF(ISNA(MATCH(B23,ListaInsumos,0)),"Insumo no está en Insumos",IF(OR(D23="",E23="",F23=""),"Faltan datos",IF(INDEX(UnidadesBase,MATCH(E23,Unidades,0))<>INDEX(InsBase,MATCH(B23,ListaInsumos,0)),"Unidad incompatible",IF(A23="","Falta fecha","OK")))))
G24: =IF(OR(D24="",E24=""),"",IFERROR(D24*INDEX(UnidadesFactor,MATCH(E24,Unidades,0)),"")) | H24: =IF(I24<>"OK","",IF(G24=0,"",F24/G24)) | I24: =IF(B24="","",IF(ISNA(MATCH(B24,ListaInsumos,0)),"Insumo no está en Insumos",IF(OR(D24="",E24="",F24=""),"Faltan datos",IF(INDEX(UnidadesBase,MATCH(E24,Unidades,0))<>INDEX(InsBase,MATCH(B24,ListaInsumos,0)),"Unidad incompatible",IF(A24="","Falta fecha","OK")))))
G25: =IF(OR(D25="",E25=""),"",IFERROR(D25*INDEX(UnidadesFactor,MATCH(E25,Unidades,0)),"")) | H25: =IF(I25<>"OK","",IF(G25=0,"",F25/G25)) | I25: =IF(B25="","",IF(ISNA(MATCH(B25,ListaInsumos,0)),"Insumo no está en Insumos",IF(OR(D25="",E25="",F25=""),"Faltan datos",IF(INDEX(UnidadesBase,MATCH(E25,Unidades,0))<>INDEX(InsBase,MATCH(B25,ListaInsumos,0)),"Unidad incompatible",IF(A25="","Falta fecha","OK")))))
G26: =IF(OR(D26="",E26=""),"",IFERROR(D26*INDEX(UnidadesFactor,MATCH(E26,Unidades,0)),"")) | H26: =IF(I26<>"OK","",IF(G26=0,"",F26/G26)) | I26: =IF(B26="","",IF(ISNA(MATCH(B26,ListaInsumos,0)),"Insumo no está en Insumos",IF(OR(D26="",E26="",F26=""),"Faltan datos",IF(INDEX(UnidadesBase,MATCH(E26,Unidades,0))<>INDEX(InsBase,MATCH(B26,ListaInsumos,0)),"Unidad incompatible",IF(A26="","Falta fecha","OK")))))
G27: =IF(OR(D27="",E27=""),"",IFERROR(D27*INDEX(UnidadesFactor,MATCH(E27,Unidades,0)),"")) | H27: =IF(I27<>"OK","",IF(G27=0,"",F27/G27)) | I27: =IF(B27="","",IF(ISNA(MATCH(B27,ListaInsumos,0)),"Insumo no está en Insumos",IF(OR(D27="",E27="",F27=""),"Faltan datos",IF(INDEX(UnidadesBase,MATCH(E27,Unidades,0))<>INDEX(InsBase,MATCH(B27,ListaInsumos,0)),"Unidad incompatible",IF(A27="","Falta fecha","OK")))))
... G2000: =IF(OR(D2000="",E2000=""),"",IFERROR(D2000*INDEX(UnidadesFactor,MATCH(E2000,Unidades,0)),"")) | H2000: =IF(I2000<>"OK","",IF(G2000=0,"",F2000/G2000)) | I2000: =IF(B2000="","",IF(ISNA(MATCH(B2000,ListaInsumos,0)),"Insumo no está en Insumos",IF(OR(D2000="",E2000="",F2000=""),"Faltan datos",IF(INDEX(UnidadesBase,MATCH(E2000,Unidades,0))<>INDEX(InsBase,MATCH(B2000,ListaInsumos,0)),"Unidad incompatible",IF(A2000="","Falta fecha","OK")))))

Sheet Recetas
A1: Recetas (ingredientes por tanda)
A2: Una fila por ingrediente. Anotá la cantidad que usás en UNA tanda de la receta. El rendimiento de la tanda se carga en la hoja Costo por Receta.
A4: Receta | B4: Insumo | C4: Cantidad | D4: Unidad | E4: Cantidad en unidad base | F4: Costo por unidad base ($) | G4: Costo en la receta ($) | H4: Control | I4: Notas
A5: Cookies Chips de Chocolate | B5: Garbanzos | D5: g | E5: =IF(OR(C5="",D5=""),"",IFERROR(C5*INDEX(UnidadesFactor,MATCH(D5,Unidades,0)),"")) | F5: =IF(B5="","",IFERROR(INDEX(InsCosto,MATCH(B5,ListaInsumos,0)),"")) | G5: =IF(AND(A5="",B5=""),"",IF(H5="OK",E5*F5,0)) -> 0 | H5: =IF(AND(A5="",B5=""),"",IF(ISNA(MATCH(B5,ListaInsumos,0)),"Insumo no está en Insumos",IF(C5="","Falta cantidad",IF(IFERROR(INDEX(UnidadesBase,MATCH(D5,Unidades,0)),"")<>INDEX(InsBase,MATCH(B5,ListaInsumos,0)),"Unidad incompatible",IF(F5="","Insumo sin compras","OK"))))) -> Falta cantidad
A6: Cookies Chips de Chocolate | B6: Azúcar de coco | D6: g | E6: =IF(OR(C6="",D6=""),"",IFERROR(C6*INDEX(UnidadesFactor,MATCH(D6,Unidades,0)),"")) | F6: =IF(B6="","",IFERROR(INDEX(InsCosto,MATCH(B6,ListaInsumos,0)),"")) | G6: =IF(AND(A6="",B6=""),"",IF(H6="OK",E6*F6,0)) -> 0 | H6: =IF(AND(A6="",B6=""),"",IF(ISNA(MATCH(B6,ListaInsumos,0)),"Insumo no está en Insumos",IF(C6="","Falta cantidad",IF(IFERROR(INDEX(UnidadesBase,MATCH(D6,Unidades,0)),"")<>INDEX(InsBase,MATCH(B6,ListaInsumos,0)),"Unidad incompatible",IF(F6="","Insumo sin compras","OK"))))) -> Falta cantidad
A7: Cookies Chips de Chocolate | B7: Extracto de vainilla | D7: ml | E7: =IF(OR(C7="",D7=""),"",IFERROR(C7*INDEX(UnidadesFactor,MATCH(D7,Unidades,0)),"")) | F7: =IF(B7="","",IFERROR(INDEX(InsCosto,MATCH(B7,ListaInsumos,0)),"")) | G7: =IF(AND(A7="",B7=""),"",IF(H7="OK",E7*F7,0)) -> 0 | H7: =IF(AND(A7="",B7=""),"",IF(ISNA(MATCH(B7,ListaInsumos,0)),"Insumo no está en Insumos",IF(C7="","Falta cantidad",IF(IFERROR(INDEX(UnidadesBase,MATCH(D7,Unidades,0)),"")<>INDEX(InsBase,MATCH(B7,ListaInsumos,0)),"Unidad incompatible",IF(F7="","Insumo sin compras","OK"))))) -> Falta cantidad
A8: Cookies Chips de Chocolate | B8: Polvo de hornear | D8: g | E8: =IF(OR(C8="",D8=""),"",IFERROR(C8*INDEX(UnidadesFactor,MATCH(D8,Unidades,0)),"")) | F8: =IF(B8="","",IFERROR(INDEX(InsCosto,MATCH(B8,ListaInsumos,0)),"")) | G8: =IF(AND(A8="",B8=""),"",IF(H8="OK",E8*F8,0)) -> 0 | H8: =IF(AND(A8="",B8=""),"",IF(ISNA(MATCH(B8,ListaInsumos,0)),"Insumo no está en Insumos",IF(C8="","Falta cantidad",IF(IFERROR(INDEX(UnidadesBase,MATCH(D8,Unidades,0)),"")<>INDEX(InsBase,MATCH(B8,ListaInsumos,0)),"Unidad incompatible",IF(F8="","Insumo sin compras","OK"))))) -> Falta cantidad
A9: Cookies Chips de Chocolate | B9: Goma xántica | D9: g | E9: =IF(OR(C9="",D9=""),"",IFERROR(C9*INDEX(UnidadesFactor,MATCH(D9,Unidades,0)),"")) | F9: =IF(B9="","",IFERROR(INDEX(InsCosto,MATCH(B9,ListaInsumos,0)),"")) -> 60 | G9: =IF(AND(A9="",B9=""),"",IF(H9="OK",E9*F9,0)) -> 0 | H9: =IF(AND(A9="",B9=""),"",IF(ISNA(MATCH(B9,ListaInsumos,0)),"Insumo no está en Insumos",IF(C9="","Falta cantidad",IF(IFERROR(INDEX(UnidadesBase,MATCH(D9,Unidades,0)),"")<>INDEX(InsBase,MATCH(B9,ListaInsumos,0)),"Unidad incompatible",IF(F9="","Insumo sin compras","OK"))))) -> Falta cantidad
A10: Cookies Chips de Chocolate | B10: Chocolate 70% sin azúcar | D10: g | E10: =IF(OR(C10="",D10=""),"",IFERROR(C10*INDEX(UnidadesFactor,MATCH(D10,Unidades,0)),"")) | F10: =IF(B10="","",IFERROR(INDEX(InsCosto,MATCH(B10,ListaInsumos,0)),"")) | G10: =IF(AND(A10="",B10=""),"",IF(H10="OK",E10*F10,0)) -> 0 | H10: =IF(AND(A10="",B10=""),"",IF(ISNA(MATCH(B10,ListaInsumos,0)),"Insumo no está en Insumos",IF(C10="","Falta cantidad",IF(IFERROR(INDEX(UnidadesBase,MATCH(D10,Unidades,0)),"")<>INDEX(InsBase,MATCH(B10,ListaInsumos,0)),"Unidad incompatible",IF(F10="","Insumo sin compras","OK"))))) -> Falta cantidad
A11: Cookies Chips de Chocolate | B11: Sal marina | D11: g | E11: =IF(OR(C11="",D11=""),"",IFERROR(C11*INDEX(UnidadesFactor,MATCH(D11,Unidades,0)),"")) | F11: =IF(B11="","",IFERROR(INDEX(InsCosto,MATCH(B11,ListaInsumos,0)),"")) -> 5 | G11: =IF(AND(A11="",B11=""),"",IF(H11="OK",E11*F11,0)) -> 0 | H11: =IF(AND(A11="",B11=""),"",IF(ISNA(MATCH(B11,ListaInsumos,0)),"Insumo no está en Insumos",IF(C11="","Falta cantidad",IF(IFERROR(INDEX(UnidadesBase,MATCH(D11,Unidades,0)),"")<>INDEX(InsBase,MATCH(B11,ListaInsumos,0)),"Unidad incompatible",IF(F11="","Insumo sin compras","OK"))))) -> Falta cantidad
A12: Pan de Molde con Trigo Sarraceno | B12: Trigo sarraceno | D12: g | E12: =IF(OR(C12="",D12=""),"",IFERROR(C12*INDEX(UnidadesFactor,MATCH(D12,Unidades,0)),"")) | F12: =IF(B12="","",IFERROR(INDEX(InsCosto,MATCH(B12,ListaInsumos,0)),"")) | G12: =IF(AND(A12="",B12=""),"",IF(H12="OK",E12*F12,0)) -> 0 | H12: =IF(AND(A12="",B12=""),"",IF(ISNA(MATCH(B12,ListaInsumos,0)),"Insumo no está en Insumos",IF(C12="","Falta cantidad",IF(IFERROR(INDEX(UnidadesBase,MATCH(D12,Unidades,0)),"")<>INDEX(InsBase,MATCH(B12,ListaInsumos,0)),"Unidad incompatible",IF(F12="","Insumo sin compras","OK"))))) -> Falta cantidad
A13: Pan de Molde con Trigo Sarraceno | B13: Harina de sorgo | D13: g | E13: =IF(OR(C13="",D13=""),"",IFERROR(C13*INDEX(UnidadesFactor,MATCH(D13,Unidades,0)),"")) | F13: =IF(B13="","",IFERROR(INDEX(InsCosto,MATCH(B13,ListaInsumos,0)),"")) | G13: =IF(AND(A13="",B13=""),"",IF(H13="OK",E13*F13,0)) -> 0 | H13: =IF(AND(A13="",B13=""),"",IF(ISNA(MATCH(B13,ListaInsumos,0)),"Insumo no está en Insumos",IF(C13="","Falta cantidad",IF(IFERROR(INDEX(UnidadesBase,MATCH(D13,Unidades,0)),"")<>INDEX(InsBase,MATCH(B13,ListaInsumos,0)),"Unidad incompatible",IF(F13="","Insumo sin compras","OK"))))) -> Falta cantidad
A14: Pan de Molde con Trigo Sarraceno | B14: Harina de lino | D14: g | E14: =IF(OR(C14="",D14=""),"",IFERROR(C14*INDEX(UnidadesFactor,MATCH(D14,Unidades,0)),"")) | F14: =IF(B14="","",IFERROR(INDEX(InsCosto,MATCH(B14,ListaInsumos,0)),"")) | G14: =IF(AND(A14="",B14=""),"",IF(H14="OK",E14*F14,0)) -> 0 | H14: =IF(AND(A14="",B14=""),"",IF(ISNA(MATCH(B14,ListaInsumos,0)),"Insumo no está en Insumos",IF(C14="","Falta cantidad",IF(IFERROR(INDEX(UnidadesBase,MATCH(D14,Unidades,0)),"")<>INDEX(InsBase,MATCH(B14,ListaInsumos,0)),"Unidad incompatible",IF(F14="","Insumo sin compras","OK"))))) -> Falta cantidad
A15: Pan de Molde con Trigo Sarraceno | B15: Harina de arroz | D15: g | E15: =IF(OR(C15="",D15=""),"",IFERROR(C15*INDEX(UnidadesFactor,MATCH(D15,Unidades,0)),"")) | F15: =IF(B15="","",IFERROR(INDEX(InsCosto,MATCH(B15,ListaInsumos,0)),"")) -> 2.8 | G15: =IF(AND(A15="",B15=""),"",IF(H15="OK",E15*F15,0)) -> 0 | H15: =IF(AND(A15="",B15=""),"",IF(ISNA(MATCH(B15,ListaInsumos,0)),"Insumo no está en Insumos",IF(C15="","Falta cantidad",IF(IFERROR(INDEX(UnidadesBase,MATCH(D15,Unidades,0)),"")<>INDEX(InsBase,MATCH(B15,ListaInsumos,0)),"Unidad incompatible",IF(F15="","Insumo sin compras","OK"))))) -> Falta cantidad
A16: Pan de Molde con Trigo Sarraceno | B16: Almidón de mandioca | D16: g | E16: =IF(OR(C16="",D16=""),"",IFERROR(C16*INDEX(UnidadesFactor,MATCH(D16,Unidades,0)),"")) | F16: =IF(B16="","",IFERROR(INDEX(InsCosto,MATCH(B16,ListaInsumos,0)),"")) -> 3.5 | G16: =IF(AND(A16="",B16=""),"",IF(H16="OK",E16*F16,0)) -> 0 | H16: =IF(AND(A16="",B16=""),"",IF(ISNA(MATCH(B16,ListaInsumos,0)),"Insumo no está en Insumos",IF(C16="","Falta cantidad",IF(IFERROR(INDEX(UnidadesBase,MATCH(D16,Unidades,0)),"")<>INDEX(InsBase,MATCH(B16,ListaInsumos,0)),"Unidad incompatible",IF(F16="","Insumo sin compras","OK"))))) -> Falta cantidad
... A27: Tablitas de Trigo Sarraceno y Semillas | B27: Semillas (mix) | D27: g | E27: =IF(OR(C27="",D27=""),"",IFERROR(C27*INDEX(UnidadesFactor,MATCH(D27,Unidades,0)),"")) | F27: =IF(B27="","",IFERROR(INDEX(InsCosto,MATCH(B27,ListaInsumos,0)),"")) | G27: =IF(AND(A27="",B27=""),"",IF(H27="OK",E27*F27,0)) -> 0 | H27: =IF(AND(A27="",B27=""),"",IF(ISNA(MATCH(B27,ListaInsumos,0)),"Insumo no está en Insumos",IF(C27="","Falta cantidad",IF(IFERROR(INDEX(UnidadesBase,MATCH(D27,Unidades,0)),"")<>INDEX(InsBase,MATCH(B27,ListaInsumos,0)),"Unidad incompatible",IF(F27="","Insumo sin compras","OK"))))) -> Falta cantidad
A28: Galletas Marineras | B28: Almidón de maíz | C28: 200 | D28: g | E28: =IF(OR(C28="",D28=""),"",IFERROR(C28*INDEX(UnidadesFactor,MATCH(D28,Unidades,0)),"")) -> 200 | F28: =IF(B28="","",IFERROR(INDEX(InsCosto,MATCH(B28,ListaInsumos,0)),"")) -> 3 | G28: =IF(AND(A28="",B28=""),"",IF(H28="OK",E28*F28,0)) -> 600 | H28: =IF(AND(A28="",B28=""),"",IF(ISNA(MATCH(B28,ListaInsumos,0)),"Insumo no está en Insumos",IF(C28="","Falta cantidad",IF(IFERROR(INDEX(UnidadesBase,MATCH(D28,Unidades,0)),"")<>INDEX(InsBase,MATCH(B28,ListaInsumos,0)),"Unidad incompatible",IF(F28="","Insumo sin compras","OK"))))) -> OK | I28: EJEMPLO: reemplazar por datos reales
A29: Galletas Marineras | B29: Harina de arroz | C29: 150 | D29: g | E29: =IF(OR(C29="",D29=""),"",IFERROR(C29*INDEX(UnidadesFactor,MATCH(D29,Unidades,0)),"")) -> 150 | F29: =IF(B29="","",IFERROR(INDEX(InsCosto,MATCH(B29,ListaInsumos,0)),"")) -> 2.8 | G29: =IF(AND(A29="",B29=""),"",IF(H29="OK",E29*F29,0)) -> 420 | H29: =IF(AND(A29="",B29=""),"",IF(ISNA(MATCH(B29,ListaInsumos,0)),"Insumo no está en Insumos",IF(C29="","Falta cantidad",IF(IFERROR(INDEX(UnidadesBase,MATCH(D29,Unidades,0)),"")<>INDEX(InsBase,MATCH(B29,ListaInsumos,0)),"Unidad incompatible",IF(F29="","Insumo sin compras","OK"))))) -> OK | I29: EJEMPLO: reemplazar por datos reales
A30: Galletas Marineras | B30: Almidón de mandioca | C30: 100 | D30: g | E30: =IF(OR(C30="",D30=""),"",IFERROR(C30*INDEX(UnidadesFactor,MATCH(D30,Unidades,0)),"")) -> 100 | F30: =IF(B30="","",IFERROR(INDEX(InsCosto,MATCH(B30,ListaInsumos,0)),"")) -> 3.5 | G30: =IF(AND(A30="",B30=""),"",IF(H30="OK",E30*F30,0)) -> 350 | H30: =IF(AND(A30="",B30=""),"",IF(ISNA(MATCH(B30,ListaInsumos,0)),"Insumo no está en Insumos",IF(C30="","Falta cantidad",IF(IFERROR(INDEX(UnidadesBase,MATCH(D30,Unidades,0)),"")<>INDEX(InsBase,MATCH(B30,ListaInsumos,0)),"Unidad incompatible",IF(F30="","Insumo sin compras","OK"))))) -> OK | I30: EJEMPLO: reemplazar por datos reales
A31: Galletas Marineras | B31: Aceite de oliva | C31: 60 | D31: ml | E31: =IF(OR(C31="",D31=""),"",IFERROR(C31*INDEX(UnidadesFactor,MATCH(D31,Unidades,0)),"")) -> 60 | F31: =IF(B31="","",IFERROR(INDEX(InsCosto,MATCH(B31,ListaInsumos,0)),"")) -> 18 | G31: =IF(AND(A31="",B31=""),"",IF(H31="OK",E31*F31,0)) -> 1080 | H31: =IF(AND(A31="",B31=""),"",IF(ISNA(MATCH(B31,ListaInsumos,0)),"Insumo no está en Insumos",IF(C31="","Falta cantidad",IF(IFERROR(INDEX(UnidadesBase,MATCH(D31,Unidades,0)),"")<>INDEX(InsBase,MATCH(B31,ListaInsumos,0)),"Unidad incompatible",IF(F31="","Insumo sin compras","OK"))))) -> OK | I31: EJEMPLO: reemplazar por datos reales
A32: Galletas Marineras | B32: Sal marina | C32: 5 | D32: g | E32: =IF(OR(C32="",D32=""),"",IFERROR(C32*INDEX(UnidadesFactor,MATCH(D32,Unidades,0)),"")) -> 5 | F32: =IF(B32="","",IFERROR(INDEX(InsCosto,MATCH(B32,ListaInsumos,0)),"")) -> 5 | G32: =IF(AND(A32="",B32=""),"",IF(H32="OK",E32*F32,0)) -> 25 | H32: =IF(AND(A32="",B32=""),"",IF(ISNA(MATCH(B32,ListaInsumos,0)),"Insumo no está en Insumos",IF(C32="","Falta cantidad",IF(IFERROR(INDEX(UnidadesBase,MATCH(D32,Unidades,0)),"")<>INDEX(InsBase,MATCH(B32,ListaInsumos,0)),"Unidad incompatible",IF(F32="","Insumo sin compras","OK"))))) -> OK | I32: EJEMPLO: reemplazar por datos reales
A33: Galletas Marineras | B33: Goma xántica | C33: 5 | D33: g | E33: =IF(OR(C33="",D33=""),"",IFERROR(C33*INDEX(UnidadesFactor,MATCH(D33,Unidades,0)),"")) -> 5 | F33: =IF(B33="","",IFERROR(INDEX(InsCosto,MATCH(B33,ListaInsumos,0)),"")) -> 60 | G33: =IF(AND(A33="",B33=""),"",IF(H33="OK",E33*F33,0)) -> 300 | H33: =IF(AND(A33="",B33=""),"",IF(ISNA(MATCH(B33,ListaInsumos,0)),"Insumo no está en Insumos",IF(C33="","Falta cantidad",IF(IFERROR(INDEX(UnidadesBase,MATCH(D33,Unidades,0)),"")<>INDEX(InsBase,MATCH(B33,ListaInsumos,0)),"Unidad incompatible",IF(F33="","Insumo sin compras","OK"))))) -> OK | I33: EJEMPLO: reemplazar por datos reales
A34: Galletas Marineras | B34: Polvo leudante | C34: 8 | D34: g | E34: =IF(OR(C34="",D34=""),"",IFERROR(C34*INDEX(UnidadesFactor,MATCH(D34,Unidades,0)),"")) -> 8 | F34: =IF(B34="","",IFERROR(INDEX(InsCosto,MATCH(B34,ListaInsumos,0)),"")) -> 15 | G34: =IF(AND(A34="",B34=""),"",IF(H34="OK",E34*F34,0)) -> 120 | H34: =IF(AND(A34="",B34=""),"",IF(ISNA(MATCH(B34,ListaInsumos,0)),"Insumo no está en Insumos",IF(C34="","Falta cantidad",IF(IFERROR(INDEX(UnidadesBase,MATCH(D34,Unidades,0)),"")<>INDEX(InsBase,MATCH(B34,ListaInsumos,0)),"Unidad incompatible",IF(F34="","Insumo sin compras","OK"))))) -> OK | I34: EJEMPLO: reemplazar por datos reales
A35: Crakers de Mijo y Cebolla | B35: Mijo | D35: g | E35: =IF(OR(C35="",D35=""),"",IFERROR(C35*INDEX(UnidadesFactor,MATCH(D35,Unidades,0)),"")) | F35: =IF(B35="","",IFERROR(INDEX(InsCosto,MATCH(B35,ListaInsumos,0)),"")) | G35: =IF(AND(A35="",B35=""),"",IF(H35="OK",E35*F35,0)) -> 0 | H35: =IF(AND(A35="",B35=""),"",IF(ISNA(MATCH(B35,ListaInsumos,0)),"Insumo no está en Insumos",IF(C35="","Falta cantidad",IF(IFERROR(INDEX(UnidadesBase,MATCH(D35,Unidades,0)),"")<>INDEX(InsBase,MATCH(B35,ListaInsumos,0)),"Unidad incompatible",IF(F35="","Insumo sin compras","OK"))))) -> Falta cantidad
A36: Crakers de Mijo y Cebolla | B36: Cebolla en polvo | D36: g | E36: =IF(OR(C36="",D36=""),"",IFERROR(C36*INDEX(UnidadesFactor,MATCH(D36,Unidades,0)),"")) | F36: =IF(B36="","",IFERROR(INDEX(InsCosto,MATCH(B36,ListaInsumos,0)),"")) | G36: =IF(AND(A36="",B36=""),"",IF(H36="OK",E36*F36,0)) -> 0 | H36: =IF(AND(A36="",B36=""),"",IF(ISNA(MATCH(B36,ListaInsumos,0)),"Insumo no está en Insumos",IF(C36="","Falta cantidad",IF(IFERROR(INDEX(UnidadesBase,MATCH(D36,Unidades,0)),"")<>INDEX(InsBase,MATCH(B36,ListaInsumos,0)),"Unidad incompatible",IF(F36="","Insumo sin compras","OK"))))) -> Falta cantidad
A37: Crakers de Mijo y Cebolla | B37: Pimienta negra | D37: g | E37: =IF(OR(C37="",D37=""),"",IFERROR(C37*INDEX(UnidadesFactor,MATCH(D37,Unidades,0)),"")) | F37: =IF(B37="","",IFERROR(INDEX(InsCosto,MATCH(B37,ListaInsumos,0)),"")) | G37: =IF(AND(A37="",B37=""),"",IF(H37="OK",E37*F37,0)) -> 0 | H37: =IF(AND(A37="",B37=""),"",IF(ISNA(MATCH(B37,ListaInsumos,0)),"Insumo no está en Insumos",IF(C37="","Falta cantidad",IF(IFERROR(INDEX(UnidadesBase,MATCH(D37,Unidades,0)),"")<>INDEX(InsBase,MATCH(B37,ListaInsumos,0)),"Unidad incompatible",IF(F37="","Insumo sin compras","OK"))))) -> Falta cantidad
A38: Crakers de Mijo y Cebolla | B38: Cúrcuma | D38: g | E38: =IF(OR(C38="",D38=""),"",IFERROR(C38*INDEX(UnidadesFactor,MATCH(D38,Unidades,0)),"")) | F38: =IF(B38="","",IFERROR(INDEX(InsCosto,MATCH(B38,ListaInsumos,0)),"")) | G38: =IF(AND(A38="",B38=""),"",IF(H38="OK",E38*F38,0)) -> 0 | H38: =IF(AND(A38="",B38=""),"",IF(ISNA(MATCH(B38,ListaInsumos,0)),"Insumo no está en Insumos",IF(C38="","Falta cantidad",IF(IFERROR(INDEX(UnidadesBase,MATCH(D38,Unidades,0)),"")<>INDEX(InsBase,MATCH(B38,ListaInsumos,0)),"Unidad incompatible",IF(F38="","Insumo sin compras","OK"))))) -> Falta cantidad
A39: Crakers de Mijo y Cebolla | B39: Aceite de oliva | D39: ml | E39: =IF(OR(C39="",D39=""),"",IFERROR(C39*INDEX(UnidadesFactor,MATCH(D39,Unidades,0)),"")) | F39: =IF(B39="","",IFERROR(INDEX(InsCosto,MATCH(B39,ListaInsumos,0)),"")) -> 18 | G39: =IF(AND(A39="",B39=""),"",IF(H39="OK",E39*F39,0)) -> 0 | H39: =IF(AND(A39="",B39=""),"",IF(ISNA(MATCH(B39,ListaInsumos,0)),"Insumo no está en Insumos",IF(C39="","Falta cantidad",IF(IFERROR(INDEX(UnidadesBase,MATCH(D39,Unidades,0)),"")<>INDEX(InsBase,MATCH(B39,ListaInsumos,0)),"Unidad incompatible",IF(F39="","Insumo sin compras","OK"))))) -> Falta cantidad
A40: Crakers de Mijo y Cebolla | B40: Sal marina | D40: g | E40: =IF(OR(C40="",D40=""),"",IFERROR(C40*INDEX(UnidadesFactor,MATCH(D40,Unidades,0)),"")) | F40: =IF(B40="","",IFERROR(INDEX(InsCosto,MATCH(B40,ListaInsumos,0)),"")) -> 5 | G40: =IF(AND(A40="",B40=""),"",IF(H40="OK",E40*F40,0)) -> 0 | H40: =IF(AND(A40="",B40=""),"",IF(ISNA(MATCH(B40,ListaInsumos,0)),"Insumo no está en Insumos",IF(C40="","Falta cantidad",IF(IFERROR(INDEX(UnidadesBase,MATCH(D40,Unidades,0)),"")<>INDEX(InsBase,MATCH(B40,ListaInsumos,0)),"Unidad incompatible",IF(F40="","Insumo sin compras","OK"))))) -> Falta cantidad
A41: Crakers de Mijo y Cebolla | B41: Goma xántica | D41: g | E41: =IF(OR(C41="",D41=""),"",IFERROR(C41*INDEX(UnidadesFactor,MATCH(D41,Unidades,0)),"")) | F41: =IF(B41="","",IFERROR(INDEX(InsCosto,MATCH(B41,ListaInsumos,0)),"")) -> 60 | G41: =IF(AND(A41="",B41=""),"",IF(H41="OK",E41*F41,0)) -> 0 | H41: =IF(AND(A41="",B41=""),"",IF(ISNA(MATCH(B41,ListaInsumos,0)),"Insumo no está en Insumos",IF(C41="","Falta cantidad",IF(IFERROR(INDEX(UnidadesBase,MATCH(D41,Unidades,0)),"")<>INDEX(InsBase,MATCH(B41,ListaInsumos,0)),"Unidad incompatible",IF(F41="","Insumo sin compras","OK"))))) -> Falta cantidad
A42: Palitos de Batata y Romero | B42: Batata | D42: g | E42: =IF(OR(C42="",D42=""),"",IFERROR(C42*INDEX(UnidadesFactor,MATCH(D42,Unidades,0)),"")) | F42: =IF(B42="","",IFERROR(INDEX(InsCosto,MATCH(B42,ListaInsumos,0)),"")) | G42: =IF(AND(A42="",B42=""),"",IF(H42="OK",E42*F42,0)) -> 0 | H42: =IF(AND(A42="",B42=""),"",IF(ISNA(MATCH(B42,ListaInsumos,0)),"Insumo no está en Insumos",IF(C42="","Falta cantidad",IF(IFERROR(INDEX(UnidadesBase,MATCH(D42,Unidades,0)),"")<>INDEX(InsBase,MATCH(B42,ListaInsumos,0)),"Unidad incompatible",IF(F42="","Insumo sin compras","OK"))))) -> Falta cantidad
A43: Palitos de Batata y Romero | B43: Romero | D43: g | E43: =IF(OR(C43="",D43=""),"",IFERROR(C43*INDEX(UnidadesFactor,MATCH(D43,Unidades,0)),"")) | F43: =IF(B43="","",IFERROR(INDEX(InsCosto,MATCH(B43,ListaInsumos,0)),"")) | G43: =IF(AND(A43="",B43=""),"",IF(H43="OK",E43*F43,0)) -> 0 | H43: =IF(AND(A43="",B43=""),"",IF(ISNA(MATCH(B43,ListaInsumos,0)),"Insumo no está en Insumos",IF(C43="","Falta cantidad",IF(IFERROR(INDEX(UnidadesBase,MATCH(D43,Unidades,0)),"")<>INDEX(InsBase,MATCH(B43,ListaInsumos,0)),"Unidad incompatible",IF(F43="","Insumo sin compras","OK"))))) -> Falta cantidad
A44: Palitos de Batata y Romero | B44: Aceite de oliva | D44: ml | E44: =IF(OR(C44="",D44=""),"",IFERROR(C44*INDEX(UnidadesFactor,MATCH(D44,Unidades,0)),"")) | F44: =IF(B44="","",IFERROR(INDEX(InsCosto,MATCH(B44,ListaInsumos,0)),"")) -> 18 | G44: =IF(AND(A44="",B44=""),"",IF(H44="OK",E44*F44,0)) -> 0 | H44: =IF(AND(A44="",B44=""),"",IF(ISNA(MATCH(B44,ListaInsumos,0)),"Insumo no está en Insumos",IF(C44="","Falta cantidad",IF(IFERROR(INDEX(UnidadesBase,MATCH(D44,Unidades,0)),"")<>INDEX(InsBase,MATCH(B44,ListaInsumos,0)),"Unidad incompatible",IF(F44="","Insumo sin compras","OK"))))) -> Falta cantidad
A45: Palitos de Batata y Romero | B45: Sal marina | D45: g | E45: =IF(OR(C45="",D45=""),"",IFERROR(C45*INDEX(UnidadesFactor,MATCH(D45,Unidades,0)),"")) | F45: =IF(B45="","",IFERROR(INDEX(InsCosto,MATCH(B45,ListaInsumos,0)),"")) -> 5 | G45: =IF(AND(A45="",B45=""),"",IF(H45="OK",E45*F45,0)) -> 0 | H45: =IF(AND(A45="",B45=""),"",IF(ISNA(MATCH(B45,ListaInsumos,0)),"Insumo no está en Insumos",IF(C45="","Falta cantidad",IF(IFERROR(INDEX(UnidadesBase,MATCH(D45,Unidades,0)),"")<>INDEX(InsBase,MATCH(B45,ListaInsumos,0)),"Unidad incompatible",IF(F45="","Insumo sin compras","OK"))))) -> Falta cantidad
A46: Palitos de Batata y Romero | B46: Goma xántica | D46: g | E46: =IF(OR(C46="",D46=""),"",IFERROR(C46*INDEX(UnidadesFactor,MATCH(D46,Unidades,0)),"")) | F46: =IF(B46="","",IFERROR(INDEX(InsCosto,MATCH(B46,ListaInsumos,0)),"")) -> 60 | G46: =IF(AND(A46="",B46=""),"",IF(H46="OK",E46*F46,0)) -> 0 | H46: =IF(AND(A46="",B46=""),"",IF(ISNA(MATCH(B46,ListaInsumos,0)),"Insumo no está en Insumos",IF(C46="","Falta cantidad",IF(IFERROR(INDEX(UnidadesBase,MATCH(D46,Unidades,0)),"")<>INDEX(InsBase,MATCH(B46,ListaInsumos,0)),"Unidad incompatible",IF(F46="","Insumo sin compras","OK"))))) -> Falta cantidad
... A84: Bastoncitos de Zanahoria y Remolacha | B84: Nuez moscada | D84: g | E84: =IF(OR(C84="",D84=""),"",IFERROR(C84*INDEX(UnidadesFactor,MATCH(D84,Unidades,0)),"")) | F84: =IF(B84="","",IFERROR(INDEX(InsCosto,MATCH(B84,ListaInsumos,0)),"")) | G84: =IF(AND(A84="",B84=""),"",IF(H84="OK",E84*F84,0)) -> 0 | H84: =IF(AND(A84="",B84=""),"",IF(ISNA(MATCH(B84,ListaInsumos,0)),"Insumo no está en Insumos",IF(C84="","Falta cantidad",IF(IFERROR(INDEX(UnidadesBase,MATCH(D84,Unidades,0)),"")<>INDEX(InsBase,MATCH(B84,ListaInsumos,0)),"Unidad incompatible",IF(F84="","Insumo sin compras","OK"))))) -> Falta cantidad
A85: Azúcar de coco fraccionada | B85: Azúcar de coco | C85: 200 | D85: g | E85: =IF(OR(C85="",D85=""),"",IFERROR(C85*INDEX(UnidadesFactor,MATCH(D85,Unidades,0)),"")) -> 200 | F85: =IF(B85="","",IFERROR(INDEX(InsCosto,MATCH(B85,ListaInsumos,0)),"")) | G85: =IF(AND(A85="",B85=""),"",IF(H85="OK",E85*F85,0)) -> 0 | H85: =IF(AND(A85="",B85=""),"",IF(ISNA(MATCH(B85,ListaInsumos,0)),"Insumo no está en Insumos",IF(C85="","Falta cantidad",IF(IFERROR(INDEX(UnidadesBase,MATCH(D85,Unidades,0)),"")<>INDEX(InsBase,MATCH(B85,ListaInsumos,0)),"Unidad incompatible",IF(F85="","Insumo sin compras","OK"))))) -> Insumo sin compras
A86: Mermelada (reventa) | B86: Mermelada Lo Artesanal 200 g | C86: 1 | D86: unidad | E86: =IF(OR(C86="",D86=""),"",IFERROR(C86*INDEX(UnidadesFactor,MATCH(D86,Unidades,0)),"")) -> 1 | F86: =IF(B86="","",IFERROR(INDEX(InsCosto,MATCH(B86,ListaInsumos,0)),"")) | G86: =IF(AND(A86="",B86=""),"",IF(H86="OK",E86*F86,0)) -> 0 | H86: =IF(AND(A86="",B86=""),"",IF(ISNA(MATCH(B86,ListaInsumos,0)),"Insumo no está en Insumos",IF(C86="","Falta cantidad",IF(IFERROR(INDEX(UnidadesBase,MATCH(D86,Unidades,0)),"")<>INDEX(InsBase,MATCH(B86,ListaInsumos,0)),"Unidad incompatible",IF(F86="","Insumo sin compras","OK"))))) -> Insumo sin compras
A87: Berenjenas Húngaras (reventa) | B87: Berenjenas Húngaras 150 g | C87: 1 | D87: unidad | E87: =IF(OR(C87="",D87=""),"",IFERROR(C87*INDEX(UnidadesFactor,MATCH(D87,Unidades,0)),"")) -> 1 | F87: =IF(B87="","",IFERROR(INDEX(InsCosto,MATCH(B87,ListaInsumos,0)),"")) | G87: =IF(AND(A87="",B87=""),"",IF(H87="OK",E87*F87,0)) -> 0 | H87: =IF(AND(A87="",B87=""),"",IF(ISNA(MATCH(B87,ListaInsumos,0)),"Insumo no está en Insumos",IF(C87="","Falta cantidad",IF(IFERROR(INDEX(UnidadesBase,MATCH(D87,Unidades,0)),"")<>INDEX(InsBase,MATCH(B87,ListaInsumos,0)),"Unidad incompatible",IF(F87="","Insumo sin compras","OK"))))) -> Insumo sin compras
A88: Aceitunas Condimentadas (reventa) | B88: Aceitunas Condimentadas 300 g | C88: 1 | D88: unidad | E88: =IF(OR(C88="",D88=""),"",IFERROR(C88*INDEX(UnidadesFactor,MATCH(D88,Unidades,0)),"")) -> 1 | F88: =IF(B88="","",IFERROR(INDEX(InsCosto,MATCH(B88,ListaInsumos,0)),"")) | G88: =IF(AND(A88="",B88=""),"",IF(H88="OK",E88*F88,0)) -> 0 | H88: =IF(AND(A88="",B88=""),"",IF(ISNA(MATCH(B88,ListaInsumos,0)),"Insumo no está en Insumos",IF(C88="","Falta cantidad",IF(IFERROR(INDEX(UnidadesBase,MATCH(D88,Unidades,0)),"")<>INDEX(InsBase,MATCH(B88,ListaInsumos,0)),"Unidad incompatible",IF(F88="","Insumo sin compras","OK"))))) -> Insumo sin compras
A89: Berenjenas en Escabeche (reventa) | B89: Berenjenas en Escabeche 200 g | C89: 1 | D89: unidad | E89: =IF(OR(C89="",D89=""),"",IFERROR(C89*INDEX(UnidadesFactor,MATCH(D89,Unidades,0)),"")) -> 1 | F89: =IF(B89="","",IFERROR(INDEX(InsCosto,MATCH(B89,ListaInsumos,0)),"")) | G89: =IF(AND(A89="",B89=""),"",IF(H89="OK",E89*F89,0)) -> 0 | H89: =IF(AND(A89="",B89=""),"",IF(ISNA(MATCH(B89,ListaInsumos,0)),"Insumo no está en Insumos",IF(C89="","Falta cantidad",IF(IFERROR(INDEX(UnidadesBase,MATCH(D89,Unidades,0)),"")<>INDEX(InsBase,MATCH(B89,ListaInsumos,0)),"Unidad incompatible",IF(F89="","Insumo sin compras","OK"))))) -> Insumo sin compras
A90: Berenjenas y Pera (reventa) | B90: Berenjenas y Pera 200 g | C90: 1 | D90: unidad | E90: =IF(OR(C90="",D90=""),"",IFERROR(C90*INDEX(UnidadesFactor,MATCH(D90,Unidades,0)),"")) -> 1 | F90: =IF(B90="","",IFERROR(INDEX(InsCosto,MATCH(B90,ListaInsumos,0)),"")) | G90: =IF(AND(A90="",B90=""),"",IF(H90="OK",E90*F90,0)) -> 0 | H90: =IF(AND(A90="",B90=""),"",IF(ISNA(MATCH(B90,ListaInsumos,0)),"Insumo no está en Insumos",IF(C90="","Falta cantidad",IF(IFERROR(INDEX(UnidadesBase,MATCH(D90,Unidades,0)),"")<>INDEX(InsBase,MATCH(B90,ListaInsumos,0)),"Unidad incompatible",IF(F90="","Insumo sin compras","OK"))))) -> Insumo sin compras
E91: =IF(OR(C91="",D91=""),"",IFERROR(C91*INDEX(UnidadesFactor,MATCH(D91,Unidades,0)),"")) | F91: =IF(B91="","",IFERROR(INDEX(InsCosto,MATCH(B91,ListaInsumos,0)),"")) | G91: =IF(AND(A91="",B91=""),"",IF(H91="OK",E91*F91,0)) | H91: =IF(AND(A91="",B91=""),"",IF(ISNA(MATCH(B91,ListaInsumos,0)),"Insumo no está en Insumos",IF(C91="","Falta cantidad",IF(IFERROR(INDEX(UnidadesBase,MATCH(D91,Unidades,0)),"")<>INDEX(InsBase,MATCH(B91,ListaInsumos,0)),"Unidad incompatible",IF(F91="","Insumo sin compras","OK")))))
E92: =IF(OR(C92="",D92=""),"",IFERROR(C92*INDEX(UnidadesFactor,MATCH(D92,Unidades,0)),"")) | F92: =IF(B92="","",IFERROR(INDEX(InsCosto,MATCH(B92,ListaInsumos,0)),"")) | G92: =IF(AND(A92="",B92=""),"",IF(H92="OK",E92*F92,0)) | H92: =IF(AND(A92="",B92=""),"",IF(ISNA(MATCH(B92,ListaInsumos,0)),"Insumo no está en Insumos",IF(C92="","Falta cantidad",IF(IFERROR(INDEX(UnidadesBase,MATCH(D92,Unidades,0)),"")<>INDEX(InsBase,MATCH(B92,ListaInsumos,0)),"Unidad incompatible",IF(F92="","Insumo sin compras","OK")))))
E93: =IF(OR(C93="",D93=""),"",IFERROR(C93*INDEX(UnidadesFactor,MATCH(D93,Unidades,0)),"")) | F93: =IF(B93="","",IFERROR(INDEX(InsCosto,MATCH(B93,ListaInsumos,0)),"")) | G93: =IF(AND(A93="",B93=""),"",IF(H93="OK",E93*F93,0)) | H93: =IF(AND(A93="",B93=""),"",IF(ISNA(MATCH(B93,ListaInsumos,0)),"Insumo no está en Insumos",IF(C93="","Falta cantidad",IF(IFERROR(INDEX(UnidadesBase,MATCH(D93,Unidades,0)),"")<>INDEX(InsBase,MATCH(B93,ListaInsumos,0)),"Unidad incompatible",IF(F93="","Insumo sin compras","OK")))))
E94: =IF(OR(C94="",D94=""),"",IFERROR(C94*INDEX(UnidadesFactor,MATCH(D94,Unidades,0)),"")) | F94: =IF(B94="","",IFERROR(INDEX(InsCosto,MATCH(B94,ListaInsumos,0)),"")) | G94: =IF(AND(A94="",B94=""),"",IF(H94="OK",E94*F94,0)) | H94: =IF(AND(A94="",B94=""),"",IF(ISNA(MATCH(B94,ListaInsumos,0)),"Insumo no está en Insumos",IF(C94="","Falta cantidad",IF(IFERROR(INDEX(UnidadesBase,MATCH(D94,Unidades,0)),"")<>INDEX(InsBase,MATCH(B94,ListaInsumos,0)),"Unidad incompatible",IF(F94="","Insumo sin compras","OK")))))
E95: =IF(OR(C95="",D95=""),"",IFERROR(C95*INDEX(UnidadesFactor,MATCH(D95,Unidades,0)),"")) | F95: =IF(B95="","",IFERROR(INDEX(InsCosto,MATCH(B95,ListaInsumos,0)),"")) | G95: =IF(AND(A95="",B95=""),"",IF(H95="OK",E95*F95,0)) | H95: =IF(AND(A95="",B95=""),"",IF(ISNA(MATCH(B95,ListaInsumos,0)),"Insumo no está en Insumos",IF(C95="","Falta cantidad",IF(IFERROR(INDEX(UnidadesBase,MATCH(D95,Unidades,0)),"")<>INDEX(InsBase,MATCH(B95,ListaInsumos,0)),"Unidad incompatible",IF(F95="","Insumo sin compras","OK")))))
E96: =IF(OR(C96="",D96=""),"",IFERROR(C96*INDEX(UnidadesFactor,MATCH(D96,Unidades,0)),"")) | F96: =IF(B96="","",IFERROR(INDEX(InsCosto,MATCH(B96,ListaInsumos,0)),"")) | G96: =IF(AND(A96="",B96=""),"",IF(H96="OK",E96*F96,0)) | H96: =IF(AND(A96="",B96=""),"",IF(ISNA(MATCH(B96,ListaInsumos,0)),"Insumo no está en Insumos",IF(C96="","Falta cantidad",IF(IFERROR(INDEX(UnidadesBase,MATCH(D96,Unidades,0)),"")<>INDEX(InsBase,MATCH(B96,ListaInsumos,0)),"Unidad incompatible",IF(F96="","Insumo sin compras","OK")))))
E97: =IF(OR(C97="",D97=""),"",IFERROR(C97*INDEX(UnidadesFactor,MATCH(D97,Unidades,0)),"")) | F97: =IF(B97="","",IFERROR(INDEX(InsCosto,MATCH(B97,ListaInsumos,0)),"")) | G97: =IF(AND(A97="",B97=""),"",IF(H97="OK",E97*F97,0)) | H97: =IF(AND(A97="",B97=""),"",IF(ISNA(MATCH(B97,ListaInsumos,0)),"Insumo no está en Insumos",IF(C97="","Falta cantidad",IF(IFERROR(INDEX(UnidadesBase,MATCH(D97,Unidades,0)),"")<>INDEX(InsBase,MATCH(B97,ListaInsumos,0)),"Unidad incompatible",IF(F97="","Insumo sin compras","OK")))))
E98: =IF(OR(C98="",D98=""),"",IFERROR(C98*INDEX(UnidadesFactor,MATCH(D98,Unidades,0)),"")) | F98: =IF(B98="","",IFERROR(INDEX(InsCosto,MATCH(B98,ListaInsumos,0)),"")) | G98: =IF(AND(A98="",B98=""),"",IF(H98="OK",E98*F98,0)) | H98: =IF(AND(A98="",B98=""),"",IF(ISNA(MATCH(B98,ListaInsumos,0)),"Insumo no está en Insumos",IF(C98="","Falta cantidad",IF(IFERROR(INDEX(UnidadesBase,MATCH(D98,Unidades,0)),"")<>INDEX(InsBase,MATCH(B98,ListaInsumos,0)),"Unidad incompatible",IF(F98="","Insumo sin compras","OK")))))
E99: =IF(OR(C99="",D99=""),"",IFERROR(C99*INDEX(UnidadesFactor,MATCH(D99,Unidades,0)),"")) | F99: =IF(B99="","",IFERROR(INDEX(InsCosto,MATCH(B99,ListaInsumos,0)),"")) | G99: =IF(AND(A99="",B99=""),"",IF(H99="OK",E99*F99,0)) | H99: =IF(AND(A99="",B99=""),"",IF(ISNA(MATCH(B99,ListaInsumos,0)),"Insumo no está en Insumos",IF(C99="","Falta cantidad",IF(IFERROR(INDEX(UnidadesBase,MATCH(D99,Unidades,0)),"")<>INDEX(InsBase,MATCH(B99,ListaInsumos,0)),"Unidad incompatible",IF(F99="","Insumo sin compras","OK")))))
E100: =IF(OR(C100="",D100=""),"",IFERROR(C100*INDEX(UnidadesFactor,MATCH(D100,Unidades,0)),"")) | F100: =IF(B100="","",IFERROR(INDEX(InsCosto,MATCH(B100,ListaInsumos,0)),"")) | G100: =IF(AND(A100="",B100=""),"",IF(H100="OK",E100*F100,0)) | H100: =IF(AND(A100="",B100=""),"",IF(ISNA(MATCH(B100,ListaInsumos,0)),"Insumo no está en Insumos",IF(C100="","Falta cantidad",IF(IFERROR(INDEX(UnidadesBase,MATCH(D100,Unidades,0)),"")<>INDEX(InsBase,MATCH(B100,ListaInsumos,0)),"Unidad incompatible",IF(F100="","Insumo sin compras","OK")))))
E101: =IF(OR(C101="",D101=""),"",IFERROR(C101*INDEX(UnidadesFactor,MATCH(D101,Unidades,0)),"")) | F101: =IF(B101="","",IFERROR(INDEX(InsCosto,MATCH(B101,ListaInsumos,0)),"")) | G101: =IF(AND(A101="",B101=""),"",IF(H101="OK",E101*F101,0)) | H101: =IF(AND(A101="",B101=""),"",IF(ISNA(MATCH(B101,ListaInsumos,0)),"Insumo no está en Insumos",IF(C101="","Falta cantidad",IF(IFERROR(INDEX(UnidadesBase,MATCH(D101,Unidades,0)),"")<>INDEX(InsBase,MATCH(B101,ListaInsumos,0)),"Unidad incompatible",IF(F101="","Insumo sin compras","OK")))))
E102: =IF(OR(C102="",D102=""),"",IFERROR(C102*INDEX(UnidadesFactor,MATCH(D102,Unidades,0)),"")) | F102: =IF(B102="","",IFERROR(INDEX(InsCosto,MATCH(B102,ListaInsumos,0)),"")) | G102: =IF(AND(A102="",B102=""),"",IF(H102="OK",E102*F102,0)) | H102: =IF(AND(A102="",B102=""),"",IF(ISNA(MATCH(B102,ListaInsumos,0)),"Insumo no está en Insumos",IF(C102="","Falta cantidad",IF(IFERROR(INDEX(UnidadesBase,MATCH(D102,Unidades,0)),"")<>INDEX(InsBase,MATCH(B102,ListaInsumos,0)),"Unidad incompatible",IF(F102="","Insumo sin compras","OK")))))
... E1000: =IF(OR(C1000="",D1000=""),"",IFERROR(C1000*INDEX(UnidadesFactor,MATCH(D1000,Unidades,0)),"")) | F1000: =IF(B1000="","",IFERROR(INDEX(InsCosto,MATCH(B1000,ListaInsumos,0)),"")) | G1000: =IF(AND(A1000="",B1000=""),"",IF(H1000="OK",E1000*F1000,0)) | H1000: =IF(AND(A1000="",B1000=""),"",IF(ISNA(MATCH(B1000,ListaInsumos,0)),"Insumo no está en Insumos",IF(C1000="","Falta cantidad",IF(IFERROR(INDEX(UnidadesBase,MATCH(D1000,Unidades,0)),"")<>INDEX(InsBase,MATCH(B1000,ListaInsumos,0)),"Unidad incompatible",IF(F1000="","Insumo sin compras","OK")))))

Sheet Costo por Receta
A1: Costo por receta
A2: Cargá cuánto producto terminado sale de cada tanda (pesalo DESPUÉS de hornear/deshidratar: pierde agua). Así se obtiene el costo por gramo real.
A4: Receta | B4: Rendimiento de la tanda (producto terminado) | C4: Unidad del rendimiento | D4: Costo total de ingredientes ($) | E4: Costo por gramo / unidad ($) | F4: Costo por kg ($) | G4: Ingredientes cargados | H4: Estado
A5: Cookies Chips de Chocolate | C5: g | D5: =IF(A5="","",SUMIFS(Recetas!$G$5:$G$1000,Recetas!$A$5:$A$1000,A5)) -> 0 | E5: =IF(OR(A5="",B5="",B5=0),"",D5/B5) | F5: =IF(OR(E5="",C5<>"g"),"",E5*1000) | G5: =IF(A5="","",COUNTIFS(Recetas!$A$5:$A$1000,A5)) -> 7 | H5: =IF(A5="","",IF(G5=0,"Sin ingredientes en Recetas",IF(OR(B5="",B5=0),"Falta rendimiento",IF(COUNTIFS(Recetas!$A$5:$A$1000,A5,Recetas!$H$5:$H$1000,"<>OK")>0,"Revisar: "&COUNTIFS(Recetas!$A$5:$A$1000,A5,Recetas!$H$5:$H$1000,"<>OK")&" ingrediente(s) con aviso","OK")))) -> Falta rendimiento
A6: Pan de Molde con Trigo Sarraceno | B6: 1 | C6: unidad | D6: =IF(A6="","",SUMIFS(Recetas!$G$5:$G$1000,Recetas!$A$5:$A$1000,A6)) -> 0 | E6: =IF(OR(A6="",B6="",B6=0),"",D6/B6) -> 0 | F6: =IF(OR(E6="",C6<>"g"),"",E6*1000) | G6: =IF(A6="","",COUNTIFS(Recetas!$A$5:$A$1000,A6)) -> 8 | H6: =IF(A6="","",IF(G6=0,"Sin ingredientes en Recetas",IF(OR(B6="",B6=0),"Falta rendimiento",IF(COUNTIFS(Recetas!$A$5:$A$1000,A6,Recetas!$H$5:$H$1000,"<>OK")>0,"Revisar: "&COUNTIFS(Recetas!$A$5:$A$1000,A6,Recetas!$H$5:$H$1000,"<>OK")&" ingrediente(s) con aviso","OK")))) -> Revisar: 8 ingrediente(s) con aviso
A7: Tablitas de Trigo Sarraceno y Semillas | C7: g | D7: =IF(A7="","",SUMIFS(Recetas!$G$5:$G$1000,Recetas!$A$5:$A$1000,A7)) -> 0 | E7: =IF(OR(A7="",B7="",B7=0),"",D7/B7) | F7: =IF(OR(E7="",C7<>"g"),"",E7*1000) | G7: =IF(A7="","",COUNTIFS(Recetas!$A$5:$A$1000,A7)) -> 8 | H7: =IF(A7="","",IF(G7=0,"Sin ingredientes en Recetas",IF(OR(B7="",B7=0),"Falta rendimiento",IF(COUNTIFS(Recetas!$A$5:$A$1000,A7,Recetas!$H$5:$H$1000,"<>OK")>0,"Revisar: "&COUNTIFS(Recetas!$A$5:$A$1000,A7,Recetas!$H$5:$H$1000,"<>OK")&" ingrediente(s) con aviso","OK")))) -> Falta rendimiento
A8: Galletas Marineras | B8: 500 | C8: g | D8: =IF(A8="","",SUMIFS(Recetas!$G$5:$G$1000,Recetas!$A$5:$A$1000,A8)) -> 2895 | E8: =IF(OR(A8="",B8="",B8=0),"",D8/B8) -> 5.79 | F8: =IF(OR(E8="",C8<>"g"),"",E8*1000) -> 5790 | G8: =IF(A8="","",COUNTIFS(Recetas!$A$5:$A$1000,A8)) -> 7 | H8: =IF(A8="","",IF(G8=0,"Sin ingredientes en Recetas",IF(OR(B8="",B8=0),"Falta rendimiento",IF(COUNTIFS(Recetas!$A$5:$A$1000,A8,Recetas!$H$5:$H$1000,"<>OK")>0,"Revisar: "&COUNTIFS(Recetas!$A$5:$A$1000,A8,Recetas!$H$5:$H$1000,"<>OK")&" ingrediente(s) con aviso","OK")))) -> OK
A9: Crakers de Mijo y Cebolla | C9: g | D9: =IF(A9="","",SUMIFS(Recetas!$G$5:$G$1000,Recetas!$A$5:$A$1000,A9)) -> 0 | E9: =IF(OR(A9="",B9="",B9=0),"",D9/B9) | F9: =IF(OR(E9="",C9<>"g"),"",E9*1000) | G9: =IF(A9="","",COUNTIFS(Recetas!$A$5:$A$1000,A9)) -> 7 | H9: =IF(A9="","",IF(G9=0,"Sin ingredientes en Recetas",IF(OR(B9="",B9=0),"Falta rendimiento",IF(COUNTIFS(Recetas!$A$5:$A$1000,A9,Recetas!$H$5:$H$1000,"<>OK")>0,"Revisar: "&COUNTIFS(Recetas!$A$5:$A$1000,A9,Recetas!$H$5:$H$1000,"<>OK")&" ingrediente(s) con aviso","OK")))) -> Falta rendimiento
A10: Palitos de Batata y Romero | C10: g | D10: =IF(A10="","",SUMIFS(Recetas!$G$5:$G$1000,Recetas!$A$5:$A$1000,A10)) -> 0 | E10: =IF(OR(A10="",B10="",B10=0),"",D10/B10) | F10: =IF(OR(E10="",C10<>"g"),"",E10*1000) | G10: =IF(A10="","",COUNTIFS(Recetas!$A$5:$A$1000,A10)) -> 5 | H10: =IF(A10="","",IF(G10=0,"Sin ingredientes en Recetas",IF(OR(B10="",B10=0),"Falta rendimiento",IF(COUNTIFS(Recetas!$A$5:$A$1000,A10,Recetas!$H$5:$H$1000,"<>OK")>0,"Revisar: "&COUNTIFS(Recetas!$A$5:$A$1000,A10,Recetas!$H$5:$H$1000,"<>OK")&" ingrediente(s) con aviso","OK")))) -> Falta rendimiento
A11: Garbancitos Crocantes | C11: g | D11: =IF(A11="","",SUMIFS(Recetas!$G$5:$G$1000,Recetas!$A$5:$A$1000,A11)) -> 0 | E11: =IF(OR(A11="",B11="",B11=0),"",D11/B11) | F11: =IF(OR(E11="",C11<>"g"),"",E11*1000) | G11: =IF(A11="","",COUNTIFS(Recetas!$A$5:$A$1000,A11)) -> 6 | H11: =IF(A11="","",IF(G11=0,"Sin ingredientes en Recetas",IF(OR(B11="",B11=0),"Falta rendimiento",IF(COUNTIFS(Recetas!$A$5:$A$1000,A11,Recetas!$H$5:$H$1000,"<>OK")>0,"Revisar: "&COUNTIFS(Recetas!$A$5:$A$1000,A11,Recetas!$H$5:$H$1000,"<>OK")&" ingrediente(s) con aviso","OK")))) -> Falta rendimiento
A12: Triangulitos de Lentejas Turcas | C12: g | D12: =IF(A12="","",SUMIFS(Recetas!$G$5:$G$1000,Recetas!$A$5:$A$1000,A12)) -> 0 | E12: =IF(OR(A12="",B12="",B12=0),"",D12/B12) | F12: =IF(OR(E12="",C12<>"g"),"",E12*1000) | G12: =IF(A12="","",COUNTIFS(Recetas!$A$5:$A$1000,A12)) -> 7 | H12: =IF(A12="","",IF(G12=0,"Sin ingredientes en Recetas",IF(OR(B12="",B12=0),"Falta rendimiento",IF(COUNTIFS(Recetas!$A$5:$A$1000,A12,Recetas!$H$5:$H$1000,"<>OK")>0,"Revisar: "&COUNTIFS(Recetas!$A$5:$A$1000,A12,Recetas!$H$5:$H$1000,"<>OK")&" ingrediente(s) con aviso","OK")))) -> Falta rendimiento
A13: Papas al Orégano | C13: g | D13: =IF(A13="","",SUMIFS(Recetas!$G$5:$G$1000,Recetas!$A$5:$A$1000,A13)) -> 0 | E13: =IF(OR(A13="",B13="",B13=0),"",D13/B13) | F13: =IF(OR(E13="",C13<>"g"),"",E13*1000) | G13: =IF(A13="","",COUNTIFS(Recetas!$A$5:$A$1000,A13)) -> 4 | H13: =IF(A13="","",IF(G13=0,"Sin ingredientes en Recetas",IF(OR(B13="",B13=0),"Falta rendimiento",IF(COUNTIFS(Recetas!$A$5:$A$1000,A13,Recetas!$H$5:$H$1000,"<>OK")>0,"Revisar: "&COUNTIFS(Recetas!$A$5:$A$1000,A13,Recetas!$H$5:$H$1000,"<>OK")&" ingrediente(s) con aviso","OK")))) -> Falta rendimiento
A14: Grisines a la Provenzal | C14: g | D14: =IF(A14="","",SUMIFS(Recetas!$G$5:$G$1000,Recetas!$A$5:$A$1000,A14)) -> 0 | E14: =IF(OR(A14="",B14="",B14=0),"",D14/B14) | F14: =IF(OR(E14="",C14<>"g"),"",E14*1000) | G14: =IF(A14="","",COUNTIFS(Recetas!$A$5:$A$1000,A14)) -> 7 | H14: =IF(A14="","",IF(G14=0,"Sin ingredientes en Recetas",IF(OR(B14="",B14=0),"Falta rendimiento",IF(COUNTIFS(Recetas!$A$5:$A$1000,A14,Recetas!$H$5:$H$1000,"<>OK")>0,"Revisar: "&COUNTIFS(Recetas!$A$5:$A$1000,A14,Recetas!$H$5:$H$1000,"<>OK")&" ingrediente(s) con aviso","OK")))) -> Falta rendimiento
A15: Rueditas de Naranja y Chocolate | C15: g | D15: =IF(A15="","",SUMIFS(Recetas!$G$5:$G$1000,Recetas!$A$5:$A$1000,A15)) -> 0 | E15: =IF(OR(A15="",B15="",B15=0),"",D15/B15) | F15: =IF(OR(E15="",C15<>"g"),"",E15*1000) | G15: =IF(A15="","",COUNTIFS(Recetas!$A$5:$A$1000,A15)) -> 7 | H15: =IF(A15="","",IF(G15=0,"Sin ingredientes en Recetas",IF(OR(B15="",B15=0),"Falta rendimiento",IF(COUNTIFS(Recetas!$A$5:$A$1000,A15,Recetas!$H$5:$H$1000,"<>OK")>0,"Revisar: "&COUNTIFS(Recetas!$A$5:$A$1000,A15,Recetas!$H$5:$H$1000,"<>OK")&" ingrediente(s) con aviso","OK")))) -> Falta rendimiento
A16: Bastoncitos de Zanahoria y Remolacha | C16: g | D16: =IF(A16="","",SUMIFS(Recetas!$G$5:$G$1000,Recetas!$A$5:$A$1000,A16)) -> 0 | E16: =IF(OR(A16="",B16="",B16=0),"",D16/B16) | F16: =IF(OR(E16="",C16<>"g"),"",E16*1000) | G16: =IF(A16="","",COUNTIFS(Recetas!$A$5:$A$1000,A16)) -> 7 | H16: =IF(A16="","",IF(G16=0,"Sin ingredientes en Recetas",IF(OR(B16="",B16=0),"Falta rendimiento",IF(COUNTIFS(Recetas!$A$5:$A$1000,A16,Recetas!$H$5:$H$1000,"<>OK")>0,"Revisar: "&COUNTIFS(Recetas!$A$5:$A$1000,A16,Recetas!$H$5:$H$1000,"<>OK")&" ingrediente(s) con aviso","OK")))) -> Falta rendimiento
A17: Azúcar de coco fraccionada | B17: 200 | C17: g | D17: =IF(A17="","",SUMIFS(Recetas!$G$5:$G$1000,Recetas!$A$5:$A$1000,A17)) -> 0 | E17: =IF(OR(A17="",B17="",B17=0),"",D17/B17) -> 0 | F17: =IF(OR(E17="",C17<>"g"),"",E17*1000) -> 0 | G17: =IF(A17="","",COUNTIFS(Recetas!$A$5:$A$1000,A17)) -> 1 | H17: =IF(A17="","",IF(G17=0,"Sin ingredientes en Recetas",IF(OR(B17="",B17=0),"Falta rendimiento",IF(COUNTIFS(Recetas!$A$5:$A$1000,A17,Recetas!$H$5:$H$1000,"<>OK")>0,"Revisar: "&COUNTIFS(Recetas!$A$5:$A$1000,A17,Recetas!$H$5:$H$1000,"<>OK")&" ingrediente(s) con aviso","OK")))) -> Revisar: 1 ingrediente(s) con aviso
A18: Mermelada (reventa) | B18: 1 | C18: unidad | D18: =IF(A18="","",SUMIFS(Recetas!$G$5:$G$1000,Recetas!$A$5:$A$1000,A18)) -> 0 | E18: =IF(OR(A18="",B18="",B18=0),"",D18/B18) -> 0 | F18: =IF(OR(E18="",C18<>"g"),"",E18*1000) | G18: =IF(A18="","",COUNTIFS(Recetas!$A$5:$A$1000,A18)) -> 1 | H18: =IF(A18="","",IF(G18=0,"Sin ingredientes en Recetas",IF(OR(B18="",B18=0),"Falta rendimiento",IF(COUNTIFS(Recetas!$A$5:$A$1000,A18,Recetas!$H$5:$H$1000,"<>OK")>0,"Revisar: "&COUNTIFS(Recetas!$A$5:$A$1000,A18,Recetas!$H$5:$H$1000,"<>OK")&" ingrediente(s) con aviso","OK")))) -> Revisar: 1 ingrediente(s) con aviso
A19: Berenjenas Húngaras (reventa) | B19: 1 | C19: unidad | D19: =IF(A19="","",SUMIFS(Recetas!$G$5:$G$1000,Recetas!$A$5:$A$1000,A19)) -> 0 | E19: =IF(OR(A19="",B19="",B19=0),"",D19/B19) -> 0 | F19: =IF(OR(E19="",C19<>"g"),"",E19*1000) | G19: =IF(A19="","",COUNTIFS(Recetas!$A$5:$A$1000,A19)) -> 1 | H19: =IF(A19="","",IF(G19=0,"Sin ingredientes en Recetas",IF(OR(B19="",B19=0),"Falta rendimiento",IF(COUNTIFS(Recetas!$A$5:$A$1000,A19,Recetas!$H$5:$H$1000,"<>OK")>0,"Revisar: "&COUNTIFS(Recetas!$A$5:$A$1000,A19,Recetas!$H$5:$H$1000,"<>OK")&" ingrediente(s) con aviso","OK")))) -> Revisar: 1 ingrediente(s) con aviso
A20: Aceitunas Condimentadas (reventa) | B20: 1 | C20: unidad | D20: =IF(A20="","",SUMIFS(Recetas!$G$5:$G$1000,Recetas!$A$5:$A$1000,A20)) -> 0 | E20: =IF(OR(A20="",B20="",B20=0),"",D20/B20) -> 0 | F20: =IF(OR(E20="",C20<>"g"),"",E20*1000) | G20: =IF(A20="","",COUNTIFS(Recetas!$A$5:$A$1000,A20)) -> 1 | H20: =IF(A20="","",IF(G20=0,"Sin ingredientes en Recetas",IF(OR(B20="",B20=0),"Falta rendimiento",IF(COUNTIFS(Recetas!$A$5:$A$1000,A20,Recetas!$H$5:$H$1000,"<>OK")>0,"Revisar: "&COUNTIFS(Recetas!$A$5:$A$1000,A20,Recetas!$H$5:$H$1000,"<>OK")&" ingrediente(s) con aviso","OK")))) -> Revisar: 1 ingrediente(s) con aviso
A21: Berenjenas en Escabeche (reventa) | B21: 1 | C21: unidad | D21: =IF(A21="","",SUMIFS(Recetas!$G$5:$G$1000,Recetas!$A$5:$A$1000,A21)) -> 0 | E21: =IF(OR(A21="",B21="",B21=0),"",D21/B21) -> 0 | F21: =IF(OR(E21="",C21<>"g"),"",E21*1000) | G21: =IF(A21="","",COUNTIFS(Recetas!$A$5:$A$1000,A21)) -> 1 | H21: =IF(A21="","",IF(G21=0,"Sin ingredientes en Recetas",IF(OR(B21="",B21=0),"Falta rendimiento",IF(COUNTIFS(Recetas!$A$5:$A$1000,A21,Recetas!$H$5:$H$1000,"<>OK")>0,"Revisar: "&COUNTIFS(Recetas!$A$5:$A$1000,A21,Recetas!$H$5:$H$1000,"<>OK")&" ingrediente(s) con aviso","OK")))) -> Revisar: 1 ingrediente(s) con aviso
A22: Berenjenas y Pera (reventa) | B22: 1 | C22: unidad | D22: =IF(A22="","",SUMIFS(Recetas!$G$5:$G$1000,Recetas!$A$5:$A$1000,A22)) -> 0 | E22: =IF(OR(A22="",B22="",B22=0),"",D22/B22) -> 0 | F22: =IF(OR(E22="",C22<>"g"),"",E22*1000) | G22: =IF(A22="","",COUNTIFS(Recetas!$A$5:$A$1000,A22)) -> 1 | H22: =IF(A22="","",IF(G22=0,"Sin ingredientes en Recetas",IF(OR(B22="",B22=0),"Falta rendimiento",IF(COUNTIFS(Recetas!$A$5:$A$1000,A22,Recetas!$H$5:$H$1000,"<>OK")>0,"Revisar: "&COUNTIFS(Recetas!$A$5:$A$1000,A22,Recetas!$H$5:$H$1000,"<>OK")&" ingrediente(s) con aviso","OK")))) -> Revisar: 1 ingrediente(s) con aviso
D23: =IF(A23="","",SUMIFS(Recetas!$G$5:$G$1000,Recetas!$A$5:$A$1000,A23)) | E23: =IF(OR(A23="",B23="",B23=0),"",D23/B23) | F23: =IF(OR(E23="",C23<>"g"),"",E23*1000) | G23: =IF(A23="","",COUNTIFS(Recetas!$A$5:$A$1000,A23)) | H23: =IF(A23="","",IF(G23=0,"Sin ingredientes en Recetas",IF(OR(B23="",B23=0),"Falta rendimiento",IF(COUNTIFS(Recetas!$A$5:$A$1000,A23,Recetas!$H$5:$H$1000,"<>OK")>0,"Revisar: "&COUNTIFS(Recetas!$A$5:$A$1000,A23,Recetas!$H$5:$H$1000,"<>OK")&" ingrediente(s) con aviso","OK"))))
D24: =IF(A24="","",SUMIFS(Recetas!$G$5:$G$1000,Recetas!$A$5:$A$1000,A24)) | E24: =IF(OR(A24="",B24="",B24=0),"",D24/B24) | F24: =IF(OR(E24="",C24<>"g"),"",E24*1000) | G24: =IF(A24="","",COUNTIFS(Recetas!$A$5:$A$1000,A24)) | H24: =IF(A24="","",IF(G24=0,"Sin ingredientes en Recetas",IF(OR(B24="",B24=0),"Falta rendimiento",IF(COUNTIFS(Recetas!$A$5:$A$1000,A24,Recetas!$H$5:$H$1000,"<>OK")>0,"Revisar: "&COUNTIFS(Recetas!$A$5:$A$1000,A24,Recetas!$H$5:$H$1000,"<>OK")&" ingrediente(s) con aviso","OK"))))
D25: =IF(A25="","",SUMIFS(Recetas!$G$5:$G$1000,Recetas!$A$5:$A$1000,A25)) | E25: =IF(OR(A25="",B25="",B25=0),"",D25/B25) | F25: =IF(OR(E25="",C25<>"g"),"",E25*1000) | G25: =IF(A25="","",COUNTIFS(Recetas!$A$5:$A$1000,A25)) | H25: =IF(A25="","",IF(G25=0,"Sin ingredientes en Recetas",IF(OR(B25="",B25=0),"Falta rendimiento",IF(COUNTIFS(Recetas!$A$5:$A$1000,A25,Recetas!$H$5:$H$1000,"<>OK")>0,"Revisar: "&COUNTIFS(Recetas!$A$5:$A$1000,A25,Recetas!$H$5:$H$1000,"<>OK")&" ingrediente(s) con aviso","OK"))))
D26: =IF(A26="","",SUMIFS(Recetas!$G$5:$G$1000,Recetas!$A$5:$A$1000,A26)) | E26: =IF(OR(A26="",B26="",B26=0),"",D26/B26) | F26: =IF(OR(E26="",C26<>"g"),"",E26*1000) | G26: =IF(A26="","",COUNTIFS(Recetas!$A$5:$A$1000,A26)) | H26: =IF(A26="","",IF(G26=0,"Sin ingredientes en Recetas",IF(OR(B26="",B26=0),"Falta rendimiento",IF(COUNTIFS(Recetas!$A$5:$A$1000,A26,Recetas!$H$5:$H$1000,"<>OK")>0,"Revisar: "&COUNTIFS(Recetas!$A$5:$A$1000,A26,Recetas!$H$5:$H$1000,"<>OK")&" ingrediente(s) con aviso","OK"))))
D27: =IF(A27="","",SUMIFS(Recetas!$G$5:$G$1000,Recetas!$A$5:$A$1000,A27)) | E27: =IF(OR(A27="",B27="",B27=0),"",D27/B27) | F27: =IF(OR(E27="",C27<>"g"),"",E27*1000) | G27: =IF(A27="","",COUNTIFS(Recetas!$A$5:$A$1000,A27)) | H27: =IF(A27="","",IF(G27=0,"Sin ingredientes en Recetas",IF(OR(B27="",B27=0),"Falta rendimiento",IF(COUNTIFS(Recetas!$A$5:$A$1000,A27,Recetas!$H$5:$H$1000,"<>OK")>0,"Revisar: "&COUNTIFS(Recetas!$A$5:$A$1000,A27,Recetas!$H$5:$H$1000,"<>OK")&" ingrediente(s) con aviso","OK"))))
D28: =IF(A28="","",SUMIFS(Recetas!$G$5:$G$1000,Recetas!$A$5:$A$1000,A28)) | E28: =IF(OR(A28="",B28="",B28=0),"",D28/B28) | F28: =IF(OR(E28="",C28<>"g"),"",E28*1000) | G28: =IF(A28="","",COUNTIFS(Recetas!$A$5:$A$1000,A28)) | H28: =IF(A28="","",IF(G28=0,"Sin ingredientes en Recetas",IF(OR(B28="",B28=0),"Falta rendimiento",IF(COUNTIFS(Recetas!$A$5:$A$1000,A28,Recetas!$H$5:$H$1000,"<>OK")>0,"Revisar: "&COUNTIFS(Recetas!$A$5:$A$1000,A28,Recetas!$H$5:$H$1000,"<>OK")&" ingrediente(s) con aviso","OK"))))
D29: =IF(A29="","",SUMIFS(Recetas!$G$5:$G$1000,Recetas!$A$5:$A$1000,A29)) | E29: =IF(OR(A29="",B29="",B29=0),"",D29/B29) | F29: =IF(OR(E29="",C29<>"g"),"",E29*1000) | G29: =IF(A29="","",COUNTIFS(Recetas!$A$5:$A$1000,A29)) | H29: =IF(A29="","",IF(G29=0,"Sin ingredientes en Recetas",IF(OR(B29="",B29=0),"Falta rendimiento",IF(COUNTIFS(Recetas!$A$5:$A$1000,A29,Recetas!$H$5:$H$1000,"<>OK")>0,"Revisar: "&COUNTIFS(Recetas!$A$5:$A$1000,A29,Recetas!$H$5:$H$1000,"<>OK")&" ingrediente(s) con aviso","OK"))))
D30: =IF(A30="","",SUMIFS(Recetas!$G$5:$G$1000,Recetas!$A$5:$A$1000,A30)) | E30: =IF(OR(A30="",B30="",B30=0),"",D30/B30) | F30: =IF(OR(E30="",C30<>"g"),"",E30*1000) | G30: =IF(A30="","",COUNTIFS(Recetas!$A$5:$A$1000,A30)) | H30: =IF(A30="","",IF(G30=0,"Sin ingredientes en Recetas",IF(OR(B30="",B30=0),"Falta rendimiento",IF(COUNTIFS(Recetas!$A$5:$A$1000,A30,Recetas!$H$5:$H$1000,"<>OK")>0,"Revisar: "&COUNTIFS(Recetas!$A$5:$A$1000,A30,Recetas!$H$5:$H$1000,"<>OK")&" ingrediente(s) con aviso","OK"))))
D31: =IF(A31="","",SUMIFS(Recetas!$G$5:$G$1000,Recetas!$A$5:$A$1000,A31)) | E31: =IF(OR(A31="",B31="",B31=0),"",D31/B31) | F31: =IF(OR(E31="",C31<>"g"),"",E31*1000) | G31: =IF(A31="","",COUNTIFS(Recetas!$A$5:$A$1000,A31)) | H31: =IF(A31="","",IF(G31=0,"Sin ingredientes en Recetas",IF(OR(B31="",B31=0),"Falta rendimiento",IF(COUNTIFS(Recetas!$A$5:$A$1000,A31,Recetas!$H$5:$H$1000,"<>OK")>0,"Revisar: "&COUNTIFS(Recetas!$A$5:$A$1000,A31,Recetas!$H$5:$H$1000,"<>OK")&" ingrediente(s) con aviso","OK"))))
D32: =IF(A32="","",SUMIFS(Recetas!$G$5:$G$1000,Recetas!$A$5:$A$1000,A32)) | E32: =IF(OR(A32="",B32="",B32=0),"",D32/B32) | F32: =IF(OR(E32="",C32<>"g"),"",E32*1000) | G32: =IF(A32="","",COUNTIFS(Recetas!$A$5:$A$1000,A32)) | H32: =IF(A32="","",IF(G32=0,"Sin ingredientes en Recetas",IF(OR(B32="",B32=0),"Falta rendimiento",IF(COUNTIFS(Recetas!$A$5:$A$1000,A32,Recetas!$H$5:$H$1000,"<>OK")>0,"Revisar: "&COUNTIFS(Recetas!$A$5:$A$1000,A32,Recetas!$H$5:$H$1000,"<>OK")&" ingrediente(s) con aviso","OK"))))
D33: =IF(A33="","",SUMIFS(Recetas!$G$5:$G$1000,Recetas!$A$5:$A$1000,A33)) | E33: =IF(OR(A33="",B33="",B33=0),"",D33/B33) | F33: =IF(OR(E33="",C33<>"g"),"",E33*1000) | G33: =IF(A33="","",COUNTIFS(Recetas!$A$5:$A$1000,A33)) | H33: =IF(A33="","",IF(G33=0,"Sin ingredientes en Recetas",IF(OR(B33="",B33=0),"Falta rendimiento",IF(COUNTIFS(Recetas!$A$5:$A$1000,A33,Recetas!$H$5:$H$1000,"<>OK")>0,"Revisar: "&COUNTIFS(Recetas!$A$5:$A$1000,A33,Recetas!$H$5:$H$1000,"<>OK")&" ingrediente(s) con aviso","OK"))))
D34: =IF(A34="","",SUMIFS(Recetas!$G$5:$G$1000,Recetas!$A$5:$A$1000,A34)) | E34: =IF(OR(A34="",B34="",B34=0),"",D34/B34) | F34: =IF(OR(E34="",C34<>"g"),"",E34*1000) | G34: =IF(A34="","",COUNTIFS(Recetas!$A$5:$A$1000,A34)) | H34: =IF(A34="","",IF(G34=0,"Sin ingredientes en Recetas",IF(OR(B34="",B34=0),"Falta rendimiento",IF(COUNTIFS(Recetas!$A$5:$A$1000,A34,Recetas!$H$5:$H$1000,"<>OK")>0,"Revisar: "&COUNTIFS(Recetas!$A$5:$A$1000,A34,Recetas!$H$5:$H$1000,"<>OK")&" ingrediente(s) con aviso","OK"))))
... D120: =IF(A120="","",SUMIFS(Recetas!$G$5:$G$1000,Recetas!$A$5:$A$1000,A120)) | E120: =IF(OR(A120="",B120="",B120=0),"",D120/B120) | F120: =IF(OR(E120="",C120<>"g"),"",E120*1000) | G120: =IF(A120="","",COUNTIFS(Recetas!$A$5:$A$1000,A120)) | H120: =IF(A120="","",IF(G120=0,"Sin ingredientes en Recetas",IF(OR(B120="",B120=0),"Falta rendimiento",IF(COUNTIFS(Recetas!$A$5:$A$1000,A120,Recetas!$H$5:$H$1000,"<>OK")>0,"Revisar: "&COUNTIFS(Recetas!$A$5:$A$1000,A120,Recetas!$H$5:$H$1000,"<>OK")&" ingrediente(s) con aviso","OK"))))

Sheet Precios
A1: Costo y precio por producto
A2: Cada fila es un producto en una presentación. Costo total = ingredientes + packaging + gastos indirectos. Precio sugerido = Costo total ÷ (1 − margen).
A4: Producto | B4: Presentación | C4: Clave (para combos) | D4: Receta | E4: Cantidad por paquete (g o unidades) | F4: Costo ingredientes ($) | G4: Envase | H4: Costo envase ($) | I4: Etiqueta / otro | J4: Costo etiqueta ($) | K4: Gastos indirectos ($) | L4: COSTO TOTAL ($) | M4: Margen deseado | N4: PRECIO SUGERIDO ($) | O4: Precio actual de venta ($) | P4: Ganancia por paquete ($) | Q4: Margen real | R4: Estado
A5: Cookies Chips de Chocolate | B5: Individual 70 g | C5: =IF(A5="","",A5&" - "&B5) -> Cookies Chips de Chocolate - Individual 70 g | D5: Cookies Chips de Chocolate | E5: 70 | F5: =IF(OR(D5="",E5=""),"",IF(IFERROR(INDEX(RecEstado,MATCH(D5,ListaRecetas,0)),"")<>"OK","",IFERROR(E5*INDEX(RecCostoU,MATCH(D5,ListaRecetas,0)),""))) | G5: Bolsa individual | H5: =IF(G5="",0,IFERROR(INDEX(InsCosto,MATCH(G5,ListaInsumos,0))*1,0)) -> 80 | I5: Etiqueta | J5: =IF(I5="",0,IFERROR(INDEX(InsCosto,MATCH(I5,ListaInsumos,0))*1,0)) -> 50 | K5: =IF(F5="","",(F5+H5+J5)*CFG_Indirectos) | L5: =IF(F5="","",F5+H5+J5+K5) | M5: =CFG_Margen -> 0.6 | N5: =IF(OR(L5="",L5=0,M5="",M5>=1),"",IF(CFG_Redondeo>0,CEILING(L5/(1-M5),CFG_Redondeo),L5/(1-M5))) | O5: 4000 | P5: =IF(OR(L5="",O5=""),"",O5-L5) | Q5: =IF(OR(P5="",O5=0),"",P5/O5) | R5: =IF(A5="","",IF(D5="","Falta elegir receta",IF(IFERROR(INDEX(RecEstado,MATCH(D5,ListaRecetas,0)),"Receta no existe")<>"OK","Receta: "&IFERROR(INDEX(RecEstado,MATCH(D5,ListaRecetas,0)),"no existe"),IF(OR(AND(G5<>"",H5=0),AND(I5<>"",J5=0)),"Packaging sin precio","OK")))) -> Receta: Falta rendimiento
A6: Cookies Chips de Chocolate | B6: Familiar 210 g | C6: =IF(A6="","",A6&" - "&B6) -> Cookies Chips de Chocolate - Familiar 210 g | D6: Cookies Chips de Chocolate | E6: 210 | F6: =IF(OR(D6="",E6=""),"",IF(IFERROR(INDEX(RecEstado,MATCH(D6,ListaRecetas,0)),"")<>"OK","",IFERROR(E6*INDEX(RecCostoU,MATCH(D6,ListaRecetas,0)),""))) | G6: Bolsa familiar | H6: =IF(G6="",0,IFERROR(INDEX(InsCosto,MATCH(G6,ListaInsumos,0))*1,0)) -> 120 | I6: Etiqueta | J6: =IF(I6="",0,IFERROR(INDEX(InsCosto,MATCH(I6,ListaInsumos,0))*1,0)) -> 50 | K6: =IF(F6="","",(F6+H6+J6)*CFG_Indirectos) | L6: =IF(F6="","",F6+H6+J6+K6) | M6: =CFG_Margen -> 0.6 | N6: =IF(OR(L6="",L6=0,M6="",M6>=1),"",IF(CFG_Redondeo>0,CEILING(L6/(1-M6),CFG_Redondeo),L6/(1-M6))) | O6: 11000 | P6: =IF(OR(L6="",O6=""),"",O6-L6) | Q6: =IF(OR(P6="",O6=0),"",P6/O6) | R6: =IF(A6="","",IF(D6="","Falta elegir receta",IF(IFERROR(INDEX(RecEstado,MATCH(D6,ListaRecetas,0)),"Receta no existe")<>"OK","Receta: "&IFERROR(INDEX(RecEstado,MATCH(D6,ListaRecetas,0)),"no existe"),IF(OR(AND(G6<>"",H6=0),AND(I6<>"",J6=0)),"Packaging sin precio","OK")))) -> Receta: Falta rendimiento
A7: Pan de Molde con Trigo Sarraceno | B7: Pan entero | C7: =IF(A7="","",A7&" - "&B7) -> Pan de Molde con Trigo Sarraceno - Pan entero | D7: Pan de Molde con Trigo Sarraceno | E7: 1 | F7: =IF(OR(D7="",E7=""),"",IF(IFERROR(INDEX(RecEstado,MATCH(D7,ListaRecetas,0)),"")<>"OK","",IFERROR(E7*INDEX(RecCostoU,MATCH(D7,ListaRecetas,0)),""))) | G7: Bolsa para pan | H7: =IF(G7="",0,IFERROR(INDEX(InsCosto,MATCH(G7,ListaInsumos,0))*1,0)) -> 0 | I7: Etiqueta | J7: =IF(I7="",0,IFERROR(INDEX(InsCosto,MATCH(I7,ListaInsumos,0))*1,0)) -> 50 | K7: =IF(F7="","",(F7+H7+J7)*CFG_Indirectos) | L7: =IF(F7="","",F7+H7+J7+K7) | M7: =CFG_Margen -> 0.6 | N7: =IF(OR(L7="",L7=0,M7="",M7>=1),"",IF(CFG_Redondeo>0,CEILING(L7/(1-M7),CFG_Redondeo),L7/(1-M7))) | O7: 9000 | P7: =IF(OR(L7="",O7=""),"",O7-L7) | Q7: =IF(OR(P7="",O7=0),"",P7/O7) | R7: =IF(A7="","",IF(D7="","Falta elegir receta",IF(IFERROR(INDEX(RecEstado,MATCH(D7,ListaRecetas,0)),"Receta no existe")<>"OK","Receta: "&IFERROR(INDEX(RecEstado,MATCH(D7,ListaRecetas,0)),"no existe"),IF(OR(AND(G7<>"",H7=0),AND(I7<>"",J7=0)),"Packaging sin precio","OK")))) -> Receta: Revisar: 8 ingrediente(s) con aviso
A8: Tablitas de Trigo Sarraceno y Semillas | B8: Individual 70 g | C8: =IF(A8="","",A8&" - "&B8) -> Tablitas de Trigo Sarraceno y Semillas - Individual 70 g | D8: Tablitas de Trigo Sarraceno y Semillas | E8: 70 | F8: =IF(OR(D8="",E8=""),"",IF(IFERROR(INDEX(RecEstado,MATCH(D8,ListaRecetas,0)),"")<>"OK","",IFERROR(E8*INDEX(RecCostoU,MATCH(D8,ListaRecetas,0)),""))) | G8: Bolsa individual | H8: =IF(G8="",0,IFERROR(INDEX(InsCosto,MATCH(G8,ListaInsumos,0))*1,0)) -> 80 | I8: Etiqueta | J8: =IF(I8="",0,IFERROR(INDEX(InsCosto,MATCH(I8,ListaInsumos,0))*1,0)) -> 50 | K8: =IF(F8="","",(F8+H8+J8)*CFG_Indirectos) | L8: =IF(F8="","",F8+H8+J8+K8) | M8: =CFG_Margen -> 0.6 | N8: =IF(OR(L8="",L8=0,M8="",M8>=1),"",IF(CFG_Redondeo>0,CEILING(L8/(1-M8),CFG_Redondeo),L8/(1-M8))) | O8: 2500 | P8: =IF(OR(L8="",O8=""),"",O8-L8) | Q8: =IF(OR(P8="",O8=0),"",P8/O8) | R8: =IF(A8="","",IF(D8="","Falta elegir receta",IF(IFERROR(INDEX(RecEstado,MATCH(D8,ListaRecetas,0)),"Receta no existe")<>"OK","Receta: "&IFERROR(INDEX(RecEstado,MATCH(D8,ListaRecetas,0)),"no existe"),IF(OR(AND(G8<>"",H8=0),AND(I8<>"",J8=0)),"Packaging sin precio","OK")))) -> Receta: Falta rendimiento
A9: Tablitas de Trigo Sarraceno y Semillas | B9: Familiar 210 g | C9: =IF(A9="","",A9&" - "&B9) -> Tablitas de Trigo Sarraceno y Semillas - Familiar 210 g | D9: Tablitas de Trigo Sarraceno y Semillas | E9: 210 | F9: =IF(OR(D9="",E9=""),"",IF(IFERROR(INDEX(RecEstado,MATCH(D9,ListaRecetas,0)),"")<>"OK","",IFERROR(E9*INDEX(RecCostoU,MATCH(D9,ListaRecetas,0)),""))) | G9: Bolsa familiar | H9: =IF(G9="",0,IFERROR(INDEX(InsCosto,MATCH(G9,ListaInsumos,0))*1,0)) -> 120 | I9: Etiqueta | J9: =IF(I9="",0,IFERROR(INDEX(InsCosto,MATCH(I9,ListaInsumos,0))*1,0)) -> 50 | K9: =IF(F9="","",(F9+H9+J9)*CFG_Indirectos) | L9: =IF(F9="","",F9+H9+J9+K9) | M9: =CFG_Margen -> 0.6 | N9: =IF(OR(L9="",L9=0,M9="",M9>=1),"",IF(CFG_Redondeo>0,CEILING(L9/(1-M9),CFG_Redondeo),L9/(1-M9))) | O9: 7000 | P9: =IF(OR(L9="",O9=""),"",O9-L9) | Q9: =IF(OR(P9="",O9=0),"",P9/O9) | R9: =IF(A9="","",IF(D9="","Falta elegir receta",IF(IFERROR(INDEX(RecEstado,MATCH(D9,ListaRecetas,0)),"Receta no existe")<>"OK","Receta: "&IFERROR(INDEX(RecEstado,MATCH(D9,ListaRecetas,0)),"no existe"),IF(OR(AND(G9<>"",H9=0),AND(I9<>"",J9=0)),"Packaging sin precio","OK")))) -> Receta: Falta rendimiento
A10: Galletas Marineras | B10: Individual 70 g | C10: =IF(A10="","",A10&" - "&B10) -> Galletas Marineras - Individual 70 g | D10: Galletas Marineras | E10: 70 | F10: =IF(OR(D10="",E10=""),"",IF(IFERROR(INDEX(RecEstado,MATCH(D10,ListaRecetas,0)),"")<>"OK","",IFERROR(E10*INDEX(RecCostoU,MATCH(D10,ListaRecetas,0)),""))) -> 405.3 | G10: Bolsa individual | H10: =IF(G10="",0,IFERROR(INDEX(InsCosto,MATCH(G10,ListaInsumos,0))*1,0)) -> 80 | I10: Etiqueta | J10: =IF(I10="",0,IFERROR(INDEX(InsCosto,MATCH(I10,ListaInsumos,0))*1,0)) -> 50 | K10: =IF(F10="","",(F10+H10+J10)*CFG_Indirectos) -> 133.825 | L10: =IF(F10="","",F10+H10+J10+K10) -> 669.125 | M10: =CFG_Margen -> 0.6 | N10: =IF(OR(L10="",L10=0,M10="",M10>=1),"",IF(CFG_Redondeo>0,CEILING(L10/(1-M10),CFG_Redondeo),L10/(1-M10))) -> 1700 | O10: 2500 | P10: =IF(OR(L10="",O10=""),"",O10-L10) -> 1830.875 | Q10: =IF(OR(P10="",O10=0),"",P10/O10) -> 0.73235 | R10: =IF(A10="","",IF(D10="","Falta elegir receta",IF(IFERROR(INDEX(RecEstado,MATCH(D10,ListaRecetas,0)),"Receta no existe")<>"OK","Receta: "&IFERROR(INDEX(RecEstado,MATCH(D10,ListaRecetas,0)),"no existe"),IF(OR(AND(G10<>"",H10=0),AND(I10<>"",J10=0)),"Packaging sin precio","OK")))) -> OK
A11: Galletas Marineras | B11: Familiar 210 g | C11: =IF(A11="","",A11&" - "&B11) -> Galletas Marineras - Familiar 210 g | D11: Galletas Marineras | E11: 210 | F11: =IF(OR(D11="",E11=""),"",IF(IFERROR(INDEX(RecEstado,MATCH(D11,ListaRecetas,0)),"")<>"OK","",IFERROR(E11*INDEX(RecCostoU,MATCH(D11,ListaRecetas,0)),""))) -> 1215.9 | G11: Bolsa familiar | H11: =IF(G11="",0,IFERROR(INDEX(InsCosto,MATCH(G11,ListaInsumos,0))*1,0)) -> 120 | I11: Etiqueta | J11: =IF(I11="",0,IFERROR(INDEX(InsCosto,MATCH(I11,ListaInsumos,0))*1,0)) -> 50 | K11: =IF(F11="","",(F11+H11+J11)*CFG_Indirectos) -> 346.475 | L11: =IF(F11="","",F11+H11+J11+K11) -> 1732.375 | M11: =CFG_Margen -> 0.6 | N11: =IF(OR(L11="",L11=0,M11="",M11>=1),"",IF(CFG_Redondeo>0,CEILING(L11/(1-M11),CFG_Redondeo),L11/(1-M11))) -> 4400 | O11: 7000 | P11: =IF(OR(L11="",O11=""),"",O11-L11) -> 5267.625 | Q11: =IF(OR(P11="",O11=0),"",P11/O11) -> 0.75251786 | R11: =IF(A11="","",IF(D11="","Falta elegir receta",IF(IFERROR(INDEX(RecEstado,MATCH(D11,ListaRecetas,0)),"Receta no existe")<>"OK","Receta: "&IFERROR(INDEX(RecEstado,MATCH(D11,ListaRecetas,0)),"no existe"),IF(OR(AND(G11<>"",H11=0),AND(I11<>"",J11=0)),"Packaging sin precio","OK")))) -> OK
A12: Crakers de Mijo y Cebolla | B12: Individual 50 g | C12: =IF(A12="","",A12&" - "&B12) -> Crakers de Mijo y Cebolla - Individual 50 g | D12: Crakers de Mijo y Cebolla | E12: 50 | F12: =IF(OR(D12="",E12=""),"",IF(IFERROR(INDEX(RecEstado,MATCH(D12,ListaRecetas,0)),"")<>"OK","",IFERROR(E12*INDEX(RecCostoU,MATCH(D12,ListaRecetas,0)),""))) | G12: Bolsa individual | H12: =IF(G12="",0,IFERROR(INDEX(InsCosto,MATCH(G12,ListaInsumos,0))*1,0)) -> 80 | I12: Etiqueta | J12: =IF(I12="",0,IFERROR(INDEX(InsCosto,MATCH(I12,ListaInsumos,0))*1,0)) -> 50 | K12: =IF(F12="","",(F12+H12+J12)*CFG_Indirectos) | L12: =IF(F12="","",F12+H12+J12+K12) | M12: =CFG_Margen -> 0.6 | N12: =IF(OR(L12="",L12=0,M12="",M12>=1),"",IF(CFG_Redondeo>0,CEILING(L12/(1-M12),CFG_Redondeo),L12/(1-M12))) | O12: 2500 | P12: =IF(OR(L12="",O12=""),"",O12-L12) | Q12: =IF(OR(P12="",O12=0),"",P12/O12) | R12: =IF(A12="","",IF(D12="","Falta elegir receta",IF(IFERROR(INDEX(RecEstado,MATCH(D12,ListaRecetas,0)),"Receta no existe")<>"OK","Receta: "&IFERROR(INDEX(RecEstado,MATCH(D12,ListaRecetas,0)),"no existe"),IF(OR(AND(G12<>"",H12=0),AND(I12<>"",J12=0)),"Packaging sin precio","OK")))) -> Receta: Falta rendimiento
A13: Crakers de Mijo y Cebolla | B13: Familiar 150 g | C13: =IF(A13="","",A13&" - "&B13) -> Crakers de Mijo y Cebolla - Familiar 150 g | D13: Crakers de Mijo y Cebolla | E13: 150 | F13: =IF(OR(D13="",E13=""),"",IF(IFERROR(INDEX(RecEstado,MATCH(D13,ListaRecetas,0)),"")<>"OK","",IFERROR(E13*INDEX(RecCostoU,MATCH(D13,ListaRecetas,0)),""))) | G13: Bolsa familiar | H13: =IF(G13="",0,IFERROR(INDEX(InsCosto,MATCH(G13,ListaInsumos,0))*1,0)) -> 120 | I13: Etiqueta | J13: =IF(I13="",0,IFERROR(INDEX(InsCosto,MATCH(I13,ListaInsumos,0))*1,0)) -> 50 | K13: =IF(F13="","",(F13+H13+J13)*CFG_Indirectos) | L13: =IF(F13="","",F13+H13+J13+K13) | M13: =CFG_Margen -> 0.6 | N13: =IF(OR(L13="",L13=0,M13="",M13>=1),"",IF(CFG_Redondeo>0,CEILING(L13/(1-M13),CFG_Redondeo),L13/(1-M13))) | O13: 7000 | P13: =IF(OR(L13="",O13=""),"",O13-L13) | Q13: =IF(OR(P13="",O13=0),"",P13/O13) | R13: =IF(A13="","",IF(D13="","Falta elegir receta",IF(IFERROR(INDEX(RecEstado,MATCH(D13,ListaRecetas,0)),"Receta no existe")<>"OK","Receta: "&IFERROR(INDEX(RecEstado,MATCH(D13,ListaRecetas,0)),"no existe"),IF(OR(AND(G13<>"",H13=0),AND(I13<>"",J13=0)),"Packaging sin precio","OK")))) -> Receta: Falta rendimiento
A14: Palitos de Batata y Romero | B14: Individual 50 g | C14: =IF(A14="","",A14&" - "&B14) -> Palitos de Batata y Romero - Individual 50 g | D14: Palitos de Batata y Romero | E14: 50 | F14: =IF(OR(D14="",E14=""),"",IF(IFERROR(INDEX(RecEstado,MATCH(D14,ListaRecetas,0)),"")<>"OK","",IFERROR(E14*INDEX(RecCostoU,MATCH(D14,ListaRecetas,0)),""))) | G14: Bolsa individual | H14: =IF(G14="",0,IFERROR(INDEX(InsCosto,MATCH(G14,ListaInsumos,0))*1,0)) -> 80 | I14: Etiqueta | J14: =IF(I14="",0,IFERROR(INDEX(InsCosto,MATCH(I14,ListaInsumos,0))*1,0)) -> 50 | K14: =IF(F14="","",(F14+H14+J14)*CFG_Indirectos) | L14: =IF(F14="","",F14+H14+J14+K14) | M14: =CFG_Margen -> 0.6 | N14: =IF(OR(L14="",L14=0,M14="",M14>=1),"",IF(CFG_Redondeo>0,CEILING(L14/(1-M14),CFG_Redondeo),L14/(1-M14))) | O14: 3000 | P14: =IF(OR(L14="",O14=""),"",O14-L14) | Q14: =IF(OR(P14="",O14=0),"",P14/O14) | R14: =IF(A14="","",IF(D14="","Falta elegir receta",IF(IFERROR(INDEX(RecEstado,MATCH(D14,ListaRecetas,0)),"Receta no existe")<>"OK","Receta: "&IFERROR(INDEX(RecEstado,MATCH(D14,ListaRecetas,0)),"no existe"),IF(OR(AND(G14<>"",H14=0),AND(I14<>"",J14=0)),"Packaging sin precio","OK")))) -> Receta: Falta rendimiento
A15: Palitos de Batata y Romero | B15: Familiar 150 g | C15: =IF(A15="","",A15&" - "&B15) -> Palitos de Batata y Romero - Familiar 150 g | D15: Palitos de Batata y Romero | E15: 150 | F15: =IF(OR(D15="",E15=""),"",IF(IFERROR(INDEX(RecEstado,MATCH(D15,ListaRecetas,0)),"")<>"OK","",IFERROR(E15*INDEX(RecCostoU,MATCH(D15,ListaRecetas,0)),""))) | G15: Bolsa familiar | H15: =IF(G15="",0,IFERROR(INDEX(InsCosto,MATCH(G15,ListaInsumos,0))*1,0)) -> 120 | I15: Etiqueta | J15: =IF(I15="",0,IFERROR(INDEX(InsCosto,MATCH(I15,ListaInsumos,0))*1,0)) -> 50 | K15: =IF(F15="","",(F15+H15+J15)*CFG_Indirectos) | L15: =IF(F15="","",F15+H15+J15+K15) | M15: =CFG_Margen -> 0.6 | N15: =IF(OR(L15="",L15=0,M15="",M15>=1),"",IF(CFG_Redondeo>0,CEILING(L15/(1-M15),CFG_Redondeo),L15/(1-M15))) | O15: 8500 | P15: =IF(OR(L15="",O15=""),"",O15-L15) | Q15: =IF(OR(P15="",O15=0),"",P15/O15) | R15: =IF(A15="","",IF(D15="","Falta elegir receta",IF(IFERROR(INDEX(RecEstado,MATCH(D15,ListaRecetas,0)),"Receta no existe")<>"OK","Receta: "&IFERROR(INDEX(RecEstado,MATCH(D15,ListaRecetas,0)),"no existe"),IF(OR(AND(G15<>"",H15=0),AND(I15<>"",J15=0)),"Packaging sin precio","OK")))) -> Receta: Falta rendimiento
A16: Garbancitos Crocantes | B16: Individual 50 g | C16: =IF(A16="","",A16&" - "&B16) -> Garbancitos Crocantes - Individual 50 g | D16: Garbancitos Crocantes | E16: 50 | F16: =IF(OR(D16="",E16=""),"",IF(IFERROR(INDEX(RecEstado,MATCH(D16,ListaRecetas,0)),"")<>"OK","",IFERROR(E16*INDEX(RecCostoU,MATCH(D16,ListaRecetas,0)),""))) | G16: Bolsa individual | H16: =IF(G16="",0,IFERROR(INDEX(InsCosto,MATCH(G16,ListaInsumos,0))*1,0)) -> 80 | I16: Etiqueta | J16: =IF(I16="",0,IFERROR(INDEX(InsCosto,MATCH(I16,ListaInsumos,0))*1,0)) -> 50 | K16: =IF(F16="","",(F16+H16+J16)*CFG_Indirectos) | L16: =IF(F16="","",F16+H16+J16+K16) | M16: =CFG_Margen -> 0.6 | N16: =IF(OR(L16="",L16=0,M16="",M16>=1),"",IF(CFG_Redondeo>0,CEILING(L16/(1-M16),CFG_Redondeo),L16/(1-M16))) | O16: 2500 | P16: =IF(OR(L16="",O16=""),"",O16-L16) | Q16: =IF(OR(P16="",O16=0),"",P16/O16) | R16: =IF(A16="","",IF(D16="","Falta elegir receta",IF(IFERROR(INDEX(RecEstado,MATCH(D16,ListaRecetas,0)),"Receta no existe")<>"OK","Receta: "&IFERROR(INDEX(RecEstado,MATCH(D16,ListaRecetas,0)),"no existe"),IF(OR(AND(G16<>"",H16=0),AND(I16<>"",J16=0)),"Packaging sin precio","OK")))) -> Receta: Falta rendimiento
... A27: Bastoncitos de Zanahoria y Remolacha | B27: Familiar 150 g | C27: =IF(A27="","",A27&" - "&B27) -> Bastoncitos de Zanahoria y Remolacha - Familiar 150 g | D27: Bastoncitos de Zanahoria y Remolacha | E27: 150 | F27: =IF(OR(D27="",E27=""),"",IF(IFERROR(INDEX(RecEstado,MATCH(D27,ListaRecetas,0)),"")<>"OK","",IFERROR(E27*INDEX(RecCostoU,MATCH(D27,ListaRecetas,0)),""))) | G27: Bolsa familiar | H27: =IF(G27="",0,IFERROR(INDEX(InsCosto,MATCH(G27,ListaInsumos,0))*1,0)) -> 120 | I27: Etiqueta | J27: =IF(I27="",0,IFERROR(INDEX(InsCosto,MATCH(I27,ListaInsumos,0))*1,0)) -> 50 | K27: =IF(F27="","",(F27+H27+J27)*CFG_Indirectos) | L27: =IF(F27="","",F27+H27+J27+K27) | M27: =CFG_Margen -> 0.6 | N27: =IF(OR(L27="",L27=0,M27="",M27>=1),"",IF(CFG_Redondeo>0,CEILING(L27/(1-M27),CFG_Redondeo),L27/(1-M27))) | O27: 8000 | P27: =IF(OR(L27="",O27=""),"",O27-L27) | Q27: =IF(OR(P27="",O27=0),"",P27/O27) | R27: =IF(A27="","",IF(D27="","Falta elegir receta",IF(IFERROR(INDEX(RecEstado,MATCH(D27,ListaRecetas,0)),"Receta no existe")<>"OK","Receta: "&IFERROR(INDEX(RecEstado,MATCH(D27,ListaRecetas,0)),"no existe"),IF(OR(AND(G27<>"",H27=0),AND(I27<>"",J27=0)),"Packaging sin precio","OK")))) -> Receta: Falta rendimiento
A28: Mermeladas Artesanales | B28: 200 g (cualquier sabor) | C28: =IF(A28="","",A28&" - "&B28) -> Mermeladas Artesanales - 200 g (cualquier sabor) | D28: Mermelada (reventa) | E28: 1 | F28: =IF(OR(D28="",E28=""),"",IF(IFERROR(INDEX(RecEstado,MATCH(D28,ListaRecetas,0)),"")<>"OK","",IFERROR(E28*INDEX(RecCostoU,MATCH(D28,ListaRecetas,0)),""))) | H28: =IF(G28="",0,IFERROR(INDEX(InsCosto,MATCH(G28,ListaInsumos,0))*1,0)) -> 0 | J28: =IF(I28="",0,IFERROR(INDEX(InsCosto,MATCH(I28,ListaInsumos,0))*1,0)) -> 0 | K28: =IF(F28="","",(F28+H28+J28)*CFG_Indirectos) | L28: =IF(F28="","",F28+H28+J28+K28) | M28: =CFG_Margen -> 0.6 | N28: =IF(OR(L28="",L28=0,M28="",M28>=1),"",IF(CFG_Redondeo>0,CEILING(L28/(1-M28),CFG_Redondeo),L28/(1-M28))) | O28: 3500 | P28: =IF(OR(L28="",O28=""),"",O28-L28) | Q28: =IF(OR(P28="",O28=0),"",P28/O28) | R28: =IF(A28="","",IF(D28="","Falta elegir receta",IF(IFERROR(INDEX(RecEstado,MATCH(D28,ListaRecetas,0)),"Receta no existe")<>"OK","Receta: "&IFERROR(INDEX(RecEstado,MATCH(D28,ListaRecetas,0)),"no existe"),IF(OR(AND(G28<>"",H28=0),AND(I28<>"",J28=0)),"Packaging sin precio","OK")))) -> Receta: Revisar: 1 ingrediente(s) con aviso
A29: Conservas de Lo Artesanal | B29: Berenjenas Húngaras 150 g | C29: =IF(A29="","",A29&" - "&B29) -> Conservas de Lo Artesanal - Berenjenas Húngaras 150 g | D29: Berenjenas Húngaras (reventa) | E29: 1 | F29: =IF(OR(D29="",E29=""),"",IF(IFERROR(INDEX(RecEstado,MATCH(D29,ListaRecetas,0)),"")<>"OK","",IFERROR(E29*INDEX(RecCostoU,MATCH(D29,ListaRecetas,0)),""))) | H29: =IF(G29="",0,IFERROR(INDEX(InsCosto,MATCH(G29,ListaInsumos,0))*1,0)) -> 0 | J29: =IF(I29="",0,IFERROR(INDEX(InsCosto,MATCH(I29,ListaInsumos,0))*1,0)) -> 0 | K29: =IF(F29="","",(F29+H29+J29)*CFG_Indirectos) | L29: =IF(F29="","",F29+H29+J29+K29) | M29: =CFG_Margen -> 0.6 | N29: =IF(OR(L29="",L29=0,M29="",M29>=1),"",IF(CFG_Redondeo>0,CEILING(L29/(1-M29),CFG_Redondeo),L29/(1-M29))) | O29: 3500 | P29: =IF(OR(L29="",O29=""),"",O29-L29) | Q29: =IF(OR(P29="",O29=0),"",P29/O29) | R29: =IF(A29="","",IF(D29="","Falta elegir receta",IF(IFERROR(INDEX(RecEstado,MATCH(D29,ListaRecetas,0)),"Receta no existe")<>"OK","Receta: "&IFERROR(INDEX(RecEstado,MATCH(D29,ListaRecetas,0)),"no existe"),IF(OR(AND(G29<>"",H29=0),AND(I29<>"",J29=0)),"Packaging sin precio","OK")))) -> Receta: Revisar: 1 ingrediente(s) con aviso
A30: Conservas de Lo Artesanal | B30: Aceitunas Condimentadas 300 g | C30: =IF(A30="","",A30&" - "&B30) -> Conservas de Lo Artesanal - Aceitunas Condimentadas 300 g | D30: Aceitunas Condimentadas (reventa) | E30: 1 | F30: =IF(OR(D30="",E30=""),"",IF(IFERROR(INDEX(RecEstado,MATCH(D30,ListaRecetas,0)),"")<>"OK","",IFERROR(E30*INDEX(RecCostoU,MATCH(D30,ListaRecetas,0)),""))) | H30: =IF(G30="",0,IFERROR(INDEX(InsCosto,MATCH(G30,ListaInsumos,0))*1,0)) -> 0 | J30: =IF(I30="",0,IFERROR(INDEX(InsCosto,MATCH(I30,ListaInsumos,0))*1,0)) -> 0 | K30: =IF(F30="","",(F30+H30+J30)*CFG_Indirectos) | L30: =IF(F30="","",F30+H30+J30+K30) | M30: =CFG_Margen -> 0.6 | N30: =IF(OR(L30="",L30=0,M30="",M30>=1),"",IF(CFG_Redondeo>0,CEILING(L30/(1-M30),CFG_Redondeo),L30/(1-M30))) | O30: 4500 | P30: =IF(OR(L30="",O30=""),"",O30-L30) | Q30: =IF(OR(P30="",O30=0),"",P30/O30) | R30: =IF(A30="","",IF(D30="","Falta elegir receta",IF(IFERROR(INDEX(RecEstado,MATCH(D30,ListaRecetas,0)),"Receta no existe")<>"OK","Receta: "&IFERROR(INDEX(RecEstado,MATCH(D30,ListaRecetas,0)),"no existe"),IF(OR(AND(G30<>"",H30=0),AND(I30<>"",J30=0)),"Packaging sin precio","OK")))) -> Receta: Revisar: 1 ingrediente(s) con aviso
A31: Conservas de Lo Artesanal | B31: Berenjenas en Escabeche 200 g | C31: =IF(A31="","",A31&" - "&B31) -> Conservas de Lo Artesanal - Berenjenas en Escabeche 200 g | D31: Berenjenas en Escabeche (reventa) | E31: 1 | F31: =IF(OR(D31="",E31=""),"",IF(IFERROR(INDEX(RecEstado,MATCH(D31,ListaRecetas,0)),"")<>"OK","",IFERROR(E31*INDEX(RecCostoU,MATCH(D31,ListaRecetas,0)),""))) | H31: =IF(G31="",0,IFERROR(INDEX(InsCosto,MATCH(G31,ListaInsumos,0))*1,0)) -> 0 | J31: =IF(I31="",0,IFERROR(INDEX(InsCosto,MATCH(I31,ListaInsumos,0))*1,0)) -> 0 | K31: =IF(F31="","",(F31+H31+J31)*CFG_Indirectos) | L31: =IF(F31="","",F31+H31+J31+K31) | M31: =CFG_Margen -> 0.6 | N31: =IF(OR(L31="",L31=0,M31="",M31>=1),"",IF(CFG_Redondeo>0,CEILING(L31/(1-M31),CFG_Redondeo),L31/(1-M31))) | O31: 5000 | P31: =IF(OR(L31="",O31=""),"",O31-L31) | Q31: =IF(OR(P31="",O31=0),"",P31/O31) | R31: =IF(A31="","",IF(D31="","Falta elegir receta",IF(IFERROR(INDEX(RecEstado,MATCH(D31,ListaRecetas,0)),"Receta no existe")<>"OK","Receta: "&IFERROR(INDEX(RecEstado,MATCH(D31,ListaRecetas,0)),"no existe"),IF(OR(AND(G31<>"",H31=0),AND(I31<>"",J31=0)),"Packaging sin precio","OK")))) -> Receta: Revisar: 1 ingrediente(s) con aviso
A32: Conservas de Lo Artesanal | B32: Berenjenas y Pera 200 g | C32: =IF(A32="","",A32&" - "&B32) -> Conservas de Lo Artesanal - Berenjenas y Pera 200 g | D32: Berenjenas y Pera (reventa) | E32: 1 | F32: =IF(OR(D32="",E32=""),"",IF(IFERROR(INDEX(RecEstado,MATCH(D32,ListaRecetas,0)),"")<>"OK","",IFERROR(E32*INDEX(RecCostoU,MATCH(D32,ListaRecetas,0)),""))) | H32: =IF(G32="",0,IFERROR(INDEX(InsCosto,MATCH(G32,ListaInsumos,0))*1,0)) -> 0 | J32: =IF(I32="",0,IFERROR(INDEX(InsCosto,MATCH(I32,ListaInsumos,0))*1,0)) -> 0 | K32: =IF(F32="","",(F32+H32+J32)*CFG_Indirectos) | L32: =IF(F32="","",F32+H32+J32+K32) | M32: =CFG_Margen -> 0.6 | N32: =IF(OR(L32="",L32=0,M32="",M32>=1),"",IF(CFG_Redondeo>0,CEILING(L32/(1-M32),CFG_Redondeo),L32/(1-M32))) | O32: 4000 | P32: =IF(OR(L32="",O32=""),"",O32-L32) | Q32: =IF(OR(P32="",O32=0),"",P32/O32) | R32: =IF(A32="","",IF(D32="","Falta elegir receta",IF(IFERROR(INDEX(RecEstado,MATCH(D32,ListaRecetas,0)),"Receta no existe")<>"OK","Receta: "&IFERROR(INDEX(RecEstado,MATCH(D32,ListaRecetas,0)),"no existe"),IF(OR(AND(G32<>"",H32=0),AND(I32<>"",J32=0)),"Packaging sin precio","OK")))) -> Receta: Revisar: 1 ingrediente(s) con aviso
A33: Azúcar de Coco | B33: 200 g | C33: =IF(A33="","",A33&" - "&B33) -> Azúcar de Coco - 200 g | D33: Azúcar de coco fraccionada | E33: 200 | F33: =IF(OR(D33="",E33=""),"",IF(IFERROR(INDEX(RecEstado,MATCH(D33,ListaRecetas,0)),"")<>"OK","",IFERROR(E33*INDEX(RecCostoU,MATCH(D33,ListaRecetas,0)),""))) | G33: Envase azúcar de coco 200 g | H33: =IF(G33="",0,IFERROR(INDEX(InsCosto,MATCH(G33,ListaInsumos,0))*1,0)) -> 0 | I33: Etiqueta | J33: =IF(I33="",0,IFERROR(INDEX(InsCosto,MATCH(I33,ListaInsumos,0))*1,0)) -> 50 | K33: =IF(F33="","",(F33+H33+J33)*CFG_Indirectos) | L33: =IF(F33="","",F33+H33+J33+K33) | M33: =CFG_Margen -> 0.6 | N33: =IF(OR(L33="",L33=0,M33="",M33>=1),"",IF(CFG_Redondeo>0,CEILING(L33/(1-M33),CFG_Redondeo),L33/(1-M33))) | O33: 5000 | P33: =IF(OR(L33="",O33=""),"",O33-L33) | Q33: =IF(OR(P33="",O33=0),"",P33/O33) | R33: =IF(A33="","",IF(D33="","Falta elegir receta",IF(IFERROR(INDEX(RecEstado,MATCH(D33,ListaRecetas,0)),"Receta no existe")<>"OK","Receta: "&IFERROR(INDEX(RecEstado,MATCH(D33,ListaRecetas,0)),"no existe"),IF(OR(AND(G33<>"",H33=0),AND(I33<>"",J33=0)),"Packaging sin precio","OK")))) -> Receta: Revisar: 1 ingrediente(s) con aviso
C34: =IF(A34="","",A34&" - "&B34) | F34: =IF(OR(D34="",E34=""),"",IF(IFERROR(INDEX(RecEstado,MATCH(D34,ListaRecetas,0)),"")<>"OK","",IFERROR(E34*INDEX(RecCostoU,MATCH(D34,ListaRecetas,0)),""))) | H34: =IF(G34="",0,IFERROR(INDEX(InsCosto,MATCH(G34,ListaInsumos,0))*1,0)) -> 0 | J34: =IF(I34="",0,IFERROR(INDEX(InsCosto,MATCH(I34,ListaInsumos,0))*1,0)) -> 0 | K34: =IF(F34="","",(F34+H34+J34)*CFG_Indirectos) | L34: =IF(F34="","",F34+H34+J34+K34) | N34: =IF(OR(L34="",L34=0,M34="",M34>=1),"",IF(CFG_Redondeo>0,CEILING(L34/(1-M34),CFG_Redondeo),L34/(1-M34))) | P34: =IF(OR(L34="",O34=""),"",O34-L34) | Q34: =IF(OR(P34="",O34=0),"",P34/O34) | R34: =IF(A34="","",IF(D34="","Falta elegir receta",IF(IFERROR(INDEX(RecEstado,MATCH(D34,ListaRecetas,0)),"Receta no existe")<>"OK","Receta: "&IFERROR(INDEX(RecEstado,MATCH(D34,ListaRecetas,0)),"no existe"),IF(OR(AND(G34<>"",H34=0),AND(I34<>"",J34=0)),"Packaging sin precio","OK"))))
C35: =IF(A35="","",A35&" - "&B35) | F35: =IF(OR(D35="",E35=""),"",IF(IFERROR(INDEX(RecEstado,MATCH(D35,ListaRecetas,0)),"")<>"OK","",IFERROR(E35*INDEX(RecCostoU,MATCH(D35,ListaRecetas,0)),""))) | H35: =IF(G35="",0,IFERROR(INDEX(InsCosto,MATCH(G35,ListaInsumos,0))*1,0)) -> 0 | J35: =IF(I35="",0,IFERROR(INDEX(InsCosto,MATCH(I35,ListaInsumos,0))*1,0)) -> 0 | K35: =IF(F35="","",(F35+H35+J35)*CFG_Indirectos) | L35: =IF(F35="","",F35+H35+J35+K35) | N35: =IF(OR(L35="",L35=0,M35="",M35>=1),"",IF(CFG_Redondeo>0,CEILING(L35/(1-M35),CFG_Redondeo),L35/(1-M35))) | P35: =IF(OR(L35="",O35=""),"",O35-L35) | Q35: =IF(OR(P35="",O35=0),"",P35/O35) | R35: =IF(A35="","",IF(D35="","Falta elegir receta",IF(IFERROR(INDEX(RecEstado,MATCH(D35,ListaRecetas,0)),"Receta no existe")<>"OK","Receta: "&IFERROR(INDEX(RecEstado,MATCH(D35,ListaRecetas,0)),"no existe"),IF(OR(AND(G35<>"",H35=0),AND(I35<>"",J35=0)),"Packaging sin precio","OK"))))
C36: =IF(A36="","",A36&" - "&B36) | F36: =IF(OR(D36="",E36=""),"",IF(IFERROR(INDEX(RecEstado,MATCH(D36,ListaRecetas,0)),"")<>"OK","",IFERROR(E36*INDEX(RecCostoU,MATCH(D36,ListaRecetas,0)),""))) | H36: =IF(G36="",0,IFERROR(INDEX(InsCosto,MATCH(G36,ListaInsumos,0))*1,0)) -> 0 | J36: =IF(I36="",0,IFERROR(INDEX(InsCosto,MATCH(I36,ListaInsumos,0))*1,0)) -> 0 | K36: =IF(F36="","",(F36+H36+J36)*CFG_Indirectos) | L36: =IF(F36="","",F36+H36+J36+K36) | N36: =IF(OR(L36="",L36=0,M36="",M36>=1),"",IF(CFG_Redondeo>0,CEILING(L36/(1-M36),CFG_Redondeo),L36/(1-M36))) | P36: =IF(OR(L36="",O36=""),"",O36-L36) | Q36: =IF(OR(P36="",O36=0),"",P36/O36) | R36: =IF(A36="","",IF(D36="","Falta elegir receta",IF(IFERROR(INDEX(RecEstado,MATCH(D36,ListaRecetas,0)),"Receta no existe")<>"OK","Receta: "&IFERROR(INDEX(RecEstado,MATCH(D36,ListaRecetas,0)),"no existe"),IF(OR(AND(G36<>"",H36=0),AND(I36<>"",J36=0)),"Packaging sin precio","OK"))))
C37: =IF(A37="","",A37&" - "&B37) | F37: =IF(OR(D37="",E37=""),"",IF(IFERROR(INDEX(RecEstado,MATCH(D37,ListaRecetas,0)),"")<>"OK","",IFERROR(E37*INDEX(RecCostoU,MATCH(D37,ListaRecetas,0)),""))) | H37: =IF(G37="",0,IFERROR(INDEX(InsCosto,MATCH(G37,ListaInsumos,0))*1,0)) -> 0 | J37: =IF(I37="",0,IFERROR(INDEX(InsCosto,MATCH(I37,ListaInsumos,0))*1,0)) -> 0 | K37: =IF(F37="","",(F37+H37+J37)*CFG_Indirectos) | L37: =IF(F37="","",F37+H37+J37+K37) | N37: =IF(OR(L37="",L37=0,M37="",M37>=1),"",IF(CFG_Redondeo>0,CEILING(L37/(1-M37),CFG_Redondeo),L37/(1-M37))) | P37: =IF(OR(L37="",O37=""),"",O37-L37) | Q37: =IF(OR(P37="",O37=0),"",P37/O37) | R37: =IF(A37="","",IF(D37="","Falta elegir receta",IF(IFERROR(INDEX(RecEstado,MATCH(D37,ListaRecetas,0)),"Receta no existe")<>"OK","Receta: "&IFERROR(INDEX(RecEstado,MATCH(D37,ListaRecetas,0)),"no existe"),IF(OR(AND(G37<>"",H37=0),AND(I37<>"",J37=0)),"Packaging sin precio","OK"))))
C38: =IF(A38="","",A38&" - "&B38) | F38: =IF(OR(D38="",E38=""),"",IF(IFERROR(INDEX(RecEstado,MATCH(D38,ListaRecetas,0)),"")<>"OK","",IFERROR(E38*INDEX(RecCostoU,MATCH(D38,ListaRecetas,0)),""))) | H38: =IF(G38="",0,IFERROR(INDEX(InsCosto,MATCH(G38,ListaInsumos,0))*1,0)) -> 0 | J38: =IF(I38="",0,IFERROR(INDEX(InsCosto,MATCH(I38,ListaInsumos,0))*1,0)) -> 0 | K38: =IF(F38="","",(F38+H38+J38)*CFG_Indirectos) | L38: =IF(F38="","",F38+H38+J38+K38) | N38: =IF(OR(L38="",L38=0,M38="",M38>=1),"",IF(CFG_Redondeo>0,CEILING(L38/(1-M38),CFG_Redondeo),L38/(1-M38))) | P38: =IF(OR(L38="",O38=""),"",O38-L38) | Q38: =IF(OR(P38="",O38=0),"",P38/O38) | R38: =IF(A38="","",IF(D38="","Falta elegir receta",IF(IFERROR(INDEX(RecEstado,MATCH(D38,ListaRecetas,0)),"Receta no existe")<>"OK","Receta: "&IFERROR(INDEX(RecEstado,MATCH(D38,ListaRecetas,0)),"no existe"),IF(OR(AND(G38<>"",H38=0),AND(I38<>"",J38=0)),"Packaging sin precio","OK"))))
C39: =IF(A39="","",A39&" - "&B39) | F39: =IF(OR(D39="",E39=""),"",IF(IFERROR(INDEX(RecEstado,MATCH(D39,ListaRecetas,0)),"")<>"OK","",IFERROR(E39*INDEX(RecCostoU,MATCH(D39,ListaRecetas,0)),""))) | H39: =IF(G39="",0,IFERROR(INDEX(InsCosto,MATCH(G39,ListaInsumos,0))*1,0)) -> 0 | J39: =IF(I39="",0,IFERROR(INDEX(InsCosto,MATCH(I39,ListaInsumos,0))*1,0)) -> 0 | K39: =IF(F39="","",(F39+H39+J39)*CFG_Indirectos) | L39: =IF(F39="","",F39+H39+J39+K39) | N39: =IF(OR(L39="",L39=0,M39="",M39>=1),"",IF(CFG_Redondeo>0,CEILING(L39/(1-M39),CFG_Redondeo),L39/(1-M39))) | P39: =IF(OR(L39="",O39=""),"",O39-L39) | Q39: =IF(OR(P39="",O39=0),"",P39/O39) | R39: =IF(A39="","",IF(D39="","Falta elegir receta",IF(IFERROR(INDEX(RecEstado,MATCH(D39,ListaRecetas,0)),"Receta no existe")<>"OK","Receta: "&IFERROR(INDEX(RecEstado,MATCH(D39,ListaRecetas,0)),"no existe"),IF(OR(AND(G39<>"",H39=0),AND(I39<>"",J39=0)),"Packaging sin precio","OK"))))
C40: =IF(A40="","",A40&" - "&B40) | F40: =IF(OR(D40="",E40=""),"",IF(IFERROR(INDEX(RecEstado,MATCH(D40,ListaRecetas,0)),"")<>"OK","",IFERROR(E40*INDEX(RecCostoU,MATCH(D40,ListaRecetas,0)),""))) | H40: =IF(G40="",0,IFERROR(INDEX(InsCosto,MATCH(G40,ListaInsumos,0))*1,0)) -> 0 | J40: =IF(I40="",0,IFERROR(INDEX(InsCosto,MATCH(I40,ListaInsumos,0))*1,0)) -> 0 | K40: =IF(F40="","",(F40+H40+J40)*CFG_Indirectos) | L40: =IF(F40="","",F40+H40+J40+K40) | N40: =IF(OR(L40="",L40=0,M40="",M40>=1),"",IF(CFG_Redondeo>0,CEILING(L40/(1-M40),CFG_Redondeo),L40/(1-M40))) | P40: =IF(OR(L40="",O40=""),"",O40-L40) | Q40: =IF(OR(P40="",O40=0),"",P40/O40) | R40: =IF(A40="","",IF(D40="","Falta elegir receta",IF(IFERROR(INDEX(RecEstado,MATCH(D40,ListaRecetas,0)),"Receta no existe")<>"OK","Receta: "&IFERROR(INDEX(RecEstado,MATCH(D40,ListaRecetas,0)),"no existe"),IF(OR(AND(G40<>"",H40=0),AND(I40<>"",J40=0)),"Packaging sin precio","OK"))))
C41: =IF(A41="","",A41&" - "&B41) | F41: =IF(OR(D41="",E41=""),"",IF(IFERROR(INDEX(RecEstado,MATCH(D41,ListaRecetas,0)),"")<>"OK","",IFERROR(E41*INDEX(RecCostoU,MATCH(D41,ListaRecetas,0)),""))) | H41: =IF(G41="",0,IFERROR(INDEX(InsCosto,MATCH(G41,ListaInsumos,0))*1,0)) -> 0 | J41: =IF(I41="",0,IFERROR(INDEX(InsCosto,MATCH(I41,ListaInsumos,0))*1,0)) -> 0 | K41: =IF(F41="","",(F41+H41+J41)*CFG_Indirectos) | L41: =IF(F41="","",F41+H41+J41+K41) | N41: =IF(OR(L41="",L41=0,M41="",M41>=1),"",IF(CFG_Redondeo>0,CEILING(L41/(1-M41),CFG_Redondeo),L41/(1-M41))) | P41: =IF(OR(L41="",O41=""),"",O41-L41) | Q41: =IF(OR(P41="",O41=0),"",P41/O41) | R41: =IF(A41="","",IF(D41="","Falta elegir receta",IF(IFERROR(INDEX(RecEstado,MATCH(D41,ListaRecetas,0)),"Receta no existe")<>"OK","Receta: "&IFERROR(INDEX(RecEstado,MATCH(D41,ListaRecetas,0)),"no existe"),IF(OR(AND(G41<>"",H41=0),AND(I41<>"",J41=0)),"Packaging sin precio","OK"))))
C42: =IF(A42="","",A42&" - "&B42) | F42: =IF(OR(D42="",E42=""),"",IF(IFERROR(INDEX(RecEstado,MATCH(D42,ListaRecetas,0)),"")<>"OK","",IFERROR(E42*INDEX(RecCostoU,MATCH(D42,ListaRecetas,0)),""))) | H42: =IF(G42="",0,IFERROR(INDEX(InsCosto,MATCH(G42,ListaInsumos,0))*1,0)) -> 0 | J42: =IF(I42="",0,IFERROR(INDEX(InsCosto,MATCH(I42,ListaInsumos,0))*1,0)) -> 0 | K42: =IF(F42="","",(F42+H42+J42)*CFG_Indirectos) | L42: =IF(F42="","",F42+H42+J42+K42) | N42: =IF(OR(L42="",L42=0,M42="",M42>=1),"",IF(CFG_Redondeo>0,CEILING(L42/(1-M42),CFG_Redondeo),L42/(1-M42))) | P42: =IF(OR(L42="",O42=""),"",O42-L42) | Q42: =IF(OR(P42="",O42=0),"",P42/O42) | R42: =IF(A42="","",IF(D42="","Falta elegir receta",IF(IFERROR(INDEX(RecEstado,MATCH(D42,ListaRecetas,0)),"Receta no existe")<>"OK","Receta: "&IFERROR(INDEX(RecEstado,MATCH(D42,ListaRecetas,0)),"no existe"),IF(OR(AND(G42<>"",H42=0),AND(I42<>"",J42=0)),"Packaging sin precio","OK"))))
C43: =IF(A43="","",A43&" - "&B43) | F43: =IF(OR(D43="",E43=""),"",IF(IFERROR(INDEX(RecEstado,MATCH(D43,ListaRecetas,0)),"")<>"OK","",IFERROR(E43*INDEX(RecCostoU,MATCH(D43,ListaRecetas,0)),""))) | H43: =IF(G43="",0,IFERROR(INDEX(InsCosto,MATCH(G43,ListaInsumos,0))*1,0)) -> 0 | J43: =IF(I43="",0,IFERROR(INDEX(InsCosto,MATCH(I43,ListaInsumos,0))*1,0)) -> 0 | K43: =IF(F43="","",(F43+H43+J43)*CFG_Indirectos) | L43: =IF(F43="","",F43+H43+J43+K43) | N43: =IF(OR(L43="",L43=0,M43="",M43>=1),"",IF(CFG_Redondeo>0,CEILING(L43/(1-M43),CFG_Redondeo),L43/(1-M43))) | P43: =IF(OR(L43="",O43=""),"",O43-L43) | Q43: =IF(OR(P43="",O43=0),"",P43/O43) | R43: =IF(A43="","",IF(D43="","Falta elegir receta",IF(IFERROR(INDEX(RecEstado,MATCH(D43,ListaRecetas,0)),"Receta no existe")<>"OK","Receta: "&IFERROR(INDEX(RecEstado,MATCH(D43,ListaRecetas,0)),"no existe"),IF(OR(AND(G43<>"",H43=0),AND(I43<>"",J43=0)),"Packaging sin precio","OK"))))
C44: =IF(A44="","",A44&" - "&B44) | F44: =IF(OR(D44="",E44=""),"",IF(IFERROR(INDEX(RecEstado,MATCH(D44,ListaRecetas,0)),"")<>"OK","",IFERROR(E44*INDEX(RecCostoU,MATCH(D44,ListaRecetas,0)),""))) | H44: =IF(G44="",0,IFERROR(INDEX(InsCosto,MATCH(G44,ListaInsumos,0))*1,0)) -> 0 | J44: =IF(I44="",0,IFERROR(INDEX(InsCosto,MATCH(I44,ListaInsumos,0))*1,0)) -> 0 | K44: =IF(F44="","",(F44+H44+J44)*CFG_Indirectos) | L44: =IF(F44="","",F44+H44+J44+K44) | N44: =IF(OR(L44="",L44=0,M44="",M44>=1),"",IF(CFG_Redondeo>0,CEILING(L44/(1-M44),CFG_Redondeo),L44/(1-M44))) | P44: =IF(OR(L44="",O44=""),"",O44-L44) | Q44: =IF(OR(P44="",O44=0),"",P44/O44) | R44: =IF(A44="","",IF(D44="","Falta elegir receta",IF(IFERROR(INDEX(RecEstado,MATCH(D44,ListaRecetas,0)),"Receta no existe")<>"OK","Receta: "&IFERROR(INDEX(RecEstado,MATCH(D44,ListaRecetas,0)),"no existe"),IF(OR(AND(G44<>"",H44=0),AND(I44<>"",J44=0)),"Packaging sin precio","OK"))))
C45: =IF(A45="","",A45&" - "&B45) | F45: =IF(OR(D45="",E45=""),"",IF(IFERROR(INDEX(RecEstado,MATCH(D45,ListaRecetas,0)),"")<>"OK","",IFERROR(E45*INDEX(RecCostoU,MATCH(D45,ListaRecetas,0)),""))) | H45: =IF(G45="",0,IFERROR(INDEX(InsCosto,MATCH(G45,ListaInsumos,0))*1,0)) -> 0 | J45: =IF(I45="",0,IFERROR(INDEX(InsCosto,MATCH(I45,ListaInsumos,0))*1,0)) -> 0 | K45: =IF(F45="","",(F45+H45+J45)*CFG_Indirectos) | L45: =IF(F45="","",F45+H45+J45+K45) | N45: =IF(OR(L45="",L45=0,M45="",M45>=1),"",IF(CFG_Redondeo>0,CEILING(L45/(1-M45),CFG_Redondeo),L45/(1-M45))) | P45: =IF(OR(L45="",O45=""),"",O45-L45) | Q45: =IF(OR(P45="",O45=0),"",P45/O45) | R45: =IF(A45="","",IF(D45="","Falta elegir receta",IF(IFERROR(INDEX(RecEstado,MATCH(D45,ListaRecetas,0)),"Receta no existe")<>"OK","Receta: "&IFERROR(INDEX(RecEstado,MATCH(D45,ListaRecetas,0)),"no existe"),IF(OR(AND(G45<>"",H45=0),AND(I45<>"",J45=0)),"Packaging sin precio","OK"))))
... C150: =IF(A150="","",A150&" - "&B150) | F150: =IF(OR(D150="",E150=""),"",IF(IFERROR(INDEX(RecEstado,MATCH(D150,ListaRecetas,0)),"")<>"OK","",IFERROR(E150*INDEX(RecCostoU,MATCH(D150,ListaRecetas,0)),""))) | H150: =IF(G150="",0,IFERROR(INDEX(InsCosto,MATCH(G150,ListaInsumos,0))*1,0)) -> 0 | J150: =IF(I150="",0,IFERROR(INDEX(InsCosto,MATCH(I150,ListaInsumos,0))*1,0)) -> 0 | K150: =IF(F150="","",(F150+H150+J150)*CFG_Indirectos) | L150: =IF(F150="","",F150+H150+J150+K150) | N150: =IF(OR(L150="",L150=0,M150="",M150>=1),"",IF(CFG_Redondeo>0,CEILING(L150/(1-M150),CFG_Redondeo),L150/(1-M150))) | P150: =IF(OR(L150="",O150=""),"",O150-L150) | Q150: =IF(OR(P150="",O150=0),"",P150/O150) | R150: =IF(A150="","",IF(D150="","Falta elegir receta",IF(IFERROR(INDEX(RecEstado,MATCH(D150,ListaRecetas,0)),"Receta no existe")<>"OK","Receta: "&IFERROR(INDEX(RecEstado,MATCH(D150,ListaRecetas,0)),"no existe"),IF(OR(AND(G150<>"",H150=0),AND(I150<>"",J150=0)),"Packaging sin precio","OK"))))

Sheet Combos
A1: Combos y promos
A2: A la izquierda, qué productos lleva cada combo. A la derecha, el resumen: costo, precio y cuánto descuento estás haciendo.
A4: Combo | B4: Producto (de la hoja Precios) | C4: Cantidad | D4: Costo unitario ($) | E4: Costo ($) | F4: Precio suelto ($) | H4: Combo | I4: Costo productos ($) | J4: Extras: juguete, caja, etc. ($) | K4: COSTO TOTAL ($) | L4: Precio del combo ($) | M4: Ganancia ($) | N4: Margen real | O4: Precio si se compra suelto ($) | P4: Descuento vs. suelto | Q4: Estado
A5: Combo Degustación | B5: Cookies Chips de Chocolate - Individual 70 g | C5: 1 | D5: =IF(B5="","",IFERROR(INDEX(ProdCosto,MATCH(B5,ListaProductos,0))*1,"")) | E5: =IF(OR(B5="",D5=""),"",C5*D5) | F5: =IF(B5="","",C5*IFERROR(INDEX(ProdPrecio,MATCH(B5,ListaProductos,0))*1,0)) -> 4000 | H5: Combo Degustación | I5: =IF(OR(H5="",Q5<>"OK"),"",SUMIFS($E$5:$E$200,$A$5:$A$200,H5)) | K5: =IF(I5="","",I5+J5) | L5: 29800 | M5: =IF(OR(K5="",L5=""),"",L5-K5) | N5: =IF(OR(M5="",L5=0),"",M5/L5) | O5: =IF(H5="","",SUMIFS($F$5:$F$200,$A$5:$A$200,H5)) -> 31500 | P5: =IF(OR(O5="",O5=0,L5=""),"",1-L5/O5) -> 0.053968254 | Q5: =IF(H5="","",IF(COUNTIFS($A$5:$A$200,H5)=0,"Sin productos cargados",IF(COUNTIFS($A$5:$A$200,H5)-COUNTIFS($A$5:$A$200,H5,$E$5:$E$200,">=0")>0,"Faltan costos de "&(COUNTIFS($A$5:$A$200,H5)-COUNTIFS($A$5:$A$200,H5,$E$5:$E$200,">=0"))&" producto(s)","OK"))) -> Faltan costos de 10 producto(s)
A6: Combo Degustación | B6: Bastoncitos de Zanahoria y Remolacha - Individual 50 g | C6: 1 | D6: =IF(B6="","",IFERROR(INDEX(ProdCosto,MATCH(B6,ListaProductos,0))*1,"")) | E6: =IF(OR(B6="",D6=""),"",C6*D6) | F6: =IF(B6="","",C6*IFERROR(INDEX(ProdPrecio,MATCH(B6,ListaProductos,0))*1,0)) -> 3000 | H6: Recreos Saludables (5 snacks + juguete) | I6: =IF(OR(H6="",Q6<>"OK"),"",SUMIFS($E$5:$E$200,$A$5:$A$200,H6)) | K6: =IF(I6="","",I6+J6) | L6: 15000 | M6: =IF(OR(K6="",L6=""),"",L6-K6) | N6: =IF(OR(M6="",L6=0),"",M6/L6) | O6: =IF(H6="","",SUMIFS($F$5:$F$200,$A$5:$A$200,H6)) -> 13000 | P6: =IF(OR(O6="",O6=0,L6=""),"",1-L6/O6) -> -0.15384615 | Q6: =IF(H6="","",IF(COUNTIFS($A$5:$A$200,H6)=0,"Sin productos cargados",IF(COUNTIFS($A$5:$A$200,H6)-COUNTIFS($A$5:$A$200,H6,$E$5:$E$200,">=0")>0,"Faltan costos de "&(COUNTIFS($A$5:$A$200,H6)-COUNTIFS($A$5:$A$200,H6,$E$5:$E$200,">=0"))&" producto(s)","OK"))) -> Faltan costos de 5 producto(s)
A7: Combo Degustación | B7: Rueditas de Naranja y Chocolate - Individual 75 g | C7: 1 | D7: =IF(B7="","",IFERROR(INDEX(ProdCosto,MATCH(B7,ListaProductos,0))*1,"")) | E7: =IF(OR(B7="",D7=""),"",C7*D7) | F7: =IF(B7="","",C7*IFERROR(INDEX(ProdPrecio,MATCH(B7,ListaProductos,0))*1,0)) -> 4000 | I7: =IF(OR(H7="",Q7<>"OK"),"",SUMIFS($E$5:$E$200,$A$5:$A$200,H7)) | K7: =IF(I7="","",I7+J7) | M7: =IF(OR(K7="",L7=""),"",L7-K7) | N7: =IF(OR(M7="",L7=0),"",M7/L7) | O7: =IF(H7="","",SUMIFS($F$5:$F$200,$A$5:$A$200,H7)) | P7: =IF(OR(O7="",O7=0,L7=""),"",1-L7/O7) | Q7: =IF(H7="","",IF(COUNTIFS($A$5:$A$200,H7)=0,"Sin productos cargados",IF(COUNTIFS($A$5:$A$200,H7)-COUNTIFS($A$5:$A$200,H7,$E$5:$E$200,">=0")>0,"Faltan costos de "&(COUNTIFS($A$5:$A$200,H7)-COUNTIFS($A$5:$A$200,H7,$E$5:$E$200,">=0"))&" producto(s)","OK")))
A8: Combo Degustación | B8: Tablitas de Trigo Sarraceno y Semillas - Individual 70 g | C8: 1 | D8: =IF(B8="","",IFERROR(INDEX(ProdCosto,MATCH(B8,ListaProductos,0))*1,"")) | E8: =IF(OR(B8="",D8=""),"",C8*D8) | F8: =IF(B8="","",C8*IFERROR(INDEX(ProdPrecio,MATCH(B8,ListaProductos,0))*1,0)) -> 2500 | I8: =IF(OR(H8="",Q8<>"OK"),"",SUMIFS($E$5:$E$200,$A$5:$A$200,H8)) | K8: =IF(I8="","",I8+J8) | M8: =IF(OR(K8="",L8=""),"",L8-K8) | N8: =IF(OR(M8="",L8=0),"",M8/L8) | O8: =IF(H8="","",SUMIFS($F$5:$F$200,$A$5:$A$200,H8)) | P8: =IF(OR(O8="",O8=0,L8=""),"",1-L8/O8) | Q8: =IF(H8="","",IF(COUNTIFS($A$5:$A$200,H8)=0,"Sin productos cargados",IF(COUNTIFS($A$5:$A$200,H8)-COUNTIFS($A$5:$A$200,H8,$E$5:$E$200,">=0")>0,"Faltan costos de "&(COUNTIFS($A$5:$A$200,H8)-COUNTIFS($A$5:$A$200,H8,$E$5:$E$200,">=0"))&" producto(s)","OK")))
A9: Combo Degustación | B9: Galletas Marineras - Individual 70 g | C9: 1 | D9: =IF(B9="","",IFERROR(INDEX(ProdCosto,MATCH(B9,ListaProductos,0))*1,"")) -> 669.125 | E9: =IF(OR(B9="",D9=""),"",C9*D9) -> 669.125 | F9: =IF(B9="","",C9*IFERROR(INDEX(ProdPrecio,MATCH(B9,ListaProductos,0))*1,0)) -> 2500 | I9: =IF(OR(H9="",Q9<>"OK"),"",SUMIFS($E$5:$E$200,$A$5:$A$200,H9)) | K9: =IF(I9="","",I9+J9) | M9: =IF(OR(K9="",L9=""),"",L9-K9) | N9: =IF(OR(M9="",L9=0),"",M9/L9) | O9: =IF(H9="","",SUMIFS($F$5:$F$200,$A$5:$A$200,H9)) | P9: =IF(OR(O9="",O9=0,L9=""),"",1-L9/O9) | Q9: =IF(H9="","",IF(COUNTIFS($A$5:$A$200,H9)=0,"Sin productos cargados",IF(COUNTIFS($A$5:$A$200,H9)-COUNTIFS($A$5:$A$200,H9,$E$5:$E$200,">=0")>0,"Faltan costos de "&(COUNTIFS($A$5:$A$200,H9)-COUNTIFS($A$5:$A$200,H9,$E$5:$E$200,">=0"))&" producto(s)","OK")))
A10: Combo Degustación | B10: Crakers de Mijo y Cebolla - Individual 50 g | C10: 1 | D10: =IF(B10="","",IFERROR(INDEX(ProdCosto,MATCH(B10,ListaProductos,0))*1,"")) | E10: =IF(OR(B10="",D10=""),"",C10*D10) | F10: =IF(B10="","",C10*IFERROR(INDEX(ProdPrecio,MATCH(B10,ListaProductos,0))*1,0)) -> 2500 | I10: =IF(OR(H10="",Q10<>"OK"),"",SUMIFS($E$5:$E$200,$A$5:$A$200,H10)) | K10: =IF(I10="","",I10+J10) | M10: =IF(OR(K10="",L10=""),"",L10-K10) | N10: =IF(OR(M10="",L10=0),"",M10/L10) | O10: =IF(H10="","",SUMIFS($F$5:$F$200,$A$5:$A$200,H10)) | P10: =IF(OR(O10="",O10=0,L10=""),"",1-L10/O10) | Q10: =IF(H10="","",IF(COUNTIFS($A$5:$A$200,H10)=0,"Sin productos cargados",IF(COUNTIFS($A$5:$A$200,H10)-COUNTIFS($A$5:$A$200,H10,$E$5:$E$200,">=0")>0,"Faltan costos de "&(COUNTIFS($A$5:$A$200,H10)-COUNTIFS($A$5:$A$200,H10,$E$5:$E$200,">=0"))&" producto(s)","OK")))
A11: Combo Degustación | B11: Palitos de Batata y Romero - Individual 50 g | C11: 1 | D11: =IF(B11="","",IFERROR(INDEX(ProdCosto,MATCH(B11,ListaProductos,0))*1,"")) | E11: =IF(OR(B11="",D11=""),"",C11*D11) | F11: =IF(B11="","",C11*IFERROR(INDEX(ProdPrecio,MATCH(B11,ListaProductos,0))*1,0)) -> 3000 | I11: =IF(OR(H11="",Q11<>"OK"),"",SUMIFS($E$5:$E$200,$A$5:$A$200,H11)) | K11: =IF(I11="","",I11+J11) | M11: =IF(OR(K11="",L11=""),"",L11-K11) | N11: =IF(OR(M11="",L11=0),"",M11/L11) | O11: =IF(H11="","",SUMIFS($F$5:$F$200,$A$5:$A$200,H11)) | P11: =IF(OR(O11="",O11=0,L11=""),"",1-L11/O11) | Q11: =IF(H11="","",IF(COUNTIFS($A$5:$A$200,H11)=0,"Sin productos cargados",IF(COUNTIFS($A$5:$A$200,H11)-COUNTIFS($A$5:$A$200,H11,$E$5:$E$200,">=0")>0,"Faltan costos de "&(COUNTIFS($A$5:$A$200,H11)-COUNTIFS($A$5:$A$200,H11,$E$5:$E$200,">=0"))&" producto(s)","OK")))
A12: Combo Degustación | B12: Triangulitos de Lentejas Turcas - Individual 50 g | C12: 1 | D12: =IF(B12="","",IFERROR(INDEX(ProdCosto,MATCH(B12,ListaProductos,0))*1,"")) | E12: =IF(OR(B12="",D12=""),"",C12*D12) | F12: =IF(B12="","",C12*IFERROR(INDEX(ProdPrecio,MATCH(B12,ListaProductos,0))*1,0)) -> 2500 | I12: =IF(OR(H12="",Q12<>"OK"),"",SUMIFS($E$5:$E$200,$A$5:$A$200,H12)) | K12: =IF(I12="","",I12+J12) | M12: =IF(OR(K12="",L12=""),"",L12-K12) | N12: =IF(OR(M12="",L12=0),"",M12/L12) | O12: =IF(H12="","",SUMIFS($F$5:$F$200,$A$5:$A$200,H12)) | P12: =IF(OR(O12="",O12=0,L12=""),"",1-L12/O12) | Q12: =IF(H12="","",IF(COUNTIFS($A$5:$A$200,H12)=0,"Sin productos cargados",IF(COUNTIFS($A$5:$A$200,H12)-COUNTIFS($A$5:$A$200,H12,$E$5:$E$200,">=0")>0,"Faltan costos de "&(COUNTIFS($A$5:$A$200,H12)-COUNTIFS($A$5:$A$200,H12,$E$5:$E$200,">=0"))&" producto(s)","OK")))
A13: Combo Degustación | B13: Papas al Orégano - Individual 50 g | C13: 1 | D13: =IF(B13="","",IFERROR(INDEX(ProdCosto,MATCH(B13,ListaProductos,0))*1,"")) | E13: =IF(OR(B13="",D13=""),"",C13*D13) | F13: =IF(B13="","",C13*IFERROR(INDEX(ProdPrecio,MATCH(B13,ListaProductos,0))*1,0)) -> 2500 | I13: =IF(OR(H13="",Q13<>"OK"),"",SUMIFS($E$5:$E$200,$A$5:$A$200,H13)) | K13: =IF(I13="","",I13+J13) | M13: =IF(OR(K13="",L13=""),"",L13-K13) | N13: =IF(OR(M13="",L13=0),"",M13/L13) | O13: =IF(H13="","",SUMIFS($F$5:$F$200,$A$5:$A$200,H13)) | P13: =IF(OR(O13="",O13=0,L13=""),"",1-L13/O13) | Q13: =IF(H13="","",IF(COUNTIFS($A$5:$A$200,H13)=0,"Sin productos cargados",IF(COUNTIFS($A$5:$A$200,H13)-COUNTIFS($A$5:$A$200,H13,$E$5:$E$200,">=0")>0,"Faltan costos de "&(COUNTIFS($A$5:$A$200,H13)-COUNTIFS($A$5:$A$200,H13,$E$5:$E$200,">=0"))&" producto(s)","OK")))
A14: Combo Degustación | B14: Garbancitos Crocantes - Individual 50 g | C14: 1 | D14: =IF(B14="","",IFERROR(INDEX(ProdCosto,MATCH(B14,ListaProductos,0))*1,"")) | E14: =IF(OR(B14="",D14=""),"",C14*D14) | F14: =IF(B14="","",C14*IFERROR(INDEX(ProdPrecio,MATCH(B14,ListaProductos,0))*1,0)) -> 2500 | I14: =IF(OR(H14="",Q14<>"OK"),"",SUMIFS($E$5:$E$200,$A$5:$A$200,H14)) | K14: =IF(I14="","",I14+J14) | M14: =IF(OR(K14="",L14=""),"",L14-K14) | N14: =IF(OR(M14="",L14=0),"",M14/L14) | O14: =IF(H14="","",SUMIFS($F$5:$F$200,$A$5:$A$200,H14)) | P14: =IF(OR(O14="",O14=0,L14=""),"",1-L14/O14) | Q14: =IF(H14="","",IF(COUNTIFS($A$5:$A$200,H14)=0,"Sin productos cargados",IF(COUNTIFS($A$5:$A$200,H14)-COUNTIFS($A$5:$A$200,H14,$E$5:$E$200,">=0")>0,"Faltan costos de "&(COUNTIFS($A$5:$A$200,H14)-COUNTIFS($A$5:$A$200,H14,$E$5:$E$200,">=0"))&" producto(s)","OK")))
A15: Combo Degustación | B15: Grisines a la Provenzal - Individual 50 g | C15: 1 | D15: =IF(B15="","",IFERROR(INDEX(ProdCosto,MATCH(B15,ListaProductos,0))*1,"")) | E15: =IF(OR(B15="",D15=""),"",C15*D15) | F15: =IF(B15="","",C15*IFERROR(INDEX(ProdPrecio,MATCH(B15,ListaProductos,0))*1,0)) -> 2500 | I15: =IF(OR(H15="",Q15<>"OK"),"",SUMIFS($E$5:$E$200,$A$5:$A$200,H15)) | K15: =IF(I15="","",I15+J15) | M15: =IF(OR(K15="",L15=""),"",L15-K15) | N15: =IF(OR(M15="",L15=0),"",M15/L15) | O15: =IF(H15="","",SUMIFS($F$5:$F$200,$A$5:$A$200,H15)) | P15: =IF(OR(O15="",O15=0,L15=""),"",1-L15/O15) | Q15: =IF(H15="","",IF(COUNTIFS($A$5:$A$200,H15)=0,"Sin productos cargados",IF(COUNTIFS($A$5:$A$200,H15)-COUNTIFS($A$5:$A$200,H15,$E$5:$E$200,">=0")>0,"Faltan costos de "&(COUNTIFS($A$5:$A$200,H15)-COUNTIFS($A$5:$A$200,H15,$E$5:$E$200,">=0"))&" producto(s)","OK")))
A16: Recreos Saludables (5 snacks + juguete) | B16: Crakers de Mijo y Cebolla - Individual 50 g | C16: 1 | D16: =IF(B16="","",IFERROR(INDEX(ProdCosto,MATCH(B16,ListaProductos,0))*1,"")) | E16: =IF(OR(B16="",D16=""),"",C16*D16) | F16: =IF(B16="","",C16*IFERROR(INDEX(ProdPrecio,MATCH(B16,ListaProductos,0))*1,0)) -> 2500 | I16: =IF(OR(H16="",Q16<>"OK"),"",SUMIFS($E$5:$E$200,$A$5:$A$200,H16)) | K16: =IF(I16="","",I16+J16) | M16: =IF(OR(K16="",L16=""),"",L16-K16) | N16: =IF(OR(M16="",L16=0),"",M16/L16) | O16: =IF(H16="","",SUMIFS($F$5:$F$200,$A$5:$A$200,H16)) | P16: =IF(OR(O16="",O16=0,L16=""),"",1-L16/O16) | Q16: =IF(H16="","",IF(COUNTIFS($A$5:$A$200,H16)=0,"Sin productos cargados",IF(COUNTIFS($A$5:$A$200,H16)-COUNTIFS($A$5:$A$200,H16,$E$5:$E$200,">=0")>0,"Faltan costos de "&(COUNTIFS($A$5:$A$200,H16)-COUNTIFS($A$5:$A$200,H16,$E$5:$E$200,">=0"))&" producto(s)","OK")))
A17: Recreos Saludables (5 snacks + juguete) | B17: Triangulitos de Lentejas Turcas - Individual 50 g | C17: 1 | D17: =IF(B17="","",IFERROR(INDEX(ProdCosto,MATCH(B17,ListaProductos,0))*1,"")) | E17: =IF(OR(B17="",D17=""),"",C17*D17) | F17: =IF(B17="","",C17*IFERROR(INDEX(ProdPrecio,MATCH(B17,ListaProductos,0))*1,0)) -> 2500 | I17: =IF(OR(H17="",Q17<>"OK"),"",SUMIFS($E$5:$E$200,$A$5:$A$200,H17)) | K17: =IF(I17="","",I17+J17) | M17: =IF(OR(K17="",L17=""),"",L17-K17) | N17: =IF(OR(M17="",L17=0),"",M17/L17) | O17: =IF(H17="","",SUMIFS($F$5:$F$200,$A$5:$A$200,H17)) | P17: =IF(OR(O17="",O17=0,L17=""),"",1-L17/O17) | Q17: =IF(H17="","",IF(COUNTIFS($A$5:$A$200,H17)=0,"Sin productos cargados",IF(COUNTIFS($A$5:$A$200,H17)-COUNTIFS($A$5:$A$200,H17,$E$5:$E$200,">=0")>0,"Faltan costos de "&(COUNTIFS($A$5:$A$200,H17)-COUNTIFS($A$5:$A$200,H17,$E$5:$E$200,">=0"))&" producto(s)","OK")))
A18: Recreos Saludables (5 snacks + juguete) | B18: Garbancitos Crocantes - Individual 50 g | C18: 1 | D18: =IF(B18="","",IFERROR(INDEX(ProdCosto,MATCH(B18,ListaProductos,0))*1,"")) | E18: =IF(OR(B18="",D18=""),"",C18*D18) | F18: =IF(B18="","",C18*IFERROR(INDEX(ProdPrecio,MATCH(B18,ListaProductos,0))*1,0)) -> 2500 | I18: =IF(OR(H18="",Q18<>"OK"),"",SUMIFS($E$5:$E$200,$A$5:$A$200,H18)) | K18: =IF(I18="","",I18+J18) | M18: =IF(OR(K18="",L18=""),"",L18-K18) | N18: =IF(OR(M18="",L18=0),"",M18/L18) | O18: =IF(H18="","",SUMIFS($F$5:$F$200,$A$5:$A$200,H18)) | P18: =IF(OR(O18="",O18=0,L18=""),"",1-L18/O18) | Q18: =IF(H18="","",IF(COUNTIFS($A$5:$A$200,H18)=0,"Sin productos cargados",IF(COUNTIFS($A$5:$A$200,H18)-COUNTIFS($A$5:$A$200,H18,$E$5:$E$200,">=0")>0,"Faltan costos de "&(COUNTIFS($A$5:$A$200,H18)-COUNTIFS($A$5:$A$200,H18,$E$5:$E$200,">=0"))&" producto(s)","OK")))
A19: Recreos Saludables (5 snacks + juguete) | B19: Papas al Orégano - Individual 50 g | C19: 1 | D19: =IF(B19="","",IFERROR(INDEX(ProdCosto,MATCH(B19,ListaProductos,0))*1,"")) | E19: =IF(OR(B19="",D19=""),"",C19*D19) | F19: =IF(B19="","",C19*IFERROR(INDEX(ProdPrecio,MATCH(B19,ListaProductos,0))*1,0)) -> 2500 | I19: =IF(OR(H19="",Q19<>"OK"),"",SUMIFS($E$5:$E$200,$A$5:$A$200,H19)) | K19: =IF(I19="","",I19+J19) | M19: =IF(OR(K19="",L19=""),"",L19-K19) | N19: =IF(OR(M19="",L19=0),"",M19/L19) | O19: =IF(H19="","",SUMIFS($F$5:$F$200,$A$5:$A$200,H19)) | P19: =IF(OR(O19="",O19=0,L19=""),"",1-L19/O19) | Q19: =IF(H19="","",IF(COUNTIFS($A$5:$A$200,H19)=0,"Sin productos cargados",IF(COUNTIFS($A$5:$A$200,H19)-COUNTIFS($A$5:$A$200,H19,$E$5:$E$200,">=0")>0,"Faltan costos de "&(COUNTIFS($A$5:$A$200,H19)-COUNTIFS($A$5:$A$200,H19,$E$5:$E$200,">=0"))&" producto(s)","OK")))
A20: Recreos Saludables (5 snacks + juguete) | B20: Bastoncitos de Zanahoria y Remolacha - Individual 50 g | C20: 1 | D20: =IF(B20="","",IFERROR(INDEX(ProdCosto,MATCH(B20,ListaProductos,0))*1,"")) | E20: =IF(OR(B20="",D20=""),"",C20*D20) | F20: =IF(B20="","",C20*IFERROR(INDEX(ProdPrecio,MATCH(B20,ListaProductos,0))*1,0)) -> 3000
D21: =IF(B21="","",IFERROR(INDEX(ProdCosto,MATCH(B21,ListaProductos,0))*1,"")) | E21: =IF(OR(B21="",D21=""),"",C21*D21) | F21: =IF(B21="","",C21*IFERROR(INDEX(ProdPrecio,MATCH(B21,ListaProductos,0))*1,0))
D22: =IF(B22="","",IFERROR(INDEX(ProdCosto,MATCH(B22,ListaProductos,0))*1,"")) | E22: =IF(OR(B22="",D22=""),"",C22*D22) | F22: =IF(B22="","",C22*IFERROR(INDEX(ProdPrecio,MATCH(B22,ListaProductos,0))*1,0))
D23: =IF(B23="","",IFERROR(INDEX(ProdCosto,MATCH(B23,ListaProductos,0))*1,"")) | E23: =IF(OR(B23="",D23=""),"",C23*D23) | F23: =IF(B23="","",C23*IFERROR(INDEX(ProdPrecio,MATCH(B23,ListaProductos,0))*1,0))
D24: =IF(B24="","",IFERROR(INDEX(ProdCosto,MATCH(B24,ListaProductos,0))*1,"")) | E24: =IF(OR(B24="",D24=""),"",C24*D24) | F24: =IF(B24="","",C24*IFERROR(INDEX(ProdPrecio,MATCH(B24,ListaProductos,0))*1,0))
D25: =IF(B25="","",IFERROR(INDEX(ProdCosto,MATCH(B25,ListaProductos,0))*1,"")) | E25: =IF(OR(B25="",D25=""),"",C25*D25) | F25: =IF(B25="","",C25*IFERROR(INDEX(ProdPrecio,MATCH(B25,ListaProductos,0))*1,0))
D26: =IF(B26="","",IFERROR(INDEX(ProdCosto,MATCH(B26,ListaProductos,0))*1,"")) | E26: =IF(OR(B26="",D26=""),"",C26*D26) | F26: =IF(B26="","",C26*IFERROR(INDEX(ProdPrecio,MATCH(B26,ListaProductos,0))*1,0))
D27: =IF(B27="","",IFERROR(INDEX(ProdCosto,MATCH(B27,ListaProductos,0))*1,"")) | E27: =IF(OR(B27="",D27=""),"",C27*D27) | F27: =IF(B27="","",C27*IFERROR(INDEX(ProdPrecio,MATCH(B27,ListaProductos,0))*1,0))
D28: =IF(B28="","",IFERROR(INDEX(ProdCosto,MATCH(B28,ListaProductos,0))*1,"")) | E28: =IF(OR(B28="",D28=""),"",C28*D28) | F28: =IF(B28="","",C28*IFERROR(INDEX(ProdPrecio,MATCH(B28,ListaProductos,0))*1,0))
D29: =IF(B29="","",IFERROR(INDEX(ProdCosto,MATCH(B29,ListaProductos,0))*1,"")) | E29: =IF(OR(B29="",D29=""),"",C29*D29) | F29: =IF(B29="","",C29*IFERROR(INDEX(ProdPrecio,MATCH(B29,ListaProductos,0))*1,0))
D30: =IF(B30="","",IFERROR(INDEX(ProdCosto,MATCH(B30,ListaProductos,0))*1,"")) | E30: =IF(OR(B30="",D30=""),"",C30*D30) | F30: =IF(B30="","",C30*IFERROR(INDEX(ProdPrecio,MATCH(B30,ListaProductos,0))*1,0))
D31: =IF(B31="","",IFERROR(INDEX(ProdCosto,MATCH(B31,ListaProductos,0))*1,"")) | E31: =IF(OR(B31="",D31=""),"",C31*D31) | F31: =IF(B31="","",C31*IFERROR(INDEX(ProdPrecio,MATCH(B31,ListaProductos,0))*1,0))
D32: =IF(B32="","",IFERROR(INDEX(ProdCosto,MATCH(B32,ListaProductos,0))*1,"")) | E32: =IF(OR(B32="",D32=""),"",C32*D32) | F32: =IF(B32="","",C32*IFERROR(INDEX(ProdPrecio,MATCH(B32,ListaProductos,0))*1,0))
... D200: =IF(B200="","",IFERROR(INDEX(ProdCosto,MATCH(B200,ListaProductos,0))*1,"")) | E200: =IF(OR(B200="",D200=""),"",C200*D200) | F200: =IF(B200="","",C200*IFERROR(INDEX(ProdPrecio,MATCH(B200,ListaProductos,0))*1,0))

Sheet Configuración
A1: Configuración general
A2: Parámetros que usan todas las hojas. Cambiá las celdas amarillas.
A4: Parámetro | B4: Valor | C4: Explicación
A5: Método para valuar insumos | B5: Último precio | C5: "Último precio" usa la compra más reciente de cada insumo (recomendado con inflación). "Promedio" usa el promedio ponderado de todas las compras.
A6: Margen de ganancia deseado (sobre precio de venta) | B6: 0.6 | C6: Supuesto inicial: 60% (equivale a vender a 2,5 veces el costo). Ajustalo a tu criterio. Se puede cambiar producto por producto en la hoja Precios.
A7: Gastos indirectos (% sobre costo directo) | B7: 0.25 | C7: Supuesto inicial: 25%. Cubre gas, luz, horas de trabajo, limpieza, envíos, comisiones, etc. Se suma al costo de ingredientes + packaging.
A8: Redondear precio sugerido hacia arriba a múltiplos de $ | B8: 100 | C8: Ej.: 100 redondea $1.672 a $1.700. Poné 0 para no redondear.
A11: Tabla de unidades
A12: Convierte la unidad en que comprás o anotás la receta a la unidad base (g, ml o unidad). Podés agregar filas.
A13: Unidad | B13: Equivale a (cantidad) | C13: Unidad base
A14: g | B14: 1 | C14: g
A15: kg | B15: 1000 | C15: g
A16: ml | B16: 1 | C16: ml
A17: cc | B17: 1 | C17: ml
A18: l | B18: 1000 | C18: ml
A19: unidad | B19: 1 | C19: unidad
A20: docena | B20: 12 | C20: unidad
